Workbook
Name SegmentaçãodeDados_DIA: #N/A
Name SegmentaçãodeDados_N1: #N/A

Sheet Resumo
L1: =SUM(L3:L6) -> 2090
I2: ="Volume Passageiros Vai e Vem: "&L1 -> Volume Passageiros Vai e Vem: 2090 | L2: Volume | M2: %
I3: Agend_NOK | J3: Não embarcou no horário ou local agendado | L3: =IFERROR(HLOOKUP(I3,$C$6:$G$7,2,0),0) -> 399 | M3: =L3/L1 -> 0.19090909
I4: Agend_OK | J4: Embarcou no horário e local agendado | L4: =IFERROR(HLOOKUP(I4,$C$6:$G$7,2,0),0) -> 270 | M4: =L4/L1 -> 0.1291866
I5: Encaixe | J5: Embarcou sem agendamento prévio | L5: =IFERROR(HLOOKUP(I5,$C$6:$G$7,2,0),0) -> 364 | M5: =L5/L1 -> 0.17416268
C6: =C9 -> Agend_NOK | D6: =D9 -> Agend_OK | E6: =E9 -> Encaixe | F6: =F9 -> Não Utilizou | G6: =G9 -> Total Geral | I6: Não Utilizou | J6: Agendou Vai e Vem, mas, não embarcou | L6: =IFERROR(HLOOKUP(I6,$C$6:$G$7,2,0),0) -> 1057 | M6: =L6/L1 -> 0.50574163
C7: =SUM(C10:C147) -> 399 | D7: =SUM(D10:D147) -> 270 | E7: =SUM(E10:E147) -> 364 | F7: =SUM(F10:F147) -> 1057 | G7: =SUM(G10:G147) -> 2090
B8: Contagem de NOME | C8: Rótulos de Coluna
B9: Rótulos de Linha | C9: Agend_NOK | D9: Agend_OK | E9: Encaixe | F9: Não Utilizou | G9: Total Geral
B10: Top Service | C10: 14 | D10: 63 | E10: 2 | F10: 165 | G10: 244
B11: IMAGEM EG | C11: 66 | D11: 12 | E11: 3 | F11: 93 | G11: 174
B12: SUPERVISAO EDITORIA RJ | C12: 9 | D12: 3 | E12: 14 | F12: 84 | G12: 110
B13: SUPERVISAO IMAGEM RJ | C13: 32 | D13: 6 | E13: 26 | F13: 59 | G13: 123
B14: MG2 | C14: 55 | D14: 17 | E14: 11 | F14: 47 | G14: 130
B15: IMAGEM ION | C15: 12 | D15: 6 | E15: 1 | F15: 42 | G15: 61
B16: CAPTACAO EVENTOS ION | C16: 7 | D16: 5 | E16: 11 | F16: 40 | G16: 63
B17: IMAGEM JB | C17: 16 | D17: 4 | F17: 28 | G17: 48
B18: SUPERVISAO EDITORIA RJ 03 04 | C18: 3 | D18: 6 | E18: 4 | F18: 24 | G18: 37
B19: PROJETOS DE PRODUCAO E DISTRIBUICAO DE CONTEUDO | C19: 4 | E19: 1 | F19: 20 | G19: 25
B20: TECNOLOGIA PARA SHOWS E EVENTOS | C20: 10 | D20: 4 | E20: 4 | F20: 18 | G20: 36
B21: LET | C21: 5 | D21: 2 | F21: 17 | G21: 24
B22: Randstad | F22: 16 | G22: 16
B23: EDITORIA RJ 03 | F23: 16 | G23: 16
B24: RTpress Imagens | F24: 16 | G24: 16
B25: I9tv | F25: 16 | G25: 16
B26: Teleprompter Carioca Ltda. | F26: 16 | G26: 16
B27: REDACAO SERIES E REALITIES | C27: 1 | F27: 15 | G27: 16
B28: SUPERVISAO EDITORIA RJ 01 01 | F28: 14 | G28: 14
B29: Gilberto Merguizo Management Studio Eireli (CAPA MGT ) | C29: 2 | F29: 14 | G29: 16
B30: CIS | C30: 1 | F30: 14 | G30: 15
B31: REDES SOCIAIS GSHOW E RECEITAS | C31: 7 | D31: 4 | E31: 1 | F31: 13 | G31: 25
B32: DRAMATURGIA DIARIA | C32: 22 | D32: 4 | F32: 13 | G32: 39
B33: COT E EXTERNA ION | F33: 12 | G33: 12
B34: CULTURA POP 2 | C34: 6 | D34: 4 | F34: 12 | G34: 22
B35: Gilberto Merguizo Management Studio Eireli ( CAPA MGT) | C35: 3 | D35: 2 | F35: 11 | G35: 16
B36: SOL DE RELACIONAMENTO - CONTEUDO - ENTRETENIMENTO | C36: 4 | D36: 2 | F36: 10 | G36: 16
B37: SUPORTE PRODUCAO PRODUTOS E PLATAFORMAS RJ | C37: 6 | D37: 3 | E37: 9 | F37: 10 | G37: 28
B38: TRANSPORTES RJ | C38: 5 | D38: 9 | E38: 43 | F38: 10 | G38: 67
B39: SUPERVISAO EDITORIA G1 01 03 - 01 | C39: 3 | D39: 2 | F39: 9 | G39: 14
B40: EDITORIA RJ | C40: 5 | D40: 7 | F40: 8 | G40: 20
B41: EXTERNAS E EVENTOS EG | E41: 12 | F41: 8 | G41: 20
B42: PROJETOS DE PARCERIA | F42: 8 | G42: 8
B43: Huawei | F43: 8 | G43: 8
B44: Helpdesk | C44: 1 | D44: 3 | F44: 8 | G44: 12
B45: SUPERVISAO EDITORIA RJ 01 07 | D45: 1 | E45: 1 | F45: 7 | G45: 9
B46: Rede palavra tv | F46: 6 | G46: 6
B47: IMAGEM PARA CAPTACAO E PRODUCAO | F47: 6 | G47: 6
B48: SERVICOS ADMINISTRATIVOS | C48: 8 | D48: 2 | F48: 6 | G48: 16
B49: CARACTERIZACAO | C49: 2 | F49: 6 | G49: 8
B50: PROJETOS PARCEIROS E INTERNOS | F50: 6 | G50: 6
B51: SUPERVISAO G1 LOCAL RJ | F51: 6 | G51: 6
B52: PRODUCAO DE PERSONAGEM E AMBIENTE | C52: 2 | E52: 8 | F52: 6 | G52: 16
B53: FANTASTICO WEB | C53: 2 | F53: 6 | G53: 8
B54: GESTAO DO CONHECIMENTO EM TECNOLOGIA | C54: 2 | D54: 6 | F54: 6 | G54: 14
B55: Gran Coffee | C55: 2 | F55: 6 | G55: 8
B56: BRIGADA RJ | C56: 3 | D56: 5 | E56: 1 | F56: 6 | G56: 15
B57: MANJUBINHA | F57: 6 | G57: 6
B58: Gilberto Merguizo Management Studio Eireli ( CAPA MGT ) | C58: 2 | D58: 1 | F58: 5 | G58: 8
B59: PLAT - CAPTACAO E EVENTOS | C59: 3 | F59: 5 | G59: 8
B60: PARCERIAS DE SUSTENTACAO RJ - ION | C60: 1 | D60: 4 | F60: 5 | G60: 10
B61: ALIMENTACAO EVENTOS E EXTERNAS | C61: 5 | D61: 6 | E61: 2 | F61: 5 | G61: 18
B62: SUPERVISAO FANTASTICO 01 | F62: 4 | G62: 4
B63: SUPERVISAO EDITORIA RJ 01 04 | C63: 5 | F63: 4 | G63: 9
B64: TECNOLOGIA PARA JORNALISMO | C64: 1 | D64: 1 | F64: 4 | G64: 6
B65: PARCERIAS DE SUSTENTACAO RJ | F65: 4 | G65: 4
B66: MISSAO CRITICA RJ | F66: 4 | G66: 4
B67: CONTEUDO GSHOW E RECEITAS | C67: 5 | D67: 8 | F67: 3 | G67: 16
B68: SOL DE RELACIONAMENTO - JORNALISMO E ESPORTE | F68: 3 | G68: 3
B69: EXTERNA INTERNA JB BT | C69: 1 | D69: 5 | E69: 5 | F69: 3 | G69: 14
B70: INTELIGENCIA SEGURANCA EMPRESARIAL | C70: 1 | D70: 5 | E70: 1 | F70: 2 | G70: 9
B71: INTERNA EG | C71: 3 | D71: 3 | F71: 2 | G71: 8
B72: CULTURA POP 1 | C72: 9 | D72: 13 | F72: 2 | G72: 24
B73: ORQUESTRACAO PARA FLUXO DE PRODUCAO | C73: 1 | D73: 1 | F73: 2 | G73: 4
B74: PRODUCAO EM VIDEO 2 | C74: 3 | D74: 3 | E74: 1 | F74: 2 | G74: 9
B75: PARCERIAS DE SUSTENTACAO RJ - JB | C75: 6 | F75: 2 | G75: 8
B76: OPERACAO DE SEGURANCA DO TRABALHO RJ | E76: 2 | F76: 2 | G76: 4
B77: CONSERVACAO PREDIAL EG | C77: 8 | D77: 10 | F77: 1 | G77: 19
B78: COT E EXTERNA JB | C78: 3 | D78: 3 | E78: 12 | G78: 18
B79: FIGURINO ASSISTENTES | E79: 15 | G79: 15
B80: LOCACOES E LICENCIAMENTO DE EXTERNAS E EVENTOS | D80: 2 | G80: 2
B81: CAPTACAO INTERNA ION 2 | E81: 1 | G81: 1
B82: SUPRIMENTOS SERVICOS E LOGISTICA | E82: 2 | G82: 2
B83: APOIO GESTAO VARIEDADES PRODUCAO | E83: 2 | G83: 2
B84: SUPERVISAO EDITORIA RJ 01 03 | E84: 6 | G84: 6
B85: CENOGRAFIA | E85: 4 | G85: 4
B86: OPERACOES CENOGRAFICAS | E86: 2 | G86: 2
B87: Prestador | E87: 91 | G87: 91
B88: MAQ E MOV | E88: 5 | G88: 5
B89: REDES SOCIAIS - REALITIES E OPERACOES CROSS | E89: 1 | G89: 1
B90: PROGRAMACAO RJ E GLOBO INTERNACIONAL | E90: 5 | G90: 5
B91: REDES SOCIAIS - VARIEDADES E INFANTIL | E91: 3 | G91: 3
B92: CURADORIA CONT-ORIGINAL NAO FICCAO | E92: 1 | G92: 1
B93: LET | C93: 5 | D93: 2 | G93: 7
B94: PRODUCAO ARTE E DESIGN | E94: 3 | G94: 3
B95: OPERACAO E MISSAO CRITICA | E95: 4 | G95: 4
B96: GESTAO EXEC DA PRODUCAO | E96: 1 | G96: 1
B97: LOG EQUIPAMENTO JORNALISMO GSAT ESTUDIOS PRODUTORA | E97: 6 | G97: 6
B98: OPERACAO E GESTAO AMBIENTAL | C98: 1 | D98: 3 | G98: 4
B99: LOGISTICA E TRANSPORTE | E99: 3 | G99: 3
B100: SEGURANCA EMPRESARIAL RJ | E100: 7 | G100: 7
...

Sheet Agendamento
A1: Chave Agend | B1: Chave data | C1: Status Agend | D1: NOME COMPLETO | E1: EMPRESA | F1: MATRÍCULA | G1: CPF (somente números) | H1: DDD + TELEFONE | I1: DIRETORIA | J1: Departamento | K1: Gestor Imediato | L1: Cargo | M1: Agendamento Original | N1: Ag. Orig. | O1: Movimentação | P1: Data | Q1: Hr
A2: =IF(LEN(F2)>1,F2,G2)&O2&P2&Q2 -> 32636EG x Sambodromo4606818h | B2: =IF(LEN(F2)>1,F2,G2)&O2&P2 -> 32636EG x Sambodromo46068 | C2: =IF((IFERROR(IFERROR(VLOOKUP(A2,Controle_Utiliz!A:A,1,0),VLOOKUP(B2,Controle_Utiliz!B:B,1,0)),"Não Utilizou"))="Não Utilizou","Não Utilizou","Agendado") -> Agendado | D2: Adilson Pereira Coutinho | E2: Globo | F2: 32636 | H2: 21964555352 | I2: ESTRATÉGIA E TECNOLOGIA | J2: IMAGEM JB | K2: JEAN CARLO GOULART ALVES | L2: OPER CAMERA II | M2: EG x Sambódromo | Vai [1º Dia, Dom, 15-Fev (Grupo Especial)] | N2: 18:00 | O2: EG x Sambodromo | P2: 46068 | Q2: =LEFT(N2,2)&"h" -> 18h
A3: =IF(LEN(F3)>1,F3,G3)&O3&P3&Q3 -> 32636EG x Sambodromo4606918h | B3: =IF(LEN(F3)>1,F3,G3)&O3&P3 -> 32636EG x Sambodromo46069 | C3: =IF((IFERROR(IFERROR(VLOOKUP(A3,Controle_Utiliz!A:A,1,0),VLOOKUP(B3,Controle_Utiliz!B:B,1,0)),"Não Utilizou"))="Não Utilizou","Não Utilizou","Agendado") -> Agendado | D3: Adilson Pereira Coutinho | E3: Globo | F3: 32636 | H3: 21964555352 | I3: ESTRATÉGIA E TECNOLOGIA | J3: IMAGEM JB | K3: JEAN CARLO GOULART ALVES | L3: OPER CAMERA II | M3: EG x Sambódromo | Vai [2º Dia, Seg, 16-Fev (Grupo Especial)] | N3: 18:00 | O3: EG x Sambodromo | P3: 46069 | Q3: =LEFT(N3,2)&"h" -> 18h
A4: =IF(LEN(F4)>1,F4,G4)&O4&P4&Q4 -> 32636EG x Sambodromo4607018h | B4: =IF(LEN(F4)>1,F4,G4)&O4&P4 -> 32636EG x Sambodromo46070 | C4: =IF((IFERROR(IFERROR(VLOOKUP(A4,Controle_Utiliz!A:A,1,0),VLOOKUP(B4,Controle_Utiliz!B:B,1,0)),"Não Utilizou"))="Não Utilizou","Não Utilizou","Agendado") -> Agendado | D4: Adilson Pereira Coutinho | E4: Globo | F4: 32636 | H4: 21964555352 | I4: ESTRATÉGIA E TECNOLOGIA | J4: IMAGEM JB | K4: JEAN CARLO GOULART ALVES | L4: OPER CAMERA II | M4: EG x Sambódromo | Vai [3º Dia, Ter, 17-Fev (Grupo Especial)] | N4: 18:00 | O4: EG x Sambodromo | P4: 46070 | Q4: =LEFT(N4,2)&"h" -> 18h
A5: =IF(LEN(F5)>1,F5,G5)&O5&P5&Q5 -> 32636EG x Sambodromo4607418h | B5: =IF(LEN(F5)>1,F5,G5)&O5&P5 -> 32636EG x Sambodromo46074 | C5: =IF((IFERROR(IFERROR(VLOOKUP(A5,Controle_Utiliz!A:A,1,0),VLOOKUP(B5,Controle_Utiliz!B:B,1,0)),"Não Utilizou"))="Não Utilizou","Não Utilizou","Agendado") -> Agendado | D5: Adilson Pereira Coutinho | E5: Globo | F5: 32636 | H5: 21964555352 | I5: ESTRATÉGIA E TECNOLOGIA | J5: IMAGEM JB | K5: JEAN CARLO GOULART ALVES | L5: OPER CAMERA II | M5: EG x Sambódromo | Vai [CAMPEÃES, Sáb, 21-Fev (Desfile das Campeãs).] | N5: 18:00 | O5: EG x Sambodromo | P5: 46074 | Q5: =LEFT(N5,2)&"h" -> 18h
A6: =IF(LEN(F6)>1,F6,G6)&O6&P6&Q6 -> 32636Sambodromo x EG4606805h | B6: =IF(LEN(F6)>1,F6,G6)&O6&P6 -> 32636Sambodromo x EG46068 | C6: =IF((IFERROR(IFERROR(VLOOKUP(A6,Controle_Utiliz!A:A,1,0),VLOOKUP(B6,Controle_Utiliz!B:B,1,0)),"Não Utilizou"))="Não Utilizou","Não Utilizou","Agendado") -> Não Utilizou | D6: Adilson Pereira Coutinho | E6: Globo | F6: 32636 | H6: 21964555352 | I6: ESTRATÉGIA E TECNOLOGIA | J6: IMAGEM JB | K6: JEAN CARLO GOULART ALVES | L6: OPER CAMERA II | M6: Sambódromo x EG | Vem [1º Dia, Dom, 15-Fev (Grupo Especial)] | N6: 05:00 | O6: Sambodromo x EG | P6: 46068 | Q6: =LEFT(N6,2)&"h" -> 05h
A7: =IF(LEN(F7)>1,F7,G7)&O7&P7&Q7 -> 32636Sambodromo x EG4606905h | B7: =IF(LEN(F7)>1,F7,G7)&O7&P7 -> 32636Sambodromo x EG46069 | C7: =IF((IFERROR(IFERROR(VLOOKUP(A7,Controle_Utiliz!A:A,1,0),VLOOKUP(B7,Controle_Utiliz!B:B,1,0)),"Não Utilizou"))="Não Utilizou","Não Utilizou","Agendado") -> Agendado | D7: Adilson Pereira Coutinho | E7: Globo | F7: 32636 | H7: 21964555352 | I7: ESTRATÉGIA E TECNOLOGIA | J7: IMAGEM JB | K7: JEAN CARLO GOULART ALVES | L7: OPER CAMERA II | M7: Sambódromo x EG | Vem [2º Dia, Seg, 16-Fev (Grupo Especial)] | N7: 05:00 | O7: Sambodromo x EG | P7: 46069 | Q7: =LEFT(N7,2)&"h" -> 05h
A8: =IF(LEN(F8)>1,F8,G8)&O8&P8&Q8 -> 32636Sambodromo x EG4607005h | B8: =IF(LEN(F8)>1,F8,G8)&O8&P8 -> 32636Sambodromo x EG46070 | C8: =IF((IFERROR(IFERROR(VLOOKUP(A8,Controle_Utiliz!A:A,1,0),VLOOKUP(B8,Controle_Utiliz!B:B,1,0)),"Não Utilizou"))="Não Utilizou","Não Utilizou","Agendado") -> Agendado | D8: Adilson Pereira Coutinho | E8: Globo | F8: 32636 | H8: 21964555352 | I8: ESTRATÉGIA E TECNOLOGIA | J8: IMAGEM JB | K8: JEAN CARLO GOULART ALVES | L8: OPER CAMERA II | M8: Sambódromo x EG | Vem [3º Dia, Ter, 17-Fev (Grupo Especial)] | N8: 05:00 | O8: Sambodromo x EG | P8: 46070 | Q8: =LEFT(N8,2)&"h" -> 05h
A9: =IF(LEN(F9)>1,F9,G9)&O9&P9&Q9 -> 32636Sambodromo x EG4607405h | B9: =IF(LEN(F9)>1,F9,G9)&O9&P9 -> 32636Sambodromo x EG46074 | C9: =IF((IFERROR(IFERROR(VLOOKUP(A9,Controle_Utiliz!A:A,1,0),VLOOKUP(B9,Controle_Utiliz!B:B,1,0)),"Não Utilizou"))="Não Utilizou","Não Utilizou","Agendado") -> Agendado | D9: Adilson Pereira Coutinho | E9: Globo | F9: 32636 | H9: 21964555352 | I9: ESTRATÉGIA E TECNOLOGIA | J9: IMAGEM JB | K9: JEAN CARLO GOULART ALVES | L9: OPER CAMERA II | M9: Sambódromo x EG | Vem [CAMPEÃES, Sáb, 21-Fev (Desfile das Campeãs).] | N9: 05:00 | O9: Sambodromo x EG | P9: 46074 | Q9: =LEFT(N9,2)&"h" -> 05h
A10: =IF(LEN(F10)>1,F10,G10)&O10&P10&Q10 -> 32636JB x Sambodromo4606818h | B10: =IF(LEN(F10)>1,F10,G10)&O10&P10 -> 32636JB x Sambodromo46068 | C10: =IF((IFERROR(IFERROR(VLOOKUP(A10,Controle_Utiliz!A:A,1,0),VLOOKUP(B10,Controle_Utiliz!B:B,1,0)),"Não Utilizou"))="Não Utilizou","Não Utilizou","Agendado") -> Não Utilizou | D10: Adilson Pereira Coutinho | E10: Globo | F10: 32636 | H10: 21964555352 | I10: ESTRATÉGIA E TECNOLOGIA | J10: IMAGEM JB | K10: JEAN CARLO GOULART ALVES | L10: OPER CAMERA II | M10: JB x Sambódromo | Vai [1º Dia, Dom, 15-Fev (Grupo Especial)] | N10: 18:00 | O10: JB x Sambodromo | P10: 46068 | Q10: =LEFT(N10,2)&"h" -> 18h
A11: =IF(LEN(F11)>1,F11,G11)&O11&P11&Q11 -> 32636JB x Sambodromo4606918h | B11: =IF(LEN(F11)>1,F11,G11)&O11&P11 -> 32636JB x Sambodromo46069 | C11: =IF((IFERROR(IFERROR(VLOOKUP(A11,Controle_Utiliz!A:A,1,0),VLOOKUP(B11,Controle_Utiliz!B:B,1,0)),"Não Utilizou"))="Não Utilizou","Não Utilizou","Agendado") -> Não Utilizou | D11: Adilson Pereira Coutinho | E11: Globo | F11: 32636 | H11: 21964555352 | I11: ESTRATÉGIA E TECNOLOGIA | J11: IMAGEM JB | K11: JEAN CARLO GOULART ALVES | L11: OPER CAMERA II | M11: JB x Sambódromo | Vai [2º Dia, Seg, 16-Fev (Grupo Especial)] | N11: 18:00 | O11: JB x Sambodromo | P11: 46069 | Q11: =LEFT(N11,2)&"h" -> 18h
A12: =IF(LEN(F12)>1,F12,G12)&O12&P12&Q12 -> 32636JB x Sambodromo4607018h | B12: =IF(LEN(F12)>1,F12,G12)&O12&P12 -> 32636JB x Sambodromo46070 | C12: =IF((IFERROR(IFERROR(VLOOKUP(A12,Controle_Utiliz!A:A,1,0),VLOOKUP(B12,Controle_Utiliz!B:B,1,0)),"Não Utilizou"))="Não Utilizou","Não Utilizou","Agendado") -> Não Utilizou | D12: Adilson Pereira Coutinho | E12: Globo | F12: 32636 | H12: 21964555352 | I12: ESTRATÉGIA E TECNOLOGIA | J12: IMAGEM JB | K12: JEAN CARLO GOULART ALVES | L12: OPER CAMERA II | M12: JB x Sambódromo | Vai [3º Dia, Ter, 17-Fev (Grupo Especial)] | N12: 18:00 | O12: JB x Sambodromo | P12: 46070 | Q12: =LEFT(N12,2)&"h" -> 18h
A13: =IF(LEN(F13)>1,F13,G13)&O13&P13&Q13 -> 32636JB x Sambodromo4607418h | B13: =IF(LEN(F13)>1,F13,G13)&O13&P13 -> 32636JB x Sambodromo46074 | C13: =IF((IFERROR(IFERROR(VLOOKUP(A13,Controle_Utiliz!A:A,1,0),VLOOKUP(B13,Controle_Utiliz!B:B,1,0)),"Não Utilizou"))="Não Utilizou","Não Utilizou","Agendado") -> Não Utilizou | D13: Adilson Pereira Coutinho | E13: Globo | F13: 32636 | H13: 21964555352 | I13: ESTRATÉGIA E TECNOLOGIA | J13: IMAGEM JB | K13: JEAN CARLO GOULART ALVES | L13: OPER CAMERA II | M13: JB x Sambódromo | Vai [CAMPEÃES, Sáb, 21-Fev (Desfile das Campeãs).] | N13: 18:00 | O13: JB x Sambodromo | P13: 46074 | Q13: =LEFT(N13,2)&"h" -> 18h
... A17: =IF(LEN(F17)>1,F17,G17)&O17&P17&Q17 -> 32636Sambodromo x JB4607405h | B17: =IF(LEN(F17)>1,F17,G17)&O17&P17 -> 32636Sambodromo x JB46074 | C17: =IF((IFERROR(IFERROR(VLOOKUP(A17,Controle_Utiliz!A:A,1,0),VLOOKUP(B17,Controle_Utiliz!B:B,1,0)),"Não Utilizou"))="Não Utilizou","Não Utilizou","Agendado") -> Não Utilizou | D17: Adilson Pereira Coutinho | E17: Globo | F17: 32636 | H17: 21964555352 | I17: ESTRATÉGIA E TECNOLOGIA | J17: IMAGEM JB | K17: JEAN CARLO GOULART ALVES | L17: OPER CAMERA II | M17: Sambódromo x JB | Vem [CAMPEÃES, Sáb, 21-Fev (Desfile das Campeãs).] | N17: 05:00 | O17: Sambodromo x JB | P17: 46074 | Q17: =LEFT(N17,2)&"h" -> 05h
A18: =IF(LEN(F18)>1,F18,G18)&O18&P18&Q18 -> 15974990722EG x Sambodromo4606817h | B18: =IF(LEN(F18)>1,F18,G18)&O18&P18 -> 15974990722EG x Sambodromo46068 | C18: =IF((IFERROR(IFERROR(VLOOKUP(A18,Controle_Utiliz!A:A,1,0),VLOOKUP(B18,Controle_Utiliz!B:B,1,0)),"Não Utilizou"))="Não Utilizou","Não Utilizou","Agendado") -> Não Utilizou | D18: Alana Chicharo Ferreira | E18: Gilberto Merguizo Management Studio Eireli ( CAPA MGT) | G18: 15974990722 | H18: 21990091564 | I18: TV GLOBO | J18: Gilberto Merguizo Management Studio Eireli ( CAPA MGT) | K18: Gilberto Merguizo Management Studio Eireli ( CAPA MGT) | L18: Gilberto Merguizo Management Studio Eireli ( CAPA MGT) | M18: EG x Sambódromo | Vai [1º Dia, Dom, 15-Fev (Grupo Especial)] | N18: 17:00 | O18: EG x Sambodromo | P18: 46068 | Q18: =LEFT(N18,2)&"h" -> 17h
A19: =IF(LEN(F19)>1,F19,G19)&O19&P19&Q19 -> 15974990722EG x Sambodromo4606917h | B19: =IF(LEN(F19)>1,F19,G19)&O19&P19 -> 15974990722EG x Sambodromo46069 | C19: =IF((IFERROR(IFERROR(VLOOKUP(A19,Controle_Utiliz!A:A,1,0),VLOOKUP(B19,Controle_Utiliz!B:B,1,0)),"Não Utilizou"))="Não Utilizou","Não Utilizou","Agendado") -> Não Utilizou | D19: Alana Chicharo Ferreira | E19: Gilberto Merguizo Management Studio Eireli ( CAPA MGT) | G19: 15974990722 | H19: 21990091564 | I19: TV GLOBO | J19: Gilberto Merguizo Management Studio Eireli ( CAPA MGT) | K19: Gilberto Merguizo Management Studio Eireli ( CAPA MGT) | L19: Gilberto Merguizo Management Studio Eireli ( CAPA MGT) | M19: EG x Sambódromo | Vai [2º Dia, Seg, 16-Fev (Grupo Especial)] | N19: 17:00 | O19: EG x Sambodromo | P19: 46069 | Q19: =LEFT(N19,2)&"h" -> 17h
A20: =IF(LEN(F20)>1,F20,G20)&O20&P20&Q20 -> 15974990722EG x Sambodromo4607017h | B20: =IF(LEN(F20)>1,F20,G20)&O20&P20 -> 15974990722EG x Sambodromo46070 | C20: =IF((IFERROR(IFERROR(VLOOKUP(A20,Controle_Utiliz!A:A,1,0),VLOOKUP(B20,Controle_Utiliz!B:B,1,0)),"Não Utilizou"))="Não Utilizou","Não Utilizou","Agendado") -> Não Utilizou | D20: Alana Chicharo Ferreira | E20: Gilberto Merguizo Management Studio Eireli ( CAPA MGT) | G20: 15974990722 | H20: 21990091564 | I20: TV GLOBO | J20: Gilberto Merguizo Management Studio Eireli ( CAPA MGT) | K20: Gilberto Merguizo Management Studio Eireli ( CAPA MGT) | L20: Gilberto Merguizo Management Studio Eireli ( CAPA MGT) | M20: EG x Sambódromo | Vai [3º Dia, Ter, 17-Fev (Grupo Especial)] | N20: 17:00 | O20: EG x Sambodromo | P20: 46070 | Q20: =LEFT(N20,2)&"h" -> 17h
A21: =IF(LEN(F21)>1,F21,G21)&O21&P21&Q21 -> 15974990722EG x Sambodromo4607417h | B21: =IF(LEN(F21)>1,F21,G21)&O21&P21 -> 15974990722EG x Sambodromo46074 | C21: =IF((IFERROR(IFERROR(VLOOKUP(A21,Controle_Utiliz!A:A,1,0),VLOOKUP(B21,Controle_Utiliz!B:B,1,0)),"Não Utilizou"))="Não Utilizou","Não Utilizou","Agendado") -> Não Utilizou | D21: Alana Chicharo Ferreira | E21: Gilberto Merguizo Management Studio Eireli ( CAPA MGT) | G21: 15974990722 | H21: 21990091564 | I21: TV GLOBO | J21: Gilberto Merguizo Management Studio Eireli ( CAPA MGT) | K21: Gilberto Merguizo Management Studio Eireli ( CAPA MGT) | L21: Gilberto Merguizo Management Studio Eireli ( CAPA MGT) | M21: EG x Sambódromo | Vai [CAMPEÃES, Sáb, 21-Fev (Desfile das Campeãs).] | N21: 17:00 | O21: EG x Sambodromo | P21: 46074 | Q21: =LEFT(N21,2)&"h" -> 17h
A22: =IF(LEN(F22)>1,F22,G22)&O22&P22&Q22 -> 15974990722Sambodromo x EG4606802h | B22: =IF(LEN(F22)>1,F22,G22)&O22&P22 -> 15974990722Sambodromo x EG46068 | C22: =IF((IFERROR(IFERROR(VLOOKUP(A22,Controle_Utiliz!A:A,1,0),VLOOKUP(B22,Controle_Utiliz!B:B,1,0)),"Não Utilizou"))="Não Utilizou","Não Utilizou","Agendado") -> Agendado | D22: Alana Chicharo Ferreira | E22: Gilberto Merguizo Management Studio Eireli ( CAPA MGT) | G22: 15974990722 | H22: 21990091564 | I22: TV GLOBO | J22: Gilberto Merguizo Management Studio Eireli ( CAPA MGT) | K22: Gilberto Merguizo Management Studio Eireli ( CAPA MGT) | L22: Gilberto Merguizo Management Studio Eireli ( CAPA MGT) | M22: Sambódromo x EG | Vem [1º Dia, Dom, 15-Fev (Grupo Especial)] | N22: 02:00 | O22: Sambodromo x EG | P22: 46068 | Q22: =LEFT(N22,2)&"h" -> 02h
A23: =IF(LEN(F23)>1,F23,G23)&O23&P23&Q23 -> 15974990722Sambodromo x EG4606902h | B23: =IF(LEN(F23)>1,F23,G23)&O23&P23 -> 15974990722Sambodromo x EG46069 | C23: =IF((IFERROR(IFERROR(VLOOKUP(A23,Controle_Utiliz!A:A,1,0),VLOOKUP(B23,Controle_Utiliz!B:B,1,0)),"Não Utilizou"))="Não Utilizou","Não Utilizou","Agendado") -> Não Utilizou | D23: Alana Chicharo Ferreira | E23: Gilberto Merguizo Management Studio Eireli ( CAPA MGT) | G23: 15974990722 | H23: 21990091564 | I23: TV GLOBO | J23: Gilberto Merguizo Management Studio Eireli ( CAPA MGT) | K23: Gilberto Merguizo Management Studio Eireli ( CAPA MGT) | L23: Gilberto Merguizo Management Studio Eireli ( CAPA MGT) | M23: Sambódromo x EG | Vem [2º Dia, Seg, 16-Fev (Grupo Especial)] | N23: 02:00 | O23: Sambodromo x EG | P23: 46069 | Q23: =LEFT(N23,2)&"h" -> 02h
A24: =IF(LEN(F24)>1,F24,G24)&O24&P24&Q24 -> 15974990722Sambodromo x EG4607002h | B24: =IF(LEN(F24)>1,F24,G24)&O24&P24 -> 15974990722Sambodromo x EG46070 | C24: =IF((IFERROR(IFERROR(VLOOKUP(A24,Controle_Utiliz!A:A,1,0),VLOOKUP(B24,Controle_Utiliz!B:B,1,0)),"Não Utilizou"))="Não Utilizou","Não Utilizou","Agendado") -> Não Utilizou | D24: Alana Chicharo Ferreira | E24: Gilberto Merguizo Management Studio Eireli ( CAPA MGT) | G24: 15974990722 | H24: 21990091564 | I24: TV GLOBO | J24: Gilberto Merguizo Management Studio Eireli ( CAPA MGT) | K24: Gilberto Merguizo Management Studio Eireli ( CAPA MGT) | L24: Gilberto Merguizo Management Studio Eireli ( CAPA MGT) | M24: Sambódromo x EG | Vem [3º Dia, Ter, 17-Fev (Grupo Especial)] | N24: 02:00 | O24: Sambodromo x EG | P24: 46070 | Q24: =LEFT(N24,2)&"h" -> 02h
A25: =IF(LEN(F25)>1,F25,G25)&O25&P25&Q25 -> 15974990722Sambodromo x EG4607402h | B25: =IF(LEN(F25)>1,F25,G25)&O25&P25 -> 15974990722Sambodromo x EG46074 | C25: =IF((IFERROR(IFERROR(VLOOKUP(A25,Controle_Utiliz!A:A,1,0),VLOOKUP(B25,Controle_Utiliz!B:B,1,0)),"Não Utilizou"))="Não Utilizou","Não Utilizou","Agendado") -> Não Utilizou | D25: Alana Chicharo Ferreira | E25: Gilberto Merguizo Management Studio Eireli ( CAPA MGT) | G25: 15974990722 | H25: 21990091564 | I25: TV GLOBO | J25: Gilberto Merguizo Management Studio Eireli ( CAPA MGT) | K25: Gilberto Merguizo Management Studio Eireli ( CAPA MGT) | L25: Gilberto Merguizo Management Studio Eireli ( CAPA MGT) | M25: Sambódromo x EG | Vem [CAMPEÃES, Sáb, 21-Fev (Desfile das Campeãs).] | N25: 02:00 | O25: Sambodromo x EG | P25: 46074 | Q25: =LEFT(N25,2)&"h" -> 02h
A26: =IF(LEN(F26)>1,F26,G26)&O26&P26&Q26 -> 03139095473EG x Sambodromo4606818h | B26: =IF(LEN(F26)>1,F26,G26)&O26&P26 -> 03139095473EG x Sambodromo46068 | C26: =IF((IFERROR(IFERROR(VLOOKUP(A26,Controle_Utiliz!A:A,1,0),VLOOKUP(B26,Controle_Utiliz!B:B,1,0)),"Não Utilizou"))="Não Utilizou","Não Utilizou","Agendado") -> Agendado | D26: ALBERTO CAVALCANTI LIRA DA SILVA | E26: Prestador - Top Service | G26: 03139095473 | H26: 21967041708 | I26: FJI - CSC OGA | J26: Prestador - Top Service | K26: Prestador - Top Service | L26: Prestador - Top Service | M26: EG x Sambódromo | Vai [1º Dia, Dom, 15-Fev (Grupo Especial)] | N26: 18:00 | O26: EG x Sambodromo | P26: 46068 | Q26: =LEFT(N26,2)&"h" -> 18h
A27: =IF(LEN(F27)>1,F27,G27)&O27&P27&Q27 -> 03139095473EG x Sambodromo4606918h | B27: =IF(LEN(F27)>1,F27,G27)&O27&P27 -> 03139095473EG x Sambodromo46069 | C27: =IF((IFERROR(IFERROR(VLOOKUP(A27,Controle_Utiliz!A:A,1,0),VLOOKUP(B27,Controle_Utiliz!B:B,1,0)),"Não Utilizou"))="Não Utilizou","Não Utilizou","Agendado") -> Agendado | D27: ALBERTO CAVALCANTI LIRA DA SILVA | E27: Prestador - Top Service | G27: 03139095473 | H27: 21967041708 | I27: FJI - CSC OGA | J27: Prestador - Top Service | K27: Prestador - Top Service | L27: Prestador - Top Service | M27: EG x Sambódromo | Vai [2º Dia, Seg, 16-Fev (Grupo Especial)] | N27: 18:00 | O27: EG x Sambodromo | P27: 46069 | Q27: =LEFT(N27,2)&"h" -> 18h
A28: =IF(LEN(F28)>1,F28,G28)&O28&P28&Q28 -> 03139095473EG x Sambodromo4607018h | B28: =IF(LEN(F28)>1,F28,G28)&O28&P28 -> 03139095473EG x Sambodromo46070 | C28: =IF((IFERROR(IFERROR(VLOOKUP(A28,Controle_Utiliz!A:A,1,0),VLOOKUP(B28,Controle_Utiliz!B:B,1,0)),"Não Utilizou"))="Não Utilizou","Não Utilizou","Agendado") -> Agendado | D28: ALBERTO CAVALCANTI LIRA DA SILVA | E28: Prestador - Top Service | G28: 03139095473 | H28: 21967041708 | I28: FJI - CSC OGA | J28: Prestador - Top Service | K28: Prestador - Top Service | L28: Prestador - Top Service | M28: EG x Sambódromo | Vai [3º Dia, Ter, 17-Fev (Grupo Especial)] | N28: 18:00 | O28: EG x Sambodromo | P28: 46070 | Q28: =LEFT(N28,2)&"h" -> 18h
A29: =IF(LEN(F29)>1,F29,G29)&O29&P29&Q29 -> 03139095473EG x Sambodromo4607418h | B29: =IF(LEN(F29)>1,F29,G29)&O29&P29 -> 03139095473EG x Sambodromo46074 | C29: =IF((IFERROR(IFERROR(VLOOKUP(A29,Controle_Utiliz!A:A,1,0),VLOOKUP(B29,Controle_Utiliz!B:B,1,0)),"Não Utilizou"))="Não Utilizou","Não Utilizou","Agendado") -> Não Utilizou | D29: ALBERTO CAVALCANTI LIRA DA SILVA | E29: Prestador - Top Service | G29: 03139095473 | H29: 21967041708 | I29: FJI - CSC OGA | J29: Prestador - Top Service | K29: Prestador - Top Service | L29: Prestador - Top Service | M29: EG x Sambódromo | Vai [CAMPEÃES, Sáb, 21-Fev (Desfile das Campeãs).] | N29: 18:00 | O29: EG x Sambodromo | P29: 46074 | Q29: =LEFT(N29,2)&"h" -> 18h
A30: =IF(LEN(F30)>1,F30,G30)&O30&P30&Q30 -> 03139095473Sambodromo x EG4606806h | B30: =IF(LEN(F30)>1,F30,G30)&O30&P30 -> 03139095473Sambodromo x EG46068 | C30: =IF((IFERROR(IFERROR(VLOOKUP(A30,Controle_Utiliz!A:A,1,0),VLOOKUP(B30,Controle_Utiliz!B:B,1,0)),"Não Utilizou"))="Não Utilizou","Não Utilizou","Agendado") -> Não Utilizou | D30: ALBERTO CAVALCANTI LIRA DA SILVA | E30: Prestador - Top Service | G30: 03139095473 | H30: 21967041708 | I30: FJI - CSC OGA | J30: Prestador - Top Service | K30: Prestador - Top Service | L30: Prestador - Top Service | M30: Sambódromo x EG | Vem [1º Dia, Dom, 15-Fev (Grupo Especial)] | N30: 06:00 | O30: Sambodromo x EG | P30: 46068 | Q30: =LEFT(N30,2)&"h" -> 06h
A31: =IF(LEN(F31)>1,F31,G31)&O31&P31&Q31 -> 03139095473Sambodromo x EG4606906h | B31: =IF(LEN(F31)>1,F31,G31)&O31&P31 -> 03139095473Sambodromo x EG46069 | C31: =IF((IFERROR(IFERROR(VLOOKUP(A31,Controle_Utiliz!A:A,1,0),VLOOKUP(B31,Controle_Utiliz!B:B,1,0)),"Não Utilizou"))="Não Utilizou","Não Utilizou","Agendado") -> Não Utilizou | D31: ALBERTO CAVALCANTI LIRA DA SILVA | E31: Prestador - Top Service | G31: 03139095473 | H31: 21967041708 | I31: FJI - CSC OGA | J31: Prestador - Top Service | K31: Prestador - Top Service | L31: Prestador - Top Service | M31: Sambódromo x EG | Vem [2º Dia, Seg, 16-Fev (Grupo Especial)] | N31: 06:00 | O31: Sambodromo x EG | P31: 46069 | Q31: =LEFT(N31,2)&"h" -> 06h
A32: =IF(LEN(F32)>1,F32,G32)&O32&P32&Q32 -> 03139095473Sambodromo x EG4607006h | B32: =IF(LEN(F32)>1,F32,G32)&O32&P32 -> 03139095473Sambodromo x EG46070 | C32: =IF((IFERROR(IFERROR(VLOOKUP(A32,Controle_Utiliz!A:A,1,0),VLOOKUP(B32,Controle_Utiliz!B:B,1,0)),"Não Utilizou"))="Não Utilizou","Não Utilizou","Agendado") -> Agendado | D32: ALBERTO CAVALCANTI LIRA DA SILVA | E32: Prestador - Top Service | G32: 03139095473 | H32: 21967041708 | I32: FJI - CSC OGA | J32: Prestador - Top Service | K32: Prestador - Top Service | L32: Prestador - Top Service | M32: Sambódromo x EG | Vem [3º Dia, Ter, 17-Fev (Grupo Especial)] | N32: 06:00 | O32: Sambodromo x EG | P32: 46070 | Q32: =LEFT(N32,2)&"h" -> 06h
A33: =IF(LEN(F33)>1,F33,G33)&O33&P33&Q33 -> 03139095473Sambodromo x EG4607406h | B33: =IF(LEN(F33)>1,F33,G33)&O33&P33 -> 03139095473Sambodromo x EG46074 | C33: =IF((IFERROR(IFERROR(VLOOKUP(A33,Controle_Utiliz!A:A,1,0),VLOOKUP(B33,Controle_Utiliz!B:B,1,0)),"Não Utilizou"))="Não Utilizou","Não Utilizou","Agendado") -> Agendado | D33: ALBERTO CAVALCANTI LIRA DA SILVA | E33: Prestador - Top Service | G33: 03139095473 | H33: 21967041708 | I33: FJI - CSC OGA | J33: Prestador - Top Service | K33: Prestador - Top Service | L33: Prestador - Top Service | M33: Sambódromo x EG | Vem [CAMPEÃES, Sáb, 21-Fev (Desfile das Campeãs).] | N33: 06:00 | O33: Sambodromo x EG | P33: 46074 | Q33: =LEFT(N33,2)&"h" -> 06h
A34: =IF(LEN(F34)>1,F34,G34)&O34&P34&Q34 -> 49605JB x Sambodromo4606819h | B34: =IF(LEN(F34)>1,F34,G34)&O34&P34 -> 49605JB x Sambodromo46068 | C34: =IF((IFERROR(IFERROR(VLOOKUP(A34,Controle_Utiliz!A:A,1,0),VLOOKUP(B34,Controle_Utiliz!B:B,1,0)),"Não Utilizou"))="Não Utilizou","Não Utilizou","Agendado") -> Agendado | D34: Alessandra Albuquerque | E34: Globo | F34: 49605 | H34: 21997311979 | I34: REDES PD | J34: PRODUCAO EM VIDEO | K34: NILO CESAR BARROS GUIMARAES MAIA | L34: PRODUTOR VIDEO III | M34: JB x Sambódromo | Vai [1º Dia, Dom, 15-Fev (Grupo Especial)] | N34: 19:00 | O34: JB x Sambodromo | P34: 46068 | Q34: =LEFT(N34,2)&"h" -> 19h
A35: =IF(LEN(F35)>1,F35,G35)&O35&P35&Q35 -> 49605JB x Sambodromo4606920h | B35: =IF(LEN(F35)>1,F35,G35)&O35&P35 -> 49605JB x Sambodromo46069 | C35: =IF((IFERROR(IFERROR(VLOOKUP(A35,Controle_Utiliz!A:A,1,0),VLOOKUP(B35,Controle_Utiliz!B:B,1,0)),"Não Utilizou"))="Não Utilizou","Não Utilizou","Agendado") -> Agendado | D35: Alessandra Albuquerque | E35: Globo | F35: 49605 | H35: 21997311979 | I35: REDES PD | J35: PRODUCAO EM VIDEO | K35: NILO CESAR BARROS GUIMARAES MAIA | L35: PRODUTOR VIDEO III | M35: JB x Sambódromo | Vai [2º Dia, Seg, 16-Fev (Grupo Especial)] | N35: 20:00 | O35: JB x Sambodromo | P35: 46069 | Q35: =LEFT(N35,2)&"h" -> 20h
A36: =IF(LEN(F36)>1,F36,G36)&O36&P36&Q36 -> 49605JB x Sambodromo4607020h | B36: =IF(LEN(F36)>1,F36,G36)&O36&P36 -> 49605JB x Sambodromo46070 | C36: =IF((IFERROR(IFERROR(VLOOKUP(A36,Controle_Utiliz!A:A,1,0),VLOOKUP(B36,Controle_Utiliz!B:B,1,0)),"Não Utilizou"))="Não Utilizou","Não Utilizou","Agendado") -> Agendado | D36: Alessandra Albuquerque | E36: Globo | F36: 49605 | H36: 21997311979 | I36: REDES PD | J36: PRODUCAO EM VIDEO | K36: NILO CESAR BARROS GUIMARAES MAIA | L36: PRODUTOR VIDEO III | M36: JB x Sambódromo | Vai [3º Dia, Ter, 17-Fev (Grupo Especial)] | N36: 20:00 | O36: JB x Sambodromo | P36: 46070 | Q36: =LEFT(N36,2)&"h" -> 20h
A37: =IF(LEN(F37)>1,F37,G37)&O37&P37&Q37 -> 49605JB x Sambodromo4607420h | B37: =IF(LEN(F37)>1,F37,G37)&O37&P37 -> 49605JB x Sambodromo46074 | C37: =IF((IFERROR(IFERROR(VLOOKUP(A37,Controle_Utiliz!A:A,1,0),VLOOKUP(B37,Controle_Utiliz!B:B,1,0)),"Não Utilizou"))="Não Utilizou","Não Utilizou","Agendado") -> Agendado | D37: Alessandra Albuquerque | E37: Globo | F37: 49605 | H37: 21997311979 | I37: REDES PD | J37: PRODUCAO EM VIDEO | K37: NILO CESAR BARROS GUIMARAES MAIA | L37: PRODUTOR VIDEO III | M37: JB x Sambódromo | Vai [CAMPEÃES, Sáb, 21-Fev (Desfile das Campeãs).] | N37: 20:00 | O37: JB x Sambodromo | P37: 46074 | Q37: =LEFT(N37,2)&"h" -> 20h
A38: =IF(LEN(F38)>1,F38,G38)&O38&P38&Q38 -> 49605Sambodromo x JB4606804h | B38: =IF(LEN(F38)>1,F38,G38)&O38&P38 -> 49605Sambodromo x JB46068 | C38: =IF((IFERROR(IFERROR(VLOOKUP(A38,Controle_Utiliz!A:A,1,0),VLOOKUP(B38,Controle_Utiliz!B:B,1,0)),"Não Utilizou"))="Não Utilizou","Não Utilizou","Agendado") -> Agendado | D38: Alessandra Albuquerque | E38: Globo | F38: 49605 | H38: 21997311979 | I38: REDES PD | J38: PRODUCAO EM VIDEO | K38: NILO CESAR BARROS GUIMARAES MAIA | L38: PRODUTOR VIDEO III | M38: Sambódromo x JB | Vem [1º Dia, Dom, 15-Fev (Grupo Especial)] | N38: 04:00 | O38: Sambodromo x JB | P38: 46068 | Q38: =LEFT(N38,2)&"h" -> 04h
A39: =IF(LEN(F39)>1,F39,G39)&O39&P39&Q39 -> 49605Sambodromo x JB4606904h | B39: =IF(LEN(F39)>1,F39,G39)&O39&P39 -> 49605Sambodromo x JB46069 | C39: =IF((IFERROR(IFERROR(VLOOKUP(A39,Controle_Utiliz!A:A,1,0),VLOOKUP(B39,Controle_Utiliz!B:B,1,0)),"Não Utilizou"))="Não Utilizou","Não Utilizou","Agendado") -> Agendado | D39: Alessandra Albuquerque | E39: Globo | F39: 49605 | H39: 21997311979 | I39: REDES PD | J39: PRODUCAO EM VIDEO | K39: NILO CESAR BARROS GUIMARAES MAIA | L39: PRODUTOR VIDEO III | M39: Sambódromo x JB | Vem [2º Dia, Seg, 16-Fev (Grupo Especial)] | N39: 04:00 | O39: Sambodromo x JB | P39: 46069 | Q39: =LEFT(N39,2)&"h" -> 04h
A40: =IF(LEN(F40)>1,F40,G40)&O40&P40&Q40 -> 49605Sambodromo x JB4607004h | B40: =IF(LEN(F40)>1,F40,G40)&O40&P40 -> 49605Sambodromo x JB46070 | C40: =IF((IFERROR(IFERROR(VLOOKUP(A40,Controle_Utiliz!A:A,1,0),VLOOKUP(B40,Controle_Utiliz!B:B,1,0)),"Não Utilizou"))="Não Utilizou","Não Utilizou","Agendado") -> Agendado | D40: Alessandra Albuquerque | E40: Globo | F40: 49605 | H40: 21997311979 | I40: REDES PD | J40: PRODUCAO EM VIDEO | K40: NILO CESAR BARROS GUIMARAES MAIA | L40: PRODUTOR VIDEO III | M40: Sambódromo x JB | Vem [3º Dia, Ter, 17-Fev (Grupo Especial)] | N40: 04:00 | O40: Sambodromo x JB | P40: 46070 | Q40: =LEFT(N40,2)&"h" -> 04h
A41: =IF(LEN(F41)>1,F41,G41)&O41&P41&Q41 -> 49605Sambodromo x JB4607404h | B41: =IF(LEN(F41)>1,F41,G41)&O41&P41 -> 49605Sambodromo x JB46074 | C41: =IF((IFERROR(IFERROR(VLOOKUP(A41,Controle_Utiliz!A:A,1,0),VLOOKUP(B41,Controle_Utiliz!B:B,1,0)),"Não Utilizou"))="Não Utilizou","Não Utilizou","Agendado") -> Não Utilizou | D41: Alessandra Albuquerque | E41: Globo | F41: 49605 | H41: 21997311979 | I41: REDES PD | J41: PRODUCAO EM VIDEO | K41: NILO CESAR BARROS GUIMARAES MAIA | L41: PRODUTOR VIDEO III | M41: Sambódromo x JB | Vem [CAMPEÃES, Sáb, 21-Fev (Desfile das Campeãs).] | N41: 04:00 | O41: Sambodromo x JB | P41: 46074 | Q41: =LEFT(N41,2)&"h" -> 04h
A42: =IF(LEN(F42)>1,F42,G42)&O42&P42&Q42 -> 57264EG x Sambodromo4607417h | B42: =IF(LEN(F42)>1,F42,G42)&O42&P42 -> 57264EG x Sambodromo46074 | C42: =IF((IFERROR(IFERROR(VLOOKUP(A42,Controle_Utiliz!A:A,1,0),VLOOKUP(B42,Controle_Utiliz!B:B,1,0)),"Não Utilizou"))="Não Utilizou","Não Utilizou","Agendado") -> Agendado | D42: Alex Ananias Alves | E42: Globo | F42: 57264 | H42: 21964214422 | I42: ESTRATÉGIA E TECNOLOGIA | J42: IMAGEM EG | K42: FABIO LOEWENBACH CASCAO | L42: OPER CAMERA I | M42: EG x Sambódromo | Vai [CAMPEÃES, Sáb, 21-Fev (Desfile das Campeãs).] | N42: 17:00 | O42: EG x Sambodromo | P42: 46074 | Q42: =LEFT(N42,2)&"h" -> 17h
A43: =IF(LEN(F43)>1,F43,G43)&O43&P43&Q43 -> 57264Sambodromo x EG4607403h | B43: =IF(LEN(F43)>1,F43,G43)&O43&P43 -> 57264Sambodromo x EG46074 | C43: =IF((IFERROR(IFERROR(VLOOKUP(A43,Controle_Utiliz!A:A,1,0),VLOOKUP(B43,Controle_Utiliz!B:B,1,0)),"Não Utilizou"))="Não Utilizou","Não Utilizou","Agendado") -> Não Utilizou | D43: Alex Ananias Alves | E43: Globo | F43: 57264 | H43: 21964214422 | I43: ESTRATÉGIA E TECNOLOGIA | J43: IMAGEM EG | K43: FABIO LOEWENBACH CASCAO | L43: OPER CAMERA I | M43: Sambódromo x EG | Vem [CAMPEÃES, Sáb, 21-Fev (Desfile das Campeãs).] | N43: 03:00 | O43: Sambodromo x EG | P43: 46074 | Q43: =LEFT(N43,2)&"h" -> 03h
A44: =IF(LEN(F44)>1,F44,G44)&O44&P44&Q44 -> 28483JB x Sambodromo4606821h | B44: =IF(LEN(F44)>1,F44,G44)&O44&P44 -> 28483JB x Sambodromo46068 | C44: =IF((IFERROR(IFERROR(VLOOKUP(A44,Controle_Utiliz!A:A,1,0),VLOOKUP(B44,Controle_Utiliz!B:B,1,0)),"Não Utilizou"))="Não Utilizou","Não Utilizou","Agendado") -> Agendado | D44: Alex Fabiano Monteiro da Silva | E44: Globo | F44: 28483 | H44: 21984607295 | I44: ESTRATÉGIA E TECNOLOGIA | J44: COT E EXTERNA JB | K44: BEATHRIZ VERAS DE LIMA LOPES | L44: TEC SISTEMAS AUDIOVISUAIS II | M44: JB x Sambódromo | Vai [1º Dia, Dom, 15-Fev (Grupo Especial)] | N44: 21:00 | O44: JB x Sambodromo | P44: 46068 | Q44: =LEFT(N44,2)&"h" -> 21h
A45: =IF(LEN(F45)>1,F45,G45)&O45&P45&Q45 -> 28483JB x Sambodromo4606921h | B45: =IF(LEN(F45)>1,F45,G45)&O45&P45 -> 28483JB x Sambodromo46069 | C45: =IF((IFERROR(IFERROR(VLOOKUP(A45,Controle_Utiliz!A:A,1,0),VLOOKUP(B45,Controle_Utiliz!B:B,1,0)),"Não Utilizou"))="Não Utilizou","Não Utilizou","Agendado") -> Agendado | D45: Alex Fabiano Monteiro da Silva | E45: Globo | F45: 28483 | H45: 21984607295 | I45: ESTRATÉGIA E TECNOLOGIA | J45: COT E EXTERNA JB | K45: BEATHRIZ VERAS DE LIMA LOPES | L45: TEC SISTEMAS AUDIOVISUAIS II | M45: JB x Sambódromo | Vai [2º Dia, Seg, 16-Fev (Grupo Especial)] | N45: 21:00 | O45: JB x Sambodromo | P45: 46069 | Q45: =LEFT(N45,2)&"h" -> 21h
... A59: =IF(LEN(F59)>1,F59,G59)&O59&P59&Q59 -> 61171Sambodromo x JB4607402h | B59: =IF(LEN(F59)>1,F59,G59)&O59&P59 -> 61171Sambodromo x JB46074 | C59: =IF((IFERROR(IFERROR(VLOOKUP(A59,Controle_Utiliz!A:A,1,0),VLOOKUP(B59,Controle_Utiliz!B:B,1,0)),"Não Utilizou"))="Não Utilizou","Não Utilizou","Agendado") -> Não Utilizou | D59: Alexandre henderson de oliveira | E59: Globo | F59: 61171 | H59: 21980193534 | I59: JORNALISMO | J59: SUPERVISAO EDITORIA RJ | K59: PATRICIA DE ANDRADE PINTO | L59: REPORTER ESPECIAL I | M59: Sambódromo x JB | Vem [CAMPEÃES, Sáb, 21-Fev (Desfile das Campeãs).] | N59: 02:00 | O59: Sambodromo x JB | P59: 46074 | Q59: =LEFT(N59,2)&"h" -> 02h
A60: =IF(LEN(F60)>1,F60,G60)&O60&P60&Q60 -> 81362EG x Sambodromo4606819h | B60: =IF(LEN(F60)>1,F60,G60)&O60&P60 -> 81362EG x Sambodromo46068 | C60: =IF((IFERROR(IFERROR(VLOOKUP(A60,Controle_Utiliz!A:A,1,0),VLOOKUP(B60,Controle_Utiliz!B:B,1,0)),"Não Utilizou"))="Não Utilizou","Não Utilizou","Agendado") -> Agendado | D60: Alexandre Lima | E60: Globo | F60: 81362 | H60: 021999777060 | I60: JORNALISMO | J60: SUPERVISAO IMAGEM RJ | K60: EDUARDO ALBERTO FERNANDEZ | L60: REPORTER CINEMATOGRAFICO II | M60: EG x Sambódromo | Vai [1º Dia, Dom, 15-Fev (Grupo Especial)] | N60: 19:00 | O60: EG x Sambodromo | P60: 46068 | Q60: =LEFT(N60,2)&"h" -> 19h
A61: =IF(LEN(F61)>1,F61,G61)&O61&P61&Q61 -> 81362EG x Sambodromo4606919h | B61: =IF(LEN(F61)>1,F61,G61)&O61&P61 -> 81362EG x Sambodromo46069 | C61: =IF((IFERROR(IFERROR(VLOOKUP(A61,Controle_Utiliz!A:A,1,0),VLOOKUP(B61,Controle_Utiliz!B:B,1,0)),"Não Utilizou"))="Não Utilizou","Não Utilizou","Agendado") -> Agendado | D61: Alexandre Lima | E61: Globo | F61: 81362 | H61: 021999777060 | I61: JORNALISMO | J61: SUPERVISAO IMAGEM RJ | K61: EDUARDO ALBERTO FERNANDEZ | L61: REPORTER CINEMATOGRAFICO II | M61: EG x Sambódromo | Vai [2º Dia, Seg, 16-Fev (Grupo Especial)] | N61: 19:00 | O61: EG x Sambodromo | P61: 46069 | Q61: =LEFT(N61,2)&"h" -> 19h
A62: =IF(LEN(F62)>1,F62,G62)&O62&P62&Q62 -> 81362EG x Sambodromo4607019h | B62: =IF(LEN(F62)>1,F62,G62)&O62&P62 -> 81362EG x Sambodromo46070 | C62: =IF((IFERROR(IFERROR(VLOOKUP(A62,Controle_Utiliz!A:A,1,0),VLOOKUP(B62,Controle_Utiliz!B:B,1,0)),"Não Utilizou"))="Não Utilizou","Não Utilizou","Agendado") -> Agendado | D62: Alexandre Lima | E62: Globo | F62: 81362 | H62: 021999777060 | I62: JORNALISMO | J62: SUPERVISAO IMAGEM RJ | K62: EDUARDO ALBERTO FERNANDEZ | L62: REPORTER CINEMATOGRAFICO II | M62: EG x Sambódromo | Vai [3º Dia, Ter, 17-Fev (Grupo Especial)] | N62: 19:00 | O62: EG x Sambodromo | P62: 46070 | Q62: =LEFT(N62,2)&"h" -> 19h
A63: =IF(LEN(F63)>1,F63,G63)&O63&P63&Q63 -> 81362EG x Sambodromo4607419h | B63: =IF(LEN(F63)>1,F63,G63)&O63&P63 -> 81362EG x Sambodromo46074 | C63: =IF((IFERROR(IFERROR(VLOOKUP(A63,Controle_Utiliz!A:A,1,0),VLOOKUP(B63,Controle_Utiliz!B:B,1,0)),"Não Utilizou"))="Não Utilizou","Não Utilizou","Agendado") -> Não Utilizou | D63: Alexandre Lima | E63: Globo | F63: 81362 | H63: 021999777060 | I63: JORNALISMO | J63: SUPERVISAO IMAGEM RJ | K63: EDUARDO ALBERTO FERNANDEZ | L63: REPORTER CINEMATOGRAFICO II | M63: EG x Sambódromo | Vai [CAMPEÃES, Sáb, 21-Fev (Desfile das Campeãs).] | N63: 19:00 | O63: EG x Sambodromo | P63: 46074 | Q63: =LEFT(N63,2)&"h" -> 19h
A64: =IF(LEN(F64)>1,F64,G64)&O64&P64&Q64 -> 81362Sambodromo x EG4606806h | B64: =IF(LEN(F64)>1,F64,G64)&O64&P64 -> 81362Sambodromo x EG46068 | C64: =IF((IFERROR(IFERROR(VLOOKUP(A64,Controle_Utiliz!A:A,1,0),VLOOKUP(B64,Controle_Utiliz!B:B,1,0)),"Não Utilizou"))="Não Utilizou","Não Utilizou","Agendado") -> Agendado | D64: Alexandre Lima | E64: Globo | F64: 81362 | H64: 021999777060 | I64: JORNALISMO | J64: SUPERVISAO IMAGEM RJ | K64: EDUARDO ALBERTO FERNANDEZ | L64: REPORTER CINEMATOGRAFICO II | M64: Sambódromo x EG | Vem [1º Dia, Dom, 15-Fev (Grupo Especial)] | N64: 06:00 | O64: Sambodromo x EG | P64: 46068 | Q64: =LEFT(N64,2)&"h" -> 06h
A65: =IF(LEN(F65)>1,F65,G65)&O65&P65&Q65 -> 81362Sambodromo x EG4606906h | B65: =IF(LEN(F65)>1,F65,G65)&O65&P65 -> 81362Sambodromo x EG46069 | C65: =IF((IFERROR(IFERROR(VLOOKUP(A65,Controle_Utiliz!A:A,1,0),VLOOKUP(B65,Controle_Utiliz!B:B,1,0)),"Não Utilizou"))="Não Utilizou","Não Utilizou","Agendado") -> Agendado | D65: Alexandre Lima | E65: Globo | F65: 81362 | H65: 021999777060 | I65: JORNALISMO | J65: SUPERVISAO IMAGEM RJ | K65: EDUARDO ALBERTO FERNANDEZ | L65: REPORTER CINEMATOGRAFICO II | M65: Sambódromo x EG | Vem [2º Dia, Seg, 16-Fev (Grupo Especial)] | N65: 06:00 | O65: Sambodromo x EG | P65: 46069 | Q65: =LEFT(N65,2)&"h" -> 06h
A66: =IF(LEN(F66)>1,F66,G66)&O66&P66&Q66 -> 81362Sambodromo x EG4607006h | B66: =IF(LEN(F66)>1,F66,G66)&O66&P66 -> 81362Sambodromo x EG46070 | C66: =IF((IFERROR(IFERROR(VLOOKUP(A66,Controle_Utiliz!A:A,1,0),VLOOKUP(B66,Controle_Utiliz!B:B,1,0)),"Não Utilizou"))="Não Utilizou","Não Utilizou","Agendado") -> Não Utilizou | D66: Alexandre Lima | E66: Globo | F66: 81362 | H66: 021999777060 | I66: JORNALISMO | J66: SUPERVISAO IMAGEM RJ | K66: EDUARDO ALBERTO FERNANDEZ | L66: REPORTER CINEMATOGRAFICO II | M66: Sambódromo x EG | Vem [3º Dia, Ter, 17-Fev (Grupo Especial)] | N66: 06:00 | O66: Sambodromo x EG | P66: 46070 | Q66: =LEFT(N66,2)&"h" -> 06h
A67: =IF(LEN(F67)>1,F67,G67)&O67&P67&Q67 -> 81362Sambodromo x EG4607406h | B67: =IF(LEN(F67)>1,F67,G67)&O67&P67 -> 81362Sambodromo x EG46074 | C67: =IF((IFERROR(IFERROR(VLOOKUP(A67,Controle_Utiliz!A:A,1,0),VLOOKUP(B67,Controle_Utiliz!B:B,1,0)),"Não Utilizou"))="Não Utilizou","Não Utilizou","Agendado") -> Não Utilizou | D67: Alexandre Lima | E67: Globo | F67: 81362 | H67: 021999777060 | I67: JORNALISMO | J67: SUPERVISAO IMAGEM RJ | K67: EDUARDO ALBERTO FERNANDEZ | L67: REPORTER CINEMATOGRAFICO II | M67: Sambódromo x EG | Vem [CAMPEÃES, Sáb, 21-Fev (Desfile das Campeãs).] | N67: 06:00 | O67: Sambodromo x EG | P67: 46074 | Q67: =LEFT(N67,2)&"h" -> 06h
A68: =IF(LEN(F68)>1,F68,G68)&O68&P68&Q68 -> 55723JB x Sambodromo4607020h | B68: =IF(LEN(F68)>1,F68,G68)&O68&P68 -> 55723JB x Sambodromo46070 | C68: =IF((IFERROR(IFERROR(VLOOKUP(A68,Controle_Utiliz!A:A,1,0),VLOOKUP(B68,Controle_Utiliz!B:B,1,0)),"Não Utilizou"))="Não Utilizou","Não Utilizou","Agendado") -> Agendado | D68: ALINE GOMES CRUZ LIMA | E68: Globo | F68: 55723 | H68: 21975771631 | I68: JORNALISMO | J68: SUPERVISAO EDITORIA G1 01 03 - 01 | K68: TATIANA CALDAS MAGALHAES | L68: EDITOR II | M68: JB x Sambódromo | Vai [3º Dia, Ter, 17-Fev (Grupo Especial)] | N68: 20:00 | O68: JB x Sambodromo | P68: 46070 | Q68: =LEFT(N68,2)&"h" -> 20h
A69: =IF(LEN(F69)>1,F69,G69)&O69&P69&Q69 -> 55723Sambodromo x JB4607005h | B69: =IF(LEN(F69)>1,F69,G69)&O69&P69 -> 55723Sambodromo x JB46070 | C69: =IF((IFERROR(IFERROR(VLOOKUP(A69,Controle_Utiliz!A:A,1,0),VLOOKUP(B69,Controle_Utiliz!B:B,1,0)),"Não Utilizou"))="Não Utilizou","Não Utilizou","Agendado") -> Agendado | D69: ALINE GOMES CRUZ LIMA | E69: Globo | F69: 55723 | H69: 21975771631 | I69: JORNALISMO | J69: SUPERVISAO EDITORIA G1 01 03 - 01 | K69: TATIANA CALDAS MAGALHAES | L69: EDITOR II | M69: Sambódromo x JB | Vem [3º Dia, Ter, 17-Fev (Grupo Especial)] | N69: 05:00 | O69: Sambodromo x JB | P69: 46070 | Q69: =LEFT(N69,2)&"h" -> 05h
A70: =IF(LEN(F70)>1,F70,G70)&O70&P70&Q70 -> 53883EG x Sambodromo4606818h | B70: =IF(LEN(F70)>1,F70,G70)&O70&P70 -> 53883EG x Sambodromo46068 | C70: =IF((IFERROR(IFERROR(VLOOKUP(A70,Controle_Utiliz!A:A,1,0),VLOOKUP(B70,Controle_Utiliz!B:B,1,0)),"Não Utilizou"))="Não Utilizou","Não Utilizou","Agendado") -> Não Utilizou | D70: Alison Diogo Mayer | E70: Globo | F70: 53883 | H70: 21990765524 | I70: TV GLOBO | J70: SUPERVISAO PRODUCAO FUTEBOL II | K70: JANIR DE HOLLANDA FERREIRA JUNIOR | L70: PRODUTOR REPORTAGEM II | M70: EG x Sambódromo | Vai [1º Dia, Dom, 15-Fev (Grupo Especial)] | N70: 18:00 | O70: EG x Sambodromo | P70: 46068 | Q70: =LEFT(N70,2)&"h" -> 18h
A71: =IF(LEN(F71)>1,F71,G71)&O71&P71&Q71 -> 53883EG x Sambodromo4606918h | B71: =IF(LEN(F71)>1,F71,G71)&O71&P71 -> 53883EG x Sambodromo46069 | C71: =IF((IFERROR(IFERROR(VLOOKUP(A71,Controle_Utiliz!A:A,1,0),VLOOKUP(B71,Controle_Utiliz!B:B,1,0)),"Não Utilizou"))="Não Utilizou","Não Utilizou","Agendado") -> Não Utilizou | D71: Alison Diogo Mayer | E71: Globo | F71: 53883 | H71: 21990765524 | I71: TV GLOBO | J71: SUPERVISAO PRODUCAO FUTEBOL II | K71: JANIR DE HOLLANDA FERREIRA JUNIOR | L71: PRODUTOR REPORTAGEM II | M71: EG x Sambódromo | Vai [2º Dia, Seg, 16-Fev (Grupo Especial)] | N71: 18:00 | O71: EG x Sambodromo | P71: 46069 | Q71: =LEFT(N71,2)&"h" -> 18h
A72: =IF(LEN(F72)>1,F72,G72)&O72&P72&Q72 -> 53883EG x Sambodromo4607018h | B72: =IF(LEN(F72)>1,F72,G72)&O72&P72 -> 53883EG x Sambodromo46070 | C72: =IF((IFERROR(IFERROR(VLOOKUP(A72,Controle_Utiliz!A:A,1,0),VLOOKUP(B72,Controle_Utiliz!B:B,1,0)),"Não Utilizou"))="Não Utilizou","Não Utilizou","Agendado") -> Não Utilizou | D72: Alison Diogo Mayer | E72: Globo | F72: 53883 | H72: 21990765524 | I72: TV GLOBO | J72: SUPERVISAO PRODUCAO FUTEBOL II | K72: JANIR DE HOLLANDA FERREIRA JUNIOR | L72: PRODUTOR REPORTAGEM II | M72: EG x Sambódromo | Vai [3º Dia, Ter, 17-Fev (Grupo Especial)] | N72: 18:00 | O72: EG x Sambodromo | P72: 46070 | Q72: =LEFT(N72,2)&"h" -> 18h
A73: =IF(LEN(F73)>1,F73,G73)&O73&P73&Q73 -> 53883EG x Sambodromo4607418h | B73: =IF(LEN(F73)>1,F73,G73)&O73&P73 -> 53883EG x Sambodromo46074 | C73: =IF((IFERROR(IFERROR(VLOOKUP(A73,Controle_Utiliz!A:A,1,0),VLOOKUP(B73,Controle_Utiliz!B:B,1,0)),"Não Utilizou"))="Não Utilizou","Não Utilizou","Agendado") -> Não Utilizou | D73: Alison Diogo Mayer | E73: Globo | F73: 53883 | H73: 21990765524 | I73: TV GLOBO | J73: SUPERVISAO PRODUCAO FUTEBOL II | K73: JANIR DE HOLLANDA FERREIRA JUNIOR | L73: PRODUTOR REPORTAGEM II | M73: EG x Sambódromo | Vai [CAMPEÃES, Sáb, 21-Fev (Desfile das Campeãs).] | N73: 18:00 | O73: EG x Sambodromo | P73: 46074 | Q73: =LEFT(N73,2)&"h" -> 18h
A74: =IF(LEN(F74)>1,F74,G74)&O74&P74&Q74 -> 53883Sambodromo x EG4606802h | B74: =IF(LEN(F74)>1,F74,G74)&O74&P74 -> 53883Sambodromo x EG46068 | C74: =IF((IFERROR(IFERROR(VLOOKUP(A74,Controle_Utiliz!A:A,1,0),VLOOKUP(B74,Controle_Utiliz!B:B,1,0)),"Não Utilizou"))="Não Utilizou","Não Utilizou","Agendado") -> Não Utilizou | D74: Alison Diogo Mayer | E74: Globo | F74: 53883 | H74: 21990765524 | I74: TV GLOBO | J74: SUPERVISAO PRODUCAO FUTEBOL II | K74: JANIR DE HOLLANDA FERREIRA JUNIOR | L74: PRODUTOR REPORTAGEM II | M74: Sambódromo x EG | Vem [1º Dia, Dom, 15-Fev (Grupo Especial)] | N74: 02:00 | O74: Sambodromo x EG | P74: 46068 | Q74: =LEFT(N74,2)&"h" -> 02h
A75: =IF(LEN(F75)>1,F75,G75)&O75&P75&Q75 -> 53883Sambodromo x EG4606902h | B75: =IF(LEN(F75)>1,F75,G75)&O75&P75 -> 53883Sambodromo x EG46069 | C75: =IF((IFERROR(IFERROR(VLOOKUP(A75,Controle_Utiliz!A:A,1,0),VLOOKUP(B75,Controle_Utiliz!B:B,1,0)),"Não Utilizou"))="Não Utilizou","Não Utilizou","Agendado") -> Não Utilizou | D75: Alison Diogo Mayer | E75: Globo | F75: 53883 | H75: 21990765524 | I75: TV GLOBO | J75: SUPERVISAO PRODUCAO FUTEBOL II | K75: JANIR DE HOLLANDA FERREIRA JUNIOR | L75: PRODUTOR REPORTAGEM II | M75: Sambódromo x EG | Vem [2º Dia, Seg, 16-Fev (Grupo Especial)] | N75: 02:00 | O75: Sambodromo x EG | P75: 46069 | Q75: =LEFT(N75,2)&"h" -> 02h
A76: =IF(LEN(F76)>1,F76,G76)&O76&P76&Q76 -> 53883Sambodromo x EG4607002h | B76: =IF(LEN(F76)>1,F76,G76)&O76&P76 -> 53883Sambodromo x EG46070 | C76: =IF((IFERROR(IFERROR(VLOOKUP(A76,Controle_Utiliz!A:A,1,0),VLOOKUP(B76,Controle_Utiliz!B:B,1,0)),"Não Utilizou"))="Não Utilizou","Não Utilizou","Agendado") -> Não Utilizou | D76: Alison Diogo Mayer | E76: Globo | F76: 53883 | H76: 21990765524 | I76: TV GLOBO | J76: SUPERVISAO PRODUCAO FUTEBOL II | K76: JANIR DE HOLLANDA FERREIRA JUNIOR | L76: PRODUTOR REPORTAGEM II | M76: Sambódromo x EG | Vem [3º Dia, Ter, 17-Fev (Grupo Especial)] | N76: 02:00 | O76: Sambodromo x EG | P76: 46070 | Q76: =LEFT(N76,2)&"h" -> 02h
A77: =IF(LEN(F77)>1,F77,G77)&O77&P77&Q77 -> 53883Sambodromo x EG4607402h | B77: =IF(LEN(F77)>1,F77,G77)&O77&P77 -> 53883Sambodromo x EG46074 | C77: =IF((IFERROR(IFERROR(VLOOKUP(A77,Controle_Utiliz!A:A,1,0),VLOOKUP(B77,Controle_Utiliz!B:B,1,0)),"Não Utilizou"))="Não Utilizou","Não Utilizou","Agendado") -> Não Utilizou | D77: Alison Diogo Mayer | E77: Globo | F77: 53883 | H77: 21990765524 | I77: TV GLOBO | J77: SUPERVISAO PRODUCAO FUTEBOL II | K77: JANIR DE HOLLANDA FERREIRA JUNIOR | L77: PRODUTOR REPORTAGEM II | M77: Sambódromo x EG | Vem [CAMPEÃES, Sáb, 21-Fev (Desfile das Campeãs).] | N77: 02:00 | O77: Sambodromo x EG | P77: 46074 | Q77: =LEFT(N77,2)&"h" -> 02h
A78: =IF(LEN(F78)>1,F78,G78)&O78&P78&Q78 -> 53883JB x Sambodromo4606818h | B78: =IF(LEN(F78)>1,F78,G78)&O78&P78 -> 53883JB x Sambodromo46068 | C78: =IF((IFERROR(IFERROR(VLOOKUP(A78,Controle_Utiliz!A:A,1,0),VLOOKUP(B78,Controle_Utiliz!B:B,1,0)),"Não Utilizou"))="Não Utilizou","Não Utilizou","Agendado") -> Não Utilizou | D78: Alison Diogo Mayer | E78: Globo | F78: 53883 | H78: 21990765524 | I78: TV GLOBO | J78: SUPERVISAO PRODUCAO FUTEBOL II | K78: JANIR DE HOLLANDA FERREIRA JUNIOR | L78: PRODUTOR REPORTAGEM II | M78: JB x Sambódromo | Vai [1º Dia, Dom, 15-Fev (Grupo Especial)] | N78: 18:00 | O78: JB x Sambodromo | P78: 46068 | Q78: =LEFT(N78,2)&"h" -> 18h
A79: =IF(LEN(F79)>1,F79,G79)&O79&P79&Q79 -> 53883JB x Sambodromo4606918h | B79: =IF(LEN(F79)>1,F79,G79)&O79&P79 -> 53883JB x Sambodromo46069 | C79: =IF((IFERROR(IFERROR(VLOOKUP(A79,Controle_Utiliz!A:A,1,0),VLOOKUP(B79,Controle_Utiliz!B:B,1,0)),"Não Utilizou"))="Não Utilizou","Não Utilizou","Agendado") -> Não Utilizou | D79: Alison Diogo Mayer | E79: Globo | F79: 53883 | H79: 21990765524 | I79: TV GLOBO | J79: SUPERVISAO PRODUCAO FUTEBOL II | K79: JANIR DE HOLLANDA FERREIRA JUNIOR | L79: PRODUTOR REPORTAGEM II | M79: JB x Sambódromo | Vai [2º Dia, Seg, 16-Fev (Grupo Especial)] | N79: 18:00 | O79: JB x Sambodromo | P79: 46069 | Q79: =LEFT(N79,2)&"h" -> 18h
... A89: =IF(LEN(F89)>1,F89,G89)&O89&P89&Q89 -> 72182Sambodromo x JB4607400h | B89: =IF(LEN(F89)>1,F89,G89)&O89&P89 -> 72182Sambodromo x JB46074 | C89: =IF((IFERROR(IFERROR(VLOOKUP(A89,Controle_Utiliz!A:A,1,0),VLOOKUP(B89,Controle_Utiliz!B:B,1,0)),"Não Utilizou"))="Não Utilizou","Não Utilizou","Agendado") -> Não Utilizou | D89: ALLISSON RODRIGUES DE MESQUITA LORETE | E89: Globo | F89: 72182 | H89: 21976822484 | I89: ESTRATÉGIA E TECNOLOGIA | J89: PARCERIAS DE SUSTENTACAO RJ - ION | K89: MARCELO AUGUSTO PINTO DE MAGALHAES | L89: ANL SOLUCOES MIDIAS II | M89: Sambódromo x JB | Vem [CAMPEÃES, Sáb, 21-Fev (Desfile das Campeãs).] | N89: 00:00 | O89: Sambodromo x JB | P89: 46074 | Q89: =LEFT(N89,2)&"h" -> 00h
A90: =IF(LEN(F90)>1,F90,G90)&O90&P90&Q90 -> 20254274765EG x Sambodromo4606820h | B90: =IF(LEN(F90)>1,F90,G90)&O90&P90 -> 20254274765EG x Sambodromo46068 | C90: =IF((IFERROR(IFERROR(VLOOKUP(A90,Controle_Utiliz!A:A,1,0),VLOOKUP(B90,Controle_Utiliz!B:B,1,0)),"Não Utilizou"))="Não Utilizou","Não Utilizou","Agendado") -> Não Utilizou | D90: Alvaro Sousa da Silveira | E90: Áudio equipe | G90: 20254274765 | H90: 21999284065 | I90: ESTRATÉGIA E TECNOLOGIA | J90: Áudio equipe | K90: Áudio equipe | L90: Áudio equipe | M90: EG x Sambódromo | Vai [1º Dia, Dom, 15-Fev (Grupo Especial)] | N90: 20:00 | O90: EG x Sambodromo | P90: 46068 | Q90: =LEFT(N90,2)&"h" -> 20h
A91: =IF(LEN(F91)>1,F91,G91)&O91&P91&Q91 -> 20254274765EG x Sambodromo4606920h | B91: =IF(LEN(F91)>1,F91,G91)&O91&P91 -> 20254274765EG x Sambodromo46069 | C91: =IF((IFERROR(IFERROR(VLOOKUP(A91,Controle_Utiliz!A:A,1,0),VLOOKUP(B91,Controle_Utiliz!B:B,1,0)),"Não Utilizou"))="Não Utilizou","Não Utilizou","Agendado") -> Não Utilizou | D91: Alvaro Sousa da Silveira | E91: Áudio equipe | G91: 20254274765 | H91: 21999284065 | I91: ESTRATÉGIA E TECNOLOGIA | J91: Áudio equipe | K91: Áudio equipe | L91: Áudio equipe | M91: EG x Sambódromo | Vai [2º Dia, Seg, 16-Fev (Grupo Especial)] | N91: 20:00 | O91: EG x Sambodromo | P91: 46069 | Q91: =LEFT(N91,2)&"h" -> 20h
A92: =IF(LEN(F92)>1,F92,G92)&O92&P92&Q92 -> 20254274765EG x Sambodromo4607020h | B92: =IF(LEN(F92)>1,F92,G92)&O92&P92 -> 20254274765EG x Sambodromo46070 | C92: =IF((IFERROR(IFERROR(VLOOKUP(A92,Controle_Utiliz!A:A,1,0),VLOOKUP(B92,Controle_Utiliz!B:B,1,0)),"Não Utilizou"))="Não Utilizou","Não Utilizou","Agendado") -> Não Utilizou | D92: Alvaro Sousa da Silveira | E92: Áudio equipe | G92: 20254274765 | H92: 21999284065 | I92: ESTRATÉGIA E TECNOLOGIA | J92: Áudio equipe | K92: Áudio equipe | L92: Áudio equipe | M92: EG x Sambódromo | Vai [3º Dia, Ter, 17-Fev (Grupo Especial)] | N92: 20:00 | O92: EG x Sambodromo | P92: 46070 | Q92: =LEFT(N92,2)&"h" -> 20h
A93: =IF(LEN(F93)>1,F93,G93)&O93&P93&Q93 -> 20254274765Sambodromo x EG4606807h | B93: =IF(LEN(F93)>1,F93,G93)&O93&P93 -> 20254274765Sambodromo x EG46068 | C93: =IF((IFERROR(IFERROR(VLOOKUP(A93,Controle_Utiliz!A:A,1,0),VLOOKUP(B93,Controle_Utiliz!B:B,1,0)),"Não Utilizou"))="Não Utilizou","Não Utilizou","Agendado") -> Não Utilizou | D93: Alvaro Sousa da Silveira | E93: Áudio equipe | G93: 20254274765 | H93: 21999284065 | I93: ESTRATÉGIA E TECNOLOGIA | J93: Áudio equipe | K93: Áudio equipe | L93: Áudio equipe | M93: Sambódromo x EG | Vem [1º Dia, Dom, 15-Fev (Grupo Especial)] | N93: 07:00 | O93: Sambodromo x EG | P93: 46068 | Q93: =LEFT(N93,2)&"h" -> 07h
A94: =IF(LEN(F94)>1,F94,G94)&O94&P94&Q94 -> 20254274765Sambodromo x EG4606907h | B94: =IF(LEN(F94)>1,F94,G94)&O94&P94 -> 20254274765Sambodromo x EG46069 | C94: =IF((IFERROR(IFERROR(VLOOKUP(A94,Controle_Utiliz!A:A,1,0),VLOOKUP(B94,Controle_Utiliz!B:B,1,0)),"Não Utilizou"))="Não Utilizou","Não Utilizou","Agendado") -> Não Utilizou | D94: Alvaro Sousa da Silveira | E94: Áudio equipe | G94: 20254274765 | H94: 21999284065 | I94: ESTRATÉGIA E TECNOLOGIA | J94: Áudio equipe | K94: Áudio equipe | L94: Áudio equipe | M94: Sambódromo x EG | Vem [2º Dia, Seg, 16-Fev (Grupo Especial)] | N94: 07:00 | O94: Sambodromo x EG | P94: 46069 | Q94: =LEFT(N94,2)&"h" -> 07h
A95: =IF(LEN(F95)>1,F95,G95)&O95&P95&Q95 -> 20254274765Sambodromo x EG4607007h | B95: =IF(LEN(F95)>1,F95,G95)&O95&P95 -> 20254274765Sambodromo x EG46070 | C95: =IF((IFERROR(IFERROR(VLOOKUP(A95,Controle_Utiliz!A:A,1,0),VLOOKUP(B95,Controle_Utiliz!B:B,1,0)),"Não Utilizou"))="Não Utilizou","Não Utilizou","Agendado") -> Não Utilizou | D95: Alvaro Sousa da Silveira | E95: Áudio equipe | G95: 20254274765 | H95: 21999284065 | I95: ESTRATÉGIA E TECNOLOGIA | J95: Áudio equipe | K95: Áudio equipe | L95: Áudio equipe | M95: Sambódromo x EG | Vem [3º Dia, Ter, 17-Fev (Grupo Especial)] | N95: 07:00 | O95: Sambodromo x EG | P95: 46070 | Q95: =LEFT(N95,2)&"h" -> 07h
A96: =IF(LEN(F96)>1,F96,G96)&O96&P96&Q96 -> 41204EG x Sambodromo4606817h | B96: =IF(LEN(F96)>1,F96,G96)&O96&P96 -> 41204EG x Sambodromo46068 | C96: =IF((IFERROR(IFERROR(VLOOKUP(A96,Controle_Utiliz!A:A,1,0),VLOOKUP(B96,Controle_Utiliz!B:B,1,0)),"Não Utilizou"))="Não Utilizou","Não Utilizou","Agendado") -> Agendado | D96: Anderson Guimarães | E96: Globo | F96: 41204 | H96: 964927037 | I96: TV GLOBO | J96: IMAGEM EG | K96: FABIO LOEWENBACH CASCAO | L96: OPER CAMERA IV | M96: EG x Sambódromo | Vai [1º Dia, Dom, 15-Fev (Grupo Especial)] | N96: 17:00 | O96: EG x Sambodromo | P96: 46068 | Q96: =LEFT(N96,2)&"h" -> 17h
A97: =IF(LEN(F97)>1,F97,G97)&O97&P97&Q97 -> 41204EG x Sambodromo4606918h | B97: =IF(LEN(F97)>1,F97,G97)&O97&P97 -> 41204EG x Sambodromo46069 | C97: =IF((IFERROR(IFERROR(VLOOKUP(A97,Controle_Utiliz!A:A,1,0),VLOOKUP(B97,Controle_Utiliz!B:B,1,0)),"Não Utilizou"))="Não Utilizou","Não Utilizou","Agendado") -> Não Utilizou | D97: Anderson Guimarães | E97: Globo | F97: 41204 | H97: 964927037 | I97: TV GLOBO | J97: IMAGEM EG | K97: FABIO LOEWENBACH CASCAO | L97: OPER CAMERA IV | M97: EG x Sambódromo | Vai [2º Dia, Seg, 16-Fev (Grupo Especial)] | N97: 18:00 | O97: EG x Sambodromo | P97: 46069 | Q97: =LEFT(N97,2)&"h" -> 18h
A98: =IF(LEN(F98)>1,F98,G98)&O98&P98&Q98 -> 41204EG x Sambodromo4607018h | B98: =IF(LEN(F98)>1,F98,G98)&O98&P98 -> 41204EG x Sambodromo46070 | C98: =IF((IFERROR(IFERROR(VLOOKUP(A98,Controle_Utiliz!A:A,1,0),VLOOKUP(B98,Controle_Utiliz!B:B,1,0)),"Não Utilizou"))="Não Utilizou","Não Utilizou","Agendado") -> Agendado | D98: Anderson Guimarães | E98: Globo | F98: 41204 | H98: 964927037 | I98: TV GLOBO | J98: IMAGEM EG | K98: FABIO LOEWENBACH CASCAO | L98: OPER CAMERA IV | M98: EG x Sambódromo | Vai [3º Dia, Ter, 17-Fev (Grupo Especial)] | N98: 18:00 | O98: EG x Sambodromo | P98: 46070 | Q98: =LEFT(N98,2)&"h" -> 18h
A99: =IF(LEN(F99)>1,F99,G99)&O99&P99&Q99 -> 41204EG x Sambodromo4607418h | B99: =IF(LEN(F99)>1,F99,G99)&O99&P99 -> 41204EG x Sambodromo46074 | C99: =IF((IFERROR(IFERROR(VLOOKUP(A99,Controle_Utiliz!A:A,1,0),VLOOKUP(B99,Controle_Utiliz!B:B,1,0)),"Não Utilizou"))="Não Utilizou","Não Utilizou","Agendado") -> Agendado | D99: Anderson Guimarães | E99: Globo | F99: 41204 | H99: 964927037 | I99: TV GLOBO | J99: IMAGEM EG | K99: FABIO LOEWENBACH CASCAO | L99: OPER CAMERA IV | M99: EG x Sambódromo | Vai [CAMPEÃES, Sáb, 21-Fev (Desfile das Campeãs).] | N99: 18:00 | O99: EG x Sambodromo | P99: 46074 | Q99: =LEFT(N99,2)&"h" -> 18h
A100: =IF(LEN(F100)>1,F100,G100)&O100&P100&Q100 -> 41204Sambodromo x EG4606801h | B100: =IF(LEN(F100)>1,F100,G100)&O100&P100 -> 41204Sambodromo x EG46068 | C100: =IF((IFERROR(IFERROR(VLOOKUP(A100,Controle_Utiliz!A:A,1,0),VLOOKUP(B100,Controle_Utiliz!B:B,1,0)),"Não Utilizou"))="Não Utilizou","Não Utilizou","Agendado") -> Agendado | D100: Anderson Guimarães | E100: Globo | F100: 41204 | H100: 964927037 | I100: TV GLOBO | J100: IMAGEM EG | K100: FABIO LOEWENBACH CASCAO | L100: OPER CAMERA IV | M100: Sambódromo x EG | Vem [1º Dia, Dom, 15-Fev (Grupo Especial)] | N100: 01:00 | O100: Sambodromo x EG | P100: 46068 | Q100: =LEFT(N100,2)&"h" -> 01h
A101: =IF(LEN(F101)>1,F101,G101)&O101&P101&Q101 -> 41204Sambodromo x EG4606902h | B101: =IF(LEN(F101)>1,F101,G101)&O101&P101 -> 41204Sambodromo x EG46069 | C101: =IF((IFERROR(IFERROR(VLOOKUP(A101,Controle_Utiliz!A:A,1,0),VLOOKUP(B101,Controle_Utiliz!B:B,1,0)),"Não Utilizou"))="Não Utilizou","Não Utilizou","Agendado") -> Agendado | D101: Anderson Guimarães | E101: Globo | F101: 41204 | H101: 964927037 | I101: TV GLOBO | J101: IMAGEM EG | K101: FABIO LOEWENBACH CASCAO | L101: OPER CAMERA IV | M101: Sambódromo x EG | Vem [2º Dia, Seg, 16-Fev (Grupo Especial)] | N101: 02:00 | O101: Sambodromo x EG | P101: 46069 | Q101: =LEFT(N101,2)&"h" -> 02h
A102: =IF(LEN(F102)>1,F102,G102)&O102&P102&Q102 -> 41204Sambodromo x EG4607001h | B102: =IF(LEN(F102)>1,F102,G102)&O102&P102 -> 41204Sambodromo x EG46070 | C102: =IF((IFERROR(IFERROR(VLOOKUP(A102,Controle_Utiliz!A:A,1,0),VLOOKUP(B102,Controle_Utiliz!B:B,1,0)),"Não Utilizou"))="Não Utilizou","Não Utilizou","Agendado") -> Agendado | D102: Anderson Guimarães | E102: Globo | F102: 41204 | H102: 964927037 | I102: TV GLOBO | J102: IMAGEM EG | K102: FABIO LOEWENBACH CASCAO | L102: OPER CAMERA IV | M102: Sambódromo x EG | Vem [3º Dia, Ter, 17-Fev (Grupo Especial)] | N102: 01:00 | O102: Sambodromo x EG | P102: 46070 | Q102: =LEFT(N102,2)&"h" -> 01h
A103: =IF(LEN(F103)>1,F103,G103)&O103&P103&Q103 -> 41204Sambodromo x EG4607401h | B103: =IF(LEN(F103)>1,F103,G103)&O103&P103 -> 41204Sambodromo x EG46074 | C103: =IF((IFERROR(IFERROR(VLOOKUP(A103,Controle_Utiliz!A:A,1,0),VLOOKUP(B103,Controle_Utiliz!B:B,1,0)),"Não Utilizou"))="Não Utilizou","Não Utilizou","Agendado") -> Agendado | D103: Anderson Guimarães | E103: Globo | F103: 41204 | H103: 964927037 | I103: TV GLOBO | J103: IMAGEM EG | K103: FABIO LOEWENBACH CASCAO | L103: OPER CAMERA IV | M103: Sambódromo x EG | Vem [CAMPEÃES, Sáb, 21-Fev (Desfile das Campeãs).] | N103: 01:00 | O103: Sambodromo x EG | P103: 46074 | Q103: =LEFT(N103,2)&"h" -> 01h
A104: =IF(LEN(F104)>1,F104,G104)&O104&P104&Q104 -> 09408235789EG x Sambodromo4606817h | B104: =IF(LEN(F104)>1,F104,G104)&O104&P104 -> 09408235789EG x Sambodromo46068 | C104: =IF((IFERROR(IFERROR(VLOOKUP(A104,Controle_Utiliz!A:A,1,0),VLOOKUP(B104,Controle_Utiliz!B:B,1,0)),"Não Utilizou"))="Não Utilizou","Não Utilizou","Agendado") -> Não Utilizou | D104: André Alan Lima Braga | E104: MyView Drones | G104: 09408235789 | H104: 21983737172 | I104: TV GLOBO | J104: MyView Drones | K104: MyView Drones | L104: MyView Drones | M104: EG x Sambódromo | Vai [1º Dia, Dom, 15-Fev (Grupo Especial)] | N104: 17:00 | O104: EG x Sambodromo | P104: 46068 | Q104: =LEFT(N104,2)&"h" -> 17h
A105: =IF(LEN(F105)>1,F105,G105)&O105&P105&Q105 -> 09408235789EG x Sambodromo4606917h | B105: =IF(LEN(F105)>1,F105,G105)&O105&P105 -> 09408235789EG x Sambodromo46069 | C105: =IF((IFERROR(IFERROR(VLOOKUP(A105,Controle_Utiliz!A:A,1,0),VLOOKUP(B105,Controle_Utiliz!B:B,1,0)),"Não Utilizou"))="Não Utilizou","Não Utilizou","Agendado") -> Não Utilizou | D105: André Alan Lima Braga | E105: MyView Drones | G105: 09408235789 | H105: 21983737172 | I105: TV GLOBO | J105: MyView Drones | K105: MyView Drones | L105: MyView Drones | M105: EG x Sambódromo | Vai [2º Dia, Seg, 16-Fev (Grupo Especial)] | N105: 17:00 | O105: EG x Sambodromo | P105: 46069 | Q105: =LEFT(N105,2)&"h" -> 17h
A106: =IF(LEN(F106)>1,F106,G106)&O106&P106&Q106 -> 09408235789EG x Sambodromo4607017h | B106: =IF(LEN(F106)>1,F106,G106)&O106&P106 -> 09408235789EG x Sambodromo46070 | C106: =IF((IFERROR(IFERROR(VLOOKUP(A106,Controle_Utiliz!A:A,1,0),VLOOKUP(B106,Controle_Utiliz!B:B,1,0)),"Não Utilizou"))="Não Utilizou","Não Utilizou","Agendado") -> Agendado | D106: André Alan Lima Braga | E106: MyView Drones | G106: 09408235789 | H106: 21983737172 | I106: TV GLOBO | J106: MyView Drones | K106: MyView Drones | L106: MyView Drones | M106: EG x Sambódromo | Vai [3º Dia, Ter, 17-Fev (Grupo Especial)] | N106: 17:00 | O106: EG x Sambodromo | P106: 46070 | Q106: =LEFT(N106,2)&"h" -> 17h
A107: =IF(LEN(F107)>1,F107,G107)&O107&P107&Q107 -> 09408235789EG x Sambodromo4607417h | B107: =IF(LEN(F107)>1,F107,G107)&O107&P107 -> 09408235789EG x Sambodromo46074 | C107: =IF((IFERROR(IFERROR(VLOOKUP(A107,Controle_Utiliz!A:A,1,0),VLOOKUP(B107,Controle_Utiliz!B:B,1,0)),"Não Utilizou"))="Não Utilizou","Não Utilizou","Agendado") -> Agendado | D107: André Alan Lima Braga | E107: MyView Drones | G107: 09408235789 | H107: 21983737172 | I107: TV GLOBO | J107: MyView Drones | K107: MyView Drones | L107: MyView Drones | M107: EG x Sambódromo | Vai [CAMPEÃES, Sáb, 21-Fev (Desfile das Campeãs).] | N107: 17:00 | O107: EG x Sambodromo | P107: 46074 | Q107: =LEFT(N107,2)&"h" -> 17h
A108: =IF(LEN(F108)>1,F108,G108)&O108&P108&Q108 -> 09408235789Sambodromo x EG4606808h | B108: =IF(LEN(F108)>1,F108,G108)&O108&P108 -> 09408235789Sambodromo x EG46068 | C108: =IF((IFERROR(IFERROR(VLOOKUP(A108,Controle_Utiliz!A:A,1,0),VLOOKUP(B108,Controle_Utiliz!B:B,1,0)),"Não Utilizou"))="Não Utilizou","Não Utilizou","Agendado") -> Não Utilizou | D108: André Alan Lima Braga | E108: MyView Drones | G108: 09408235789 | H108: 21983737172 | I108: TV GLOBO | J108: MyView Drones | K108: MyView Drones | L108: MyView Drones | M108: Sambódromo x EG | Vem [1º Dia, Dom, 15-Fev (Grupo Especial)] | N108: 08:00 | O108: Sambodromo x EG | P108: 46068 | Q108: =LEFT(N108,2)&"h" -> 08h
A109: =IF(LEN(F109)>1,F109,G109)&O109&P109&Q109 -> 09408235789Sambodromo x EG4606908h | B109: =IF(LEN(F109)>1,F109,G109)&O109&P109 -> 09408235789Sambodromo x EG46069 | C109: =IF((IFERROR(IFERROR(VLOOKUP(A109,Controle_Utiliz!A:A,1,0),VLOOKUP(B109,Controle_Utiliz!B:B,1,0)),"Não Utilizou"))="Não Utilizou","Não Utilizou","Agendado") -> Não Utilizou | D109: André Alan Lima Braga | E109: MyView Drones | G109: 09408235789 | H109: 21983737172 | I109: TV GLOBO | J109: MyView Drones | K109: MyView Drones | L109: MyView Drones | M109: Sambódromo x EG | Vem [2º Dia, Seg, 16-Fev (Grupo Especial)] | N109: 08:00 | O109: Sambodromo x EG | P109: 46069 | Q109: =LEFT(N109,2)&"h" -> 08h
A110: =IF(LEN(F110)>1,F110,G110)&O110&P110&Q110 -> 09408235789Sambodromo x EG4607008h | B110: =IF(LEN(F110)>1,F110,G110)&O110&P110 -> 09408235789Sambodromo x EG46070 | C110: =IF((IFERROR(IFERROR(VLOOKUP(A110,Controle_Utiliz!A:A,1,0),VLOOKUP(B110,Controle_Utiliz!B:B,1,0)),"Não Utilizou"))="Não Utilizou","Não Utilizou","Agendado") -> Agendado | D110: André Alan Lima Braga | E110: MyView Drones | G110: 09408235789 | H110: 21983737172 | I110: TV GLOBO | J110: MyView Drones | K110: MyView Drones | L110: MyView Drones | M110: Sambódromo x EG | Vem [3º Dia, Ter, 17-Fev (Grupo Especial)] | N110: 08:00 | O110: Sambodromo x EG | P110: 46070 | Q110: =LEFT(N110,2)&"h" -> 08h
A111: =IF(LEN(F111)>1,F111,G111)&O111&P111&Q111 -> 09408235789Sambodromo x EG4607408h | B111: =IF(LEN(F111)>1,F111,G111)&O111&P111 -> 09408235789Sambodromo x EG46074 | C111: =IF((IFERROR(IFERROR(VLOOKUP(A111,Controle_Utiliz!A:A,1,0),VLOOKUP(B111,Controle_Utiliz!B:B,1,0)),"Não Utilizou"))="Não Utilizou","Não Utilizou","Agendado") -> Não Utilizou | D111: André Alan Lima Braga | E111: MyView Drones | G111: 09408235789 | H111: 21983737172 | I111: TV GLOBO | J111: MyView Drones | K111: MyView Drones | L111: MyView Drones | M111: Sambódromo x EG | Vem [CAMPEÃES, Sáb, 21-Fev (Desfile das Campeãs).] | N111: 08:00 | O111: Sambodromo x EG | P111: 46074 | Q111: =LEFT(N111,2)&"h" -> 08h
A112: =IF(LEN(F112)>1,F112,G112)&O112&P112&Q112 -> 84109EG x Sambodromo4606919h | B112: =IF(LEN(F112)>1,F112,G112)&O112&P112 -> 84109EG x Sambodromo46069 | C112: =IF((IFERROR(IFERROR(VLOOKUP(A112,Controle_Utiliz!A:A,1,0),VLOOKUP(B112,Controle_Utiliz!B:B,1,0)),"Não Utilizou"))="Não Utilizou","Não Utilizou","Agendado") -> Agendado | D112: Antonio Marcos Basilio Menezes | E112: Globo | F112: 84109 | H112: 21993615441 | I112: FJI - CSC OGA | J112: CONSERVACAO PREDIAL EG | K112: BRUNO DA CAMARA RIBEIRO | L112: ASSIST OPERACOES PREDIAIS | M112: EG x Sambódromo | Vai [2º Dia, Seg, 16-Fev (Grupo Especial)] | N112: 19:00 | O112: EG x Sambodromo | P112: 46069 | Q112: =LEFT(N112,2)&"h" -> 19h
A113: =IF(LEN(F113)>1,F113,G113)&O113&P113&Q113 -> 84109EG x Sambodromo4607421h | B113: =IF(LEN(F113)>1,F113,G113)&O113&P113 -> 84109EG x Sambodromo46074 | C113: =IF((IFERROR(IFERROR(VLOOKUP(A113,Controle_Utiliz!A:A,1,0),VLOOKUP(B113,Controle_Utiliz!B:B,1,0)),"Não Utilizou"))="Não Utilizou","Não Utilizou","Agendado") -> Agendado | D113: Antonio Marcos Basilio Menezes | E113: Globo | F113: 84109 | H113: 21993615441 | I113: FJI - CSC OGA | J113: CONSERVACAO PREDIAL EG | K113: BRUNO DA CAMARA RIBEIRO | L113: ASSIST OPERACOES PREDIAIS | M113: EG x Sambódromo | Vai [CAMPEÃES, Sáb, 21-Fev (Desfile das Campeãs).] | N113: 21:00 | O113: EG x Sambodromo | P113: 46074 | Q113: =LEFT(N113,2)&"h" -> 21h
A114: =IF(LEN(F114)>1,F114,G114)&O114&P114&Q114 -> 84109Sambodromo x EG4606906h | B114: =IF(LEN(F114)>1,F114,G114)&O114&P114 -> 84109Sambodromo x EG46069 | C114: =IF((IFERROR(IFERROR(VLOOKUP(A114,Controle_Utiliz!A:A,1,0),VLOOKUP(B114,Controle_Utiliz!B:B,1,0)),"Não Utilizou"))="Não Utilizou","Não Utilizou","Agendado") -> Agendado | D114: Antonio Marcos Basilio Menezes | E114: Globo | F114: 84109 | H114: 21993615441 | I114: FJI - CSC OGA | J114: CONSERVACAO PREDIAL EG | K114: BRUNO DA CAMARA RIBEIRO | L114: ASSIST OPERACOES PREDIAIS | M114: Sambódromo x EG | Vem [2º Dia, Seg, 16-Fev (Grupo Especial)] | N114: 06:00 | O114: Sambodromo x EG | P114: 46069 | Q114: =LEFT(N114,2)&"h" -> 06h
A115: =IF(LEN(F115)>1,F115,G115)&O115&P115&Q115 -> 84109Sambodromo x EG4607406h | B115: =IF(LEN(F115)>1,F115,G115)&O115&P115 -> 84109Sambodromo x EG46074 | C115: =IF((IFERROR(IFERROR(VLOOKUP(A115,Controle_Utiliz!A:A,1,0),VLOOKUP(B115,Controle_Utiliz!B:B,1,0)),"Não Utilizou"))="Não Utilizou","Não Utilizou","Agendado") -> Não Utilizou | D115: Antonio Marcos Basilio Menezes | E115: Globo | F115: 84109 | H115: 21993615441 | I115: FJI - CSC OGA | J115: CONSERVACAO PREDIAL EG | K115: BRUNO DA CAMARA RIBEIRO | L115: ASSIST OPERACOES PREDIAIS | M115: Sambódromo x EG | Vem [CAMPEÃES, Sáb, 21-Fev (Desfile das Campeãs).] | N115: 06:00 | O115: Sambodromo x EG | P115: 46074 | Q115: =LEFT(N115,2)&"h" -> 06h
A116: =IF(LEN(F116)>1,F116,G116)&O116&P116&Q116 -> 52812EG x Sambodromo4606817h | B116: =IF(LEN(F116)>1,F116,G116)&O116&P116 -> 52812EG x Sambodromo46068 | C116: =IF((IFERROR(IFERROR(VLOOKUP(A116,Controle_Utiliz!A:A,1,0),VLOOKUP(B116,Controle_Utiliz!B:B,1,0)),"Não Utilizou"))="Não Utilizou","Não Utilizou","Agendado") -> Agendado | D116: ARLAN PEREIRA DA SILVA | E116: Globo | F116: 52812 | H116: 21974300982 | I116: FJI - CSC OGA | J116: DRAMATURGIA DIARIA | K116: THIAGO GOMES BRANDAO | L116: MONTADOR III | M116: EG x Sambódromo | Vai [1º Dia, Dom, 15-Fev (Grupo Especial)] | N116: 17:00 | O116: EG x Sambodromo | P116: 46068 | Q116: =LEFT(N116,2)&"h" -> 17h
A117: =IF(LEN(F117)>1,F117,G117)&O117&P117&Q117 -> 52812EG x Sambodromo4606917h | B117: =IF(LEN(F117)>1,F117,G117)&O117&P117 -> 52812EG x Sambodromo46069 | C117: =IF((IFERROR(IFERROR(VLOOKUP(A117,Controle_Utiliz!A:A,1,0),VLOOKUP(B117,Controle_Utiliz!B:B,1,0)),"Não Utilizou"))="Não Utilizou","Não Utilizou","Agendado") -> Agendado | D117: ARLAN PEREIRA DA SILVA | E117: Globo | F117: 52812 | H117: 21974300982 | I117: FJI - CSC OGA | J117: DRAMATURGIA DIARIA | K117: THIAGO GOMES BRANDAO | L117: MONTADOR III | M117: EG x Sambódromo | Vai [2º Dia, Seg, 16-Fev (Grupo Especial)] | N117: 17:00 | O117: EG x Sambodromo | P117: 46069 | Q117: =LEFT(N117,2)&"h" -> 17h
A118: =IF(LEN(F118)>1,F118,G118)&O118&P118&Q118 -> 52812EG x Sambodromo4607020h | B118: =IF(LEN(F118)>1,F118,G118)&O118&P118 -> 52812EG x Sambodromo46070 | C118: =IF((IFERROR(IFERROR(VLOOKUP(A118,Controle_Utiliz!A:A,1,0),VLOOKUP(B118,Controle_Utiliz!B:B,1,0)),"Não Utilizou"))="Não Utilizou","Não Utilizou","Agendado") -> Agendado | D118: ARLAN PEREIRA DA SILVA | E118: Globo | F118: 52812 | H118: 21974300982 | I118: FJI - CSC OGA | J118: DRAMATURGIA DIARIA | K118: THIAGO GOMES BRANDAO | L118: MONTADOR III | M118: EG x Sambódromo | Vai [3º Dia, Ter, 17-Fev (Grupo Especial)] | N118: 20:00 | O118: EG x Sambodromo | P118: 46070 | Q118: =LEFT(N118,2)&"h" -> 20h
A119: =IF(LEN(F119)>1,F119,G119)&O119&P119&Q119 -> 52812EG x Sambodromo4607420h | B119: =IF(LEN(F119)>1,F119,G119)&O119&P119 -> 52812EG x Sambodromo46074 | C119: =IF((IFERROR(IFERROR(VLOOKUP(A119,Controle_Utiliz!A:A,1,0),VLOOKUP(B119,Controle_Utiliz!B:B,1,0)),"Não Utilizou"))="Não Utilizou","Não Utilizou","Agendado") -> Agendado | D119: ARLAN PEREIRA DA SILVA | E119: Globo | F119: 52812 | H119: 21974300982 | I119: FJI - CSC OGA | J119: DRAMATURGIA DIARIA | K119: THIAGO GOMES BRANDAO | L119: MONTADOR III | M119: EG x Sambódromo | Vai [CAMPEÃES, Sáb, 21-Fev (Desfile das Campeãs).] | N119: 20:00 | O119: EG x Sambodromo | P119: 46074 | Q119: =LEFT(N119,2)&"h" -> 20h
A120: =IF(LEN(F120)>1,F120,G120)&O120&P120&Q120 -> 52812Sambodromo x EG4606800h | B120: =IF(LEN(F120)>1,F120,G120)&O120&P120 -> 52812Sambodromo x EG46068 | C120: =IF((IFERROR(IFERROR(VLOOKUP(A120,Controle_Utiliz!A:A,1,0),VLOOKUP(B120,Controle_Utiliz!B:B,1,0)),"Não Utilizou"))="Não Utilizou","Não Utilizou","Agendado") -> Agendado | D120: ARLAN PEREIRA DA SILVA | E120: Globo | F120: 52812 | H120: 21974300982 | I120: FJI - CSC OGA | J120: DRAMATURGIA DIARIA | K120: THIAGO GOMES BRANDAO | L120: MONTADOR III | M120: Sambódromo x EG | Vem [1º Dia, Dom, 15-Fev (Grupo Especial)] | N120: 00:00 | O120: Sambodromo x EG | P120: 46068 | Q120: =LEFT(N120,2)&"h" -> 00h
A121: =IF(LEN(F121)>1,F121,G121)&O121&P121&Q121 -> 52812Sambodromo x EG4606900h | B121: =IF(LEN(F121)>1,F121,G121)&O121&P121 -> 52812Sambodromo x EG46069 | C121: =IF((IFERROR(IFERROR(VLOOKUP(A121,Controle_Utiliz!A:A,1,0),VLOOKUP(B121,Controle_Utiliz!B:B,1,0)),"Não Utilizou"))="Não Utilizou","Não Utilizou","Agendado") -> Agendado | D121: ARLAN PEREIRA DA SILVA | E121: Globo | F121: 52812 | H121: 21974300982 | I121: FJI - CSC OGA | J121: DRAMATURGIA DIARIA | K121: THIAGO GOMES BRANDAO | L121: MONTADOR III | M121: Sambódromo x EG | Vem [2º Dia, Seg, 16-Fev (Grupo Especial)] | N121: 00:00 | O121: Sambodromo x EG | P121: 46069 | Q121: =LEFT(N121,2)&"h" -> 00h
A122: =IF(LEN(F122)>1,F122,G122)&O122&P122&Q122 -> 52812Sambodromo x EG4607005h | B122: =IF(LEN(F122)>1,F122,G122)&O122&P122 -> 52812Sambodromo x EG46070 | C122: =IF((IFERROR(IFERROR(VLOOKUP(A122,Controle_Utiliz!A:A,1,0),VLOOKUP(B122,Controle_Utiliz!B:B,1,0)),"Não Utilizou"))="Não Utilizou","Não Utilizou","Agendado") -> Agendado | D122: ARLAN PEREIRA DA SILVA | E122: Globo | F122: 52812 | H122: 21974300982 | I122: FJI - CSC OGA | J122: DRAMATURGIA DIARIA | K122: THIAGO GOMES BRANDAO | L122: MONTADOR III | M122: Sambódromo x EG | Vem [3º Dia, Ter, 17-Fev (Grupo Especial)] | N122: 05:00 | O122: Sambodromo x EG | P122: 46070 | Q122: =LEFT(N122,2)&"h" -> 05h
A123: =IF(LEN(F123)>1,F123,G123)&O123&P123&Q123 -> 52812Sambodromo x EG4607405h | B123: =IF(LEN(F123)>1,F123,G123)&O123&P123 -> 52812Sambodromo x EG46074 | C123: =IF((IFERROR(IFERROR(VLOOKUP(A123,Controle_Utiliz!A:A,1,0),VLOOKUP(B123,Controle_Utiliz!B:B,1,0)),"Não Utilizou"))="Não Utilizou","Não Utilizou","Agendado") -> Não Utilizou | D123: ARLAN PEREIRA DA SILVA | E123: Globo | F123: 52812 | H123: 21974300982 | I123: FJI - CSC OGA | J123: DRAMATURGIA DIARIA | K123: THIAGO GOMES BRANDAO | L123: MONTADOR III | M123: Sambódromo x EG | Vem [CAMPEÃES, Sáb, 21-Fev (Desfile das Campeãs).] | N123: 05:00 | O123: Sambodromo x EG | P123: 46074 | Q123: =LEFT(N123,2)&"h" -> 05h
... A175: =IF(LEN(F175)>1,F175,G175)&O175&P175&Q175 -> 55129Sambodromo x JB4607005h | B175: =IF(LEN(F175)>1,F175,G175)&O175&P175 -> 55129Sambodromo x JB46070 | C175: =IF((IFERROR(IFERROR(VLOOKUP(A175,Controle_Utiliz!A:A,1,0),VLOOKUP(B175,Controle_Utiliz!B:B,1,0)),"Não Utilizou"))="Não Utilizou","Não Utilizou","Agendado") -> Não Utilizou | D175: BRUNO DOS SANTOS REGO | E175: Globo | F175: 55129 | H175: 21968137356 | I175: FJI - CSC SEGURANÇA EMPRESARIAL | J175: EXTERNA INTERNA JB BT | K175: RODRIGO AZEVEDO DE ARAUJO | L175: LIDER SEGURANCA | M175: Sambódromo x JB | Vem [3º Dia, Ter, 17-Fev (Grupo Especial)] | N175: 05:00 | O175: Sambodromo x JB | P175: 46070 | Q175: =LEFT(N175,2)&"h" -> 05h
A176: =IF(LEN(F176)>1,F176,G176)&O176&P176&Q176 -> 00905JB x Sambodromo4606918h | B176: =IF(LEN(F176)>1,F176,G176)&O176&P176 -> 00905JB x Sambodromo46069 | C176: =IF((IFERROR(IFERROR(VLOOKUP(A176,Controle_Utiliz!A:A,1,0),VLOOKUP(B176,Controle_Utiliz!B:B,1,0)),"Não Utilizou"))="Não Utilizou","Não Utilizou","Agendado") -> Não Utilizou | D176: Bruno Grubertt | E176: Globo | F176: 00905 | H176: 81981158124 | I176: JORNALISMO | J176: SUPERVISAO EDITORIA RJ | K176: PATRICIA DE ANDRADE PINTO | L176: REPORTER III | M176: JB x Sambódromo | Vai [2º Dia, Seg, 16-Fev (Grupo Especial)] | N176: 18:00 | O176: JB x Sambodromo | P176: 46069 | Q176: =LEFT(N176,2)&"h" -> 18h
...

Sheet Controle_Utiliz
A1: Chave Agend | B1: Chave data | C1: NOME | D1: MATRÍCULA | E1: DOCUMENTO | F1: TRECHO | G1: SAÍDA | H1: DATA | I1: DIA | J1: AGENDAMENTO | K1: N1 | L1: Departamento | M1: Gestor Imediato | N1: Cargo | R1: 46068 | S1: =R1+1 -> 46069 | T1: =S1+1 -> 46070 | U1: 46074
A2: =IF(LEN(D2)>1,D2,E2)&F2&H2&G2 -> 87678EG x Sambodromo4606823h | B2: =IF(LEN(D2)>1,D2,E2)&F2&H2 -> 87678EG x Sambodromo46068 | C2: ADILSON ANDRADE | D2: 87678 | F2: EG x Sambodromo | G2: 23h | H2: =IF(LEFT(I2,1)="1",46068,IF(LEFT(I2,1)="2",46069,IF(LEFT(I2,1)="3",46070,46074))) -> 46068 | I2: 1 - Primeiro dia | J2: =IF(LEN(A2&B2)<2,"Não Utilizou",IF((IFERROR(IFERROR(VLOOKUP(A2,Agendamento!A:C,3,0),VLOOKUP(B2,Agendamento!B:C,2,0)&"B"),"Encaixe"))="Agendado","Agend_OK",IF((IFERROR(IFERROR(VLOOKUP(A2,Agendamento!A:C,3,0),VLOOKUP(B2,Agendamento!B:C,2,0)&"B"),"Encaixe"))="AgendadoB","Agend_NOK",IF((IFERROR(IFERROR(VLOOKUP(A2,Agendamento!A:C,3,0),VLOOKUP(B2,Agendamento!B:C,2,0)&"B"),"Encaixe"))="Encaixe","Encaixe","Não Utilizou")))) -> Encaixe | K2: =IFERROR(VLOOKUP(L2,'Base Colaboradores'!C:F,4,0),"PRESTADOR DE SERVIÇOS") -> FINANCAS JURIDICO E INFRAESTRUTURA | L2: TRANSPORTES RJ | M2: FABIO PAIXAO DOS SANTOS | N2: MOTORISTA CARRETEIRO | R2: =R1 -> 46068 | S2: =S1 -> 46069 | T2: =T1 -> 46070 | U2: =U1 -> 46074
A3: =IF(LEN(D3)>1,D3,E3)&F3&H3&G3 -> 32636EG x Sambodromo4606817h | B3: =IF(LEN(D3)>1,D3,E3)&F3&H3 -> 32636EG x Sambodromo46068 | C3: ADILSON COUTINHO | D3: 32636 | F3: EG x Sambodromo | G3: 17h | H3: =IF(LEFT(I3,1)="1",46068,IF(LEFT(I3,1)="2",46069,IF(LEFT(I3,1)="3",46070,46074))) -> 46068 | I3: 1 - Primeiro dia | J3: =IF(LEN(A3&B3)<2,"Não Utilizou",IF((IFERROR(IFERROR(VLOOKUP(A3,Agendamento!A:C,3,0),VLOOKUP(B3,Agendamento!B:C,2,0)&"B"),"Encaixe"))="Agendado","Agend_OK",IF((IFERROR(IFERROR(VLOOKUP(A3,Agendamento!A:C,3,0),VLOOKUP(B3,Agendamento!B:C,2,0)&"B"),"Encaixe"))="AgendadoB","Agend_NOK",IF((IFERROR(IFERROR(VLOOKUP(A3,Agendamento!A:C,3,0),VLOOKUP(B3,Agendamento!B:C,2,0)&"B"),"Encaixe"))="Encaixe","Encaixe","Não Utilizou")))) -> Agend_NOK | K3: =IFERROR(VLOOKUP(L3,'Base Colaboradores'!C:F,4,0),"PRESTADOR DE SERVIÇOS") -> TECNOLOGIA | L3: IMAGEM JB | M3: JEAN CARLO GOULART ALVES | N3: OPER CAMERA II
A4: =IF(LEN(D4)>1,D4,E4)&F4&H4&G4 -> 03139095473EG x Sambodromo4606818h | B4: =IF(LEN(D4)>1,D4,E4)&F4&H4 -> 03139095473EG x Sambodromo46068 | C4: ALBERTO CAVALCANTI | E4: 03139095473 | F4: EG x Sambodromo | G4: 18h | H4: =IF(LEFT(I4,1)="1",46068,IF(LEFT(I4,1)="2",46069,IF(LEFT(I4,1)="3",46070,46074))) -> 46068 | I4: 1 - Primeiro dia | J4: =IF(LEN(A4&B4)<2,"Não Utilizou",IF((IFERROR(IFERROR(VLOOKUP(A4,Agendamento!A:C,3,0),VLOOKUP(B4,Agendamento!B:C,2,0)&"B"),"Encaixe"))="Agendado","Agend_OK",IF((IFERROR(IFERROR(VLOOKUP(A4,Agendamento!A:C,3,0),VLOOKUP(B4,Agendamento!B:C,2,0)&"B"),"Encaixe"))="AgendadoB","Agend_NOK",IF((IFERROR(IFERROR(VLOOKUP(A4,Agendamento!A:C,3,0),VLOOKUP(B4,Agendamento!B:C,2,0)&"B"),"Encaixe"))="Encaixe","Encaixe","Não Utilizou")))) -> Agend_OK | K4: =IFERROR(VLOOKUP(L4,'Base Colaboradores'!C:F,4,0),"PRESTADOR DE SERVIÇOS") -> PRESTADOR DE SERVIÇOS | L4: Top Service | M4: Prestador | N4: Prestador
A5: =IF(LEN(D5)>1,D5,E5)&F5&H5&G5 -> 54495EG x Sambodromo4606817h | B5: =IF(LEN(D5)>1,D5,E5)&F5&H5 -> 54495EG x Sambodromo46068 | C5: ALBERTO FERNANDES | D5: 54495 | F5: EG x Sambodromo | G5: 17h | H5: =IF(LEFT(I5,1)="1",46068,IF(LEFT(I5,1)="2",46069,IF(LEFT(I5,1)="3",46070,46074))) -> 46068 | I5: 1 - Primeiro dia | J5: =IF(LEN(A5&B5)<2,"Não Utilizou",IF((IFERROR(IFERROR(VLOOKUP(A5,Agendamento!A:C,3,0),VLOOKUP(B5,Agendamento!B:C,2,0)&"B"),"Encaixe"))="Agendado","Agend_OK",IF((IFERROR(IFERROR(VLOOKUP(A5,Agendamento!A:C,3,0),VLOOKUP(B5,Agendamento!B:C,2,0)&"B"),"Encaixe"))="AgendadoB","Agend_NOK",IF((IFERROR(IFERROR(VLOOKUP(A5,Agendamento!A:C,3,0),VLOOKUP(B5,Agendamento!B:C,2,0)&"B"),"Encaixe"))="Encaixe","Encaixe","Não Utilizou")))) -> Agend_OK | K5: =IFERROR(VLOOKUP(L5,'Base Colaboradores'!C:F,4,0),"PRESTADOR DE SERVIÇOS") -> JORNALISMO | L5: SUPERVISAO IMAGEM RJ | M5: MARCIO STERNICK | N5: SUP EXEC CINEGRAFIA
A6: =IF(LEN(D6)>1,D6,E6)&F6&H6&G6 -> 49605JB x Sambodromo4606818h | B6: =IF(LEN(D6)>1,D6,E6)&F6&H6 -> 49605JB x Sambodromo46068 | C6: ALESSANDRA ALBUQUERQUE | D6: 49605 | F6: JB x Sambodromo | G6: 18h | H6: =IF(LEFT(I6,1)="1",46068,IF(LEFT(I6,1)="2",46069,IF(LEFT(I6,1)="3",46070,46074))) -> 46068 | I6: 1 - Primeiro dia | J6: =IF(LEN(A6&B6)<2,"Não Utilizou",IF((IFERROR(IFERROR(VLOOKUP(A6,Agendamento!A:C,3,0),VLOOKUP(B6,Agendamento!B:C,2,0)&"B"),"Encaixe"))="Agendado","Agend_OK",IF((IFERROR(IFERROR(VLOOKUP(A6,Agendamento!A:C,3,0),VLOOKUP(B6,Agendamento!B:C,2,0)&"B"),"Encaixe"))="AgendadoB","Agend_NOK",IF((IFERROR(IFERROR(VLOOKUP(A6,Agendamento!A:C,3,0),VLOOKUP(B6,Agendamento!B:C,2,0)&"B"),"Encaixe"))="Encaixe","Encaixe","Não Utilizou")))) -> Agend_NOK | K6: =IFERROR(VLOOKUP(L6,'Base Colaboradores'!C:F,4,0),"PRESTADOR DE SERVIÇOS") -> PRODUTOS DIGITAIS | L6: PRODUCAO EM VIDEO | M6: NILO CESAR BARROS GUIMARAES MAIA | N6: PRODUTOR VIDEO III
A7: =IF(LEN(D7)>1,D7,E7)&F7&H7&G7 -> 28483JB x Sambodromo4606819h | B7: =IF(LEN(D7)>1,D7,E7)&F7&H7 -> 28483JB x Sambodromo46068 | C7: ALEX MONTEIRO | D7: 28483 | F7: JB x Sambodromo | G7: 19h | H7: =IF(LEFT(I7,1)="1",46068,IF(LEFT(I7,1)="2",46069,IF(LEFT(I7,1)="3",46070,46074))) -> 46068 | I7: 1 - Primeiro dia | J7: =IF(LEN(A7&B7)<2,"Não Utilizou",IF((IFERROR(IFERROR(VLOOKUP(A7,Agendamento!A:C,3,0),VLOOKUP(B7,Agendamento!B:C,2,0)&"B"),"Encaixe"))="Agendado","Agend_OK",IF((IFERROR(IFERROR(VLOOKUP(A7,Agendamento!A:C,3,0),VLOOKUP(B7,Agendamento!B:C,2,0)&"B"),"Encaixe"))="AgendadoB","Agend_NOK",IF((IFERROR(IFERROR(VLOOKUP(A7,Agendamento!A:C,3,0),VLOOKUP(B7,Agendamento!B:C,2,0)&"B"),"Encaixe"))="Encaixe","Encaixe","Não Utilizou")))) -> Agend_NOK | K7: =IFERROR(VLOOKUP(L7,'Base Colaboradores'!C:F,4,0),"PRESTADOR DE SERVIÇOS") -> TECNOLOGIA | L7: COT E EXTERNA JB | M7: BEATHRIZ VERAS DE LIMA LOPES | N7: TEC SISTEMAS AUDIOVISUAIS II
A8: =IF(LEN(D8)>1,D8,E8)&F8&H8&G8 -> 09804198835EG x Sambodromo4606817h | B8: =IF(LEN(D8)>1,D8,E8)&F8&H8 -> 09804198835EG x Sambodromo46068 | C8: ALEXANDRE DE AMEIDA | E8: 09804198835 | F8: EG x Sambodromo | G8: 17h | H8: =IF(LEFT(I8,1)="1",46068,IF(LEFT(I8,1)="2",46069,IF(LEFT(I8,1)="3",46070,46074))) -> 46068 | I8: 1 - Primeiro dia | J8: =IF(LEN(A8&B8)<2,"Não Utilizou",IF((IFERROR(IFERROR(VLOOKUP(A8,Agendamento!A:C,3,0),VLOOKUP(B8,Agendamento!B:C,2,0)&"B"),"Encaixe"))="Agendado","Agend_OK",IF((IFERROR(IFERROR(VLOOKUP(A8,Agendamento!A:C,3,0),VLOOKUP(B8,Agendamento!B:C,2,0)&"B"),"Encaixe"))="AgendadoB","Agend_NOK",IF((IFERROR(IFERROR(VLOOKUP(A8,Agendamento!A:C,3,0),VLOOKUP(B8,Agendamento!B:C,2,0)&"B"),"Encaixe"))="Encaixe","Encaixe","Não Utilizou")))) -> Encaixe | K8: =IFERROR(VLOOKUP(L8,'Base Colaboradores'!C:F,4,0),"PRESTADOR DE SERVIÇOS") -> PRESTADOR DE SERVIÇOS | L8: Prestador | M8: Prestador | N8: Prestador
A9: =IF(LEN(D9)>1,D9,E9)&F9&H9&G9 -> 81362EG x Sambodromo4606823h | B9: =IF(LEN(D9)>1,D9,E9)&F9&H9 -> 81362EG x Sambodromo46068 | C9: ALEXANDRE JOSE LIMA | D9: 81362 | F9: EG x Sambodromo | G9: 23h | H9: =IF(LEFT(I9,1)="1",46068,IF(LEFT(I9,1)="2",46069,IF(LEFT(I9,1)="3",46070,46074))) -> 46068 | I9: 1 - Primeiro dia | J9: =IF(LEN(A9&B9)<2,"Não Utilizou",IF((IFERROR(IFERROR(VLOOKUP(A9,Agendamento!A:C,3,0),VLOOKUP(B9,Agendamento!B:C,2,0)&"B"),"Encaixe"))="Agendado","Agend_OK",IF((IFERROR(IFERROR(VLOOKUP(A9,Agendamento!A:C,3,0),VLOOKUP(B9,Agendamento!B:C,2,0)&"B"),"Encaixe"))="AgendadoB","Agend_NOK",IF((IFERROR(IFERROR(VLOOKUP(A9,Agendamento!A:C,3,0),VLOOKUP(B9,Agendamento!B:C,2,0)&"B"),"Encaixe"))="Encaixe","Encaixe","Não Utilizou")))) -> Agend_NOK | K9: =IFERROR(VLOOKUP(L9,'Base Colaboradores'!C:F,4,0),"PRESTADOR DE SERVIÇOS") -> JORNALISMO | L9: SUPERVISAO IMAGEM RJ | M9: EDUARDO ALBERTO FERNANDEZ | N9: REPORTER CINEMATOGRAFICO II
A10: =IF(LEN(D10)>1,D10,E10)&F10&H10&G10 -> 91802JB x Sambodromo4606818h | B10: =IF(LEN(D10)>1,D10,E10)&F10&H10 -> 91802JB x Sambodromo46068 | C10: ANA PAULA CAVALCANTE | D10: 91802 | F10: JB x Sambodromo | G10: 18h | H10: =IF(LEFT(I10,1)="1",46068,IF(LEFT(I10,1)="2",46069,IF(LEFT(I10,1)="3",46070,46074))) -> 46068 | I10: 1 - Primeiro dia | J10: =IF(LEN(A10&B10)<2,"Não Utilizou",IF((IFERROR(IFERROR(VLOOKUP(A10,Agendamento!A:C,3,0),VLOOKUP(B10,Agendamento!B:C,2,0)&"B"),"Encaixe"))="Agendado","Agend_OK",IF((IFERROR(IFERROR(VLOOKUP(A10,Agendamento!A:C,3,0),VLOOKUP(B10,Agendamento!B:C,2,0)&"B"),"Encaixe"))="AgendadoB","Agend_NOK",IF((IFERROR(IFERROR(VLOOKUP(A10,Agendamento!A:C,3,0),VLOOKUP(B10,Agendamento!B:C,2,0)&"B"),"Encaixe"))="Encaixe","Encaixe","Não Utilizou")))) -> Encaixe | K10: =IFERROR(VLOOKUP(L10,'Base Colaboradores'!C:F,4,0),"PRESTADOR DE SERVIÇOS") -> TECNOLOGIA | L10: COT E EXTERNA JB | M10: BEATHRIZ VERAS DE LIMA LOPES | N10: TEC CAPTACAO SOM I
A11: =IF(LEN(D11)>1,D11,E11)&F11&H11&G11 -> 41204EG x Sambodromo4606817h | B11: =IF(LEN(D11)>1,D11,E11)&F11&H11 -> 41204EG x Sambodromo46068 | C11: ANDERSON GUIMARAES | D11: 41204 | F11: EG x Sambodromo | G11: 17h | H11: =IF(LEFT(I11,1)="1",46068,IF(LEFT(I11,1)="2",46069,IF(LEFT(I11,1)="3",46070,46074))) -> 46068 | I11: 1 - Primeiro dia | J11: =IF(LEN(A11&B11)<2,"Não Utilizou",IF((IFERROR(IFERROR(VLOOKUP(A11,Agendamento!A:C,3,0),VLOOKUP(B11,Agendamento!B:C,2,0)&"B"),"Encaixe"))="Agendado","Agend_OK",IF((IFERROR(IFERROR(VLOOKUP(A11,Agendamento!A:C,3,0),VLOOKUP(B11,Agendamento!B:C,2,0)&"B"),"Encaixe"))="AgendadoB","Agend_NOK",IF((IFERROR(IFERROR(VLOOKUP(A11,Agendamento!A:C,3,0),VLOOKUP(B11,Agendamento!B:C,2,0)&"B"),"Encaixe"))="Encaixe","Encaixe","Não Utilizou")))) -> Agend_OK | K11: =IFERROR(VLOOKUP(L11,'Base Colaboradores'!C:F,4,0),"PRESTADOR DE SERVIÇOS") -> TECNOLOGIA | L11: IMAGEM EG | M11: FABIO LOEWENBACH CASCAO | N11: OPER CAMERA IV
A12: =IF(LEN(D12)>1,D12,E12)&F12&H12&G12 -> 39276JB x Sambodromo4606821h | B12: =IF(LEN(D12)>1,D12,E12)&F12&H12 -> 39276JB x Sambodromo46068 | C12: ANDRE CARVALHO | D12: 39276 | F12: JB x Sambodromo | G12: 21h | H12: =IF(LEFT(I12,1)="1",46068,IF(LEFT(I12,1)="2",46069,IF(LEFT(I12,1)="3",46070,46074))) -> 46068 | I12: 1 - Primeiro dia | J12: =IF(LEN(A12&B12)<2,"Não Utilizou",IF((IFERROR(IFERROR(VLOOKUP(A12,Agendamento!A:C,3,0),VLOOKUP(B12,Agendamento!B:C,2,0)&"B"),"Encaixe"))="Agendado","Agend_OK",IF((IFERROR(IFERROR(VLOOKUP(A12,Agendamento!A:C,3,0),VLOOKUP(B12,Agendamento!B:C,2,0)&"B"),"Encaixe"))="AgendadoB","Agend_NOK",IF((IFERROR(IFERROR(VLOOKUP(A12,Agendamento!A:C,3,0),VLOOKUP(B12,Agendamento!B:C,2,0)&"B"),"Encaixe"))="Encaixe","Encaixe","Não Utilizou")))) -> Encaixe | K12: =IFERROR(VLOOKUP(L12,'Base Colaboradores'!C:F,4,0),"PRESTADOR DE SERVIÇOS") -> TV GLOBO | L12: SUPERVISAO PROGRAMACAO RIO DE JANEIRO | M12: ALINE SILVA SANTOS | N12: COORD PROGRAMACAO REGIONAL
A13: =IF(LEN(D13)>1,D13,E13)&F13&H13&G13 -> 01193644763EG x Sambodromo4606822h | B13: =IF(LEN(D13)>1,D13,E13)&F13&H13 -> 01193644763EG x Sambodromo46068 | C13: ANDREIA CARLA | E13: 01193644763 | F13: EG x Sambodromo | G13: 22h | H13: =IF(LEFT(I13,1)="1",46068,IF(LEFT(I13,1)="2",46069,IF(LEFT(I13,1)="3",46070,46074))) -> 46068 | I13: 1 - Primeiro dia | J13: =IF(LEN(A13&B13)<2,"Não Utilizou",IF((IFERROR(IFERROR(VLOOKUP(A13,Agendamento!A:C,3,0),VLOOKUP(B13,Agendamento!B:C,2,0)&"B"),"Encaixe"))="Agendado","Agend_OK",IF((IFERROR(IFERROR(VLOOKUP(A13,Agendamento!A:C,3,0),VLOOKUP(B13,Agendamento!B:C,2,0)&"B"),"Encaixe"))="AgendadoB","Agend_NOK",IF((IFERROR(IFERROR(VLOOKUP(A13,Agendamento!A:C,3,0),VLOOKUP(B13,Agendamento!B:C,2,0)&"B"),"Encaixe"))="Encaixe","Encaixe","Não Utilizou")))) -> Encaixe | K13: =IFERROR(VLOOKUP(L13,'Base Colaboradores'!C:F,4,0),"PRESTADOR DE SERVIÇOS") -> PRESTADOR DE SERVIÇOS | L13: Prestador | M13: Prestador | N13: Prestador
A14: =IF(LEN(D14)>1,D14,E14)&F14&H14&G14 -> 05551438724JB x Sambodromo4606819h | B14: =IF(LEN(D14)>1,D14,E14)&F14&H14 -> 05551438724JB x Sambodromo46068 | C14: ANTONIO PIMENTEL | E14: 05551438724 | F14: JB x Sambodromo | G14: 19h | H14: =IF(LEFT(I14,1)="1",46068,IF(LEFT(I14,1)="2",46069,IF(LEFT(I14,1)="3",46070,46074))) -> 46068 | I14: 1 - Primeiro dia | J14: =IF(LEN(A14&B14)<2,"Não Utilizou",IF((IFERROR(IFERROR(VLOOKUP(A14,Agendamento!A:C,3,0),VLOOKUP(B14,Agendamento!B:C,2,0)&"B"),"Encaixe"))="Agendado","Agend_OK",IF((IFERROR(IFERROR(VLOOKUP(A14,Agendamento!A:C,3,0),VLOOKUP(B14,Agendamento!B:C,2,0)&"B"),"Encaixe"))="AgendadoB","Agend_NOK",IF((IFERROR(IFERROR(VLOOKUP(A14,Agendamento!A:C,3,0),VLOOKUP(B14,Agendamento!B:C,2,0)&"B"),"Encaixe"))="Encaixe","Encaixe","Não Utilizou")))) -> Encaixe | K14: =IFERROR(VLOOKUP(L14,'Base Colaboradores'!C:F,4,0),"PRESTADOR DE SERVIÇOS") -> PRESTADOR DE SERVIÇOS | L14: Prestador | M14: Prestador | N14: Prestador
A15: =IF(LEN(D15)>1,D15,E15)&F15&H15&G15 -> 52812EG x Sambodromo4606818h | B15: =IF(LEN(D15)>1,D15,E15)&F15&H15 -> 52812EG x Sambodromo46068 | C15: ARLAN PEREIRA | D15: 52812 | F15: EG x Sambodromo | G15: 18h | H15: =IF(LEFT(I15,1)="1",46068,IF(LEFT(I15,1)="2",46069,IF(LEFT(I15,1)="3",46070,46074))) -> 46068 | I15: 1 - Primeiro dia | J15: =IF(LEN(A15&B15)<2,"Não Utilizou",IF((IFERROR(IFERROR(VLOOKUP(A15,Agendamento!A:C,3,0),VLOOKUP(B15,Agendamento!B:C,2,0)&"B"),"Encaixe"))="Agendado","Agend_OK",IF((IFERROR(IFERROR(VLOOKUP(A15,Agendamento!A:C,3,0),VLOOKUP(B15,Agendamento!B:C,2,0)&"B"),"Encaixe"))="AgendadoB","Agend_NOK",IF((IFERROR(IFERROR(VLOOKUP(A15,Agendamento!A:C,3,0),VLOOKUP(B15,Agendamento!B:C,2,0)&"B"),"Encaixe"))="Encaixe","Encaixe","Não Utilizou")))) -> Agend_NOK | K15: =IFERROR(VLOOKUP(L15,'Base Colaboradores'!C:F,4,0),"PRESTADOR DE SERVIÇOS") -> FINANCAS JURIDICO E INFRAESTRUTURA | L15: DRAMATURGIA DIARIA | M15: THIAGO GOMES BRANDAO | N15: MONTADOR III
A16: =IF(LEN(D16)>1,D16,E16)&F16&H16&G16 -> 70088JB x Sambodromo4606818h | B16: =IF(LEN(D16)>1,D16,E16)&F16&H16 -> 70088JB x Sambodromo46068 | C16: BETTE LUCCHESE | D16: 70088 | F16: JB x Sambodromo | G16: 18h | H16: =IF(LEFT(I16,1)="1",46068,IF(LEFT(I16,1)="2",46069,IF(LEFT(I16,1)="3",46070,46074))) -> 46068 | I16: 1 - Primeiro dia | J16: =IF(LEN(A16&B16)<2,"Não Utilizou",IF((IFERROR(IFERROR(VLOOKUP(A16,Agendamento!A:C,3,0),VLOOKUP(B16,Agendamento!B:C,2,0)&"B"),"Encaixe"))="Agendado","Agend_OK",IF((IFERROR(IFERROR(VLOOKUP(A16,Agendamento!A:C,3,0),VLOOKUP(B16,Agendamento!B:C,2,0)&"B"),"Encaixe"))="AgendadoB","Agend_NOK",IF((IFERROR(IFERROR(VLOOKUP(A16,Agendamento!A:C,3,0),VLOOKUP(B16,Agendamento!B:C,2,0)&"B"),"Encaixe"))="Encaixe","Encaixe","Não Utilizou")))) -> Agend_NOK | K16: =IFERROR(VLOOKUP(L16,'Base Colaboradores'!C:F,4,0),"PRESTADOR DE SERVIÇOS") -> JORNALISMO | L16: EDITORIA RJ | M16: MARCIO STERNICK | N16: REPORTER ESPECIAL II
A17: =IF(LEN(D17)>1,D17,E17)&F17&H17&G17 -> 84786JB x Sambodromo4606819h | B17: =IF(LEN(D17)>1,D17,E17)&F17&H17 -> 84786JB x Sambodromo46068 | C17: BIANCA FASSANO | D17: 84786 | F17: JB x Sambodromo | G17: 19h | H17: =IF(LEFT(I17,1)="1",46068,IF(LEFT(I17,1)="2",46069,IF(LEFT(I17,1)="3",46070,46074))) -> 46068 | I17: 1 - Primeiro dia | J17: =IF(LEN(A17&B17)<2,"Não Utilizou",IF((IFERROR(IFERROR(VLOOKUP(A17,Agendamento!A:C,3,0),VLOOKUP(B17,Agendamento!B:C,2,0)&"B"),"Encaixe"))="Agendado","Agend_OK",IF((IFERROR(IFERROR(VLOOKUP(A17,Agendamento!A:C,3,0),VLOOKUP(B17,Agendamento!B:C,2,0)&"B"),"Encaixe"))="AgendadoB","Agend_NOK",IF((IFERROR(IFERROR(VLOOKUP(A17,Agendamento!A:C,3,0),VLOOKUP(B17,Agendamento!B:C,2,0)&"B"),"Encaixe"))="Encaixe","Encaixe","Não Utilizou")))) -> Agend_OK | K17: =IFERROR(VLOOKUP(L17,'Base Colaboradores'!C:F,4,0),"PRESTADOR DE SERVIÇOS") -> RECURSOS HUMANOS | L17: APOIO A PESSOAS E BEM-ESTAR | M17: RENATA RODRIGUES MARTINS | N17: ANL SERVICOS RECURSOS HUMANOS II
A18: =IF(LEN(D18)>1,D18,E18)&F18&H18&G18 -> 78882EG x Sambodromo4606822h | B18: =IF(LEN(D18)>1,D18,E18)&F18&H18 -> 78882EG x Sambodromo46068 | C18: BRENDA PORTO | D18: 78882 | F18: EG x Sambodromo | G18: 22h | H18: =IF(LEFT(I18,1)="1",46068,IF(LEFT(I18,1)="2",46069,IF(LEFT(I18,1)="3",46070,46074))) -> 46068 | I18: 1 - Primeiro dia | J18: =IF(LEN(A18&B18)<2,"Não Utilizou",IF((IFERROR(IFERROR(VLOOKUP(A18,Agendamento!A:C,3,0),VLOOKUP(B18,Agendamento!B:C,2,0)&"B"),"Encaixe"))="Agendado","Agend_OK",IF((IFERROR(IFERROR(VLOOKUP(A18,Agendamento!A:C,3,0),VLOOKUP(B18,Agendamento!B:C,2,0)&"B"),"Encaixe"))="AgendadoB","Agend_NOK",IF((IFERROR(IFERROR(VLOOKUP(A18,Agendamento!A:C,3,0),VLOOKUP(B18,Agendamento!B:C,2,0)&"B"),"Encaixe"))="Encaixe","Encaixe","Não Utilizou")))) -> Agend_OK | K18: =IFERROR(VLOOKUP(L18,'Base Colaboradores'!C:F,4,0),"PRESTADOR DE SERVIÇOS") -> TECNOLOGIA | L18: IMAGEM EG | M18: FABIO LOEWENBACH CASCAO | N18: OPER CAMERA I
A19: =IF(LEN(D19)>1,D19,E19)&F19&H19&G19 -> 78728EG x Sambodromo4606822h | B19: =IF(LEN(D19)>1,D19,E19)&F19&H19 -> 78728EG x Sambodromo46068 | C19: BRUNO GONÇALVES | D19: 78728 | F19: EG x Sambodromo | G19: 22h | H19: =IF(LEFT(I19,1)="1",46068,IF(LEFT(I19,1)="2",46069,IF(LEFT(I19,1)="3",46070,46074))) -> 46068 | I19: 1 - Primeiro dia | J19: =IF(LEN(A19&B19)<2,"Não Utilizou",IF((IFERROR(IFERROR(VLOOKUP(A19,Agendamento!A:C,3,0),VLOOKUP(B19,Agendamento!B:C,2,0)&"B"),"Encaixe"))="Agendado","Agend_OK",IF((IFERROR(IFERROR(VLOOKUP(A19,Agendamento!A:C,3,0),VLOOKUP(B19,Agendamento!B:C,2,0)&"B"),"Encaixe"))="AgendadoB","Agend_NOK",IF((IFERROR(IFERROR(VLOOKUP(A19,Agendamento!A:C,3,0),VLOOKUP(B19,Agendamento!B:C,2,0)&"B"),"Encaixe"))="Encaixe","Encaixe","Não Utilizou")))) -> Agend_NOK | K19: =IFERROR(VLOOKUP(L19,'Base Colaboradores'!C:F,4,0),"PRESTADOR DE SERVIÇOS") -> TECNOLOGIA | L19: IMAGEM EG | M19: FABIO LOEWENBACH CASCAO | N19: OPER CAMERA I
A20: =IF(LEN(D20)>1,D20,E20)&F20&H20&G20 -> 905JB x Sambodromo4606819h | B20: =IF(LEN(D20)>1,D20,E20)&F20&H20 -> 905JB x Sambodromo46068 | C20: BRUNO GRUBERTT | D20: 905 | F20: JB x Sambodromo | G20: 19h | H20: =IF(LEFT(I20,1)="1",46068,IF(LEFT(I20,1)="2",46069,IF(LEFT(I20,1)="3",46070,46074))) -> 46068 | I20: 1 - Primeiro dia | J20: =IF(LEN(A20&B20)<2,"Não Utilizou",IF((IFERROR(IFERROR(VLOOKUP(A20,Agendamento!A:C,3,0),VLOOKUP(B20,Agendamento!B:C,2,0)&"B"),"Encaixe"))="Agendado","Agend_OK",IF((IFERROR(IFERROR(VLOOKUP(A20,Agendamento!A:C,3,0),VLOOKUP(B20,Agendamento!B:C,2,0)&"B"),"Encaixe"))="AgendadoB","Agend_NOK",IF((IFERROR(IFERROR(VLOOKUP(A20,Agendamento!A:C,3,0),VLOOKUP(B20,Agendamento!B:C,2,0)&"B"),"Encaixe"))="Encaixe","Encaixe","Não Utilizou")))) -> Encaixe | K20: =IFERROR(VLOOKUP(L20,'Base Colaboradores'!C:F,4,0),"PRESTADOR DE SERVIÇOS") -> JORNALISMO | L20: SUPERVISAO EDITORIA RJ | M20: PATRICIA DE ANDRADE PINTO | N20: REPORTER III
A21: =IF(LEN(D21)>1,D21,E21)&F21&H21&G21 -> 55129JB x Sambodromo4606818h | B21: =IF(LEN(D21)>1,D21,E21)&F21&H21 -> 55129JB x Sambodromo46068 | C21: BRUNO REGO | D21: 55129 | F21: JB x Sambodromo | G21: 18h | H21: =IF(LEFT(I21,1)="1",46068,IF(LEFT(I21,1)="2",46069,IF(LEFT(I21,1)="3",46070,46074))) -> 46068 | I21: 1 - Primeiro dia | J21: =IF(LEN(A21&B21)<2,"Não Utilizou",IF((IFERROR(IFERROR(VLOOKUP(A21,Agendamento!A:C,3,0),VLOOKUP(B21,Agendamento!B:C,2,0)&"B"),"Encaixe"))="Agendado","Agend_OK",IF((IFERROR(IFERROR(VLOOKUP(A21,Agendamento!A:C,3,0),VLOOKUP(B21,Agendamento!B:C,2,0)&"B"),"Encaixe"))="AgendadoB","Agend_NOK",IF((IFERROR(IFERROR(VLOOKUP(A21,Agendamento!A:C,3,0),VLOOKUP(B21,Agendamento!B:C,2,0)&"B"),"Encaixe"))="Encaixe","Encaixe","Não Utilizou")))) -> Agend_OK | K21: =IFERROR(VLOOKUP(L21,'Base Colaboradores'!C:F,4,0),"PRESTADOR DE SERVIÇOS") -> FINANCAS JURIDICO E INFRAESTRUTURA | L21: EXTERNA INTERNA JB BT | M21: RODRIGO AZEVEDO DE ARAUJO | N21: LIDER SEGURANCA
A22: =IF(LEN(D22)>1,D22,E22)&F22&H22&G22 -> 55278EG x Sambodromo4606818h | B22: =IF(LEN(D22)>1,D22,E22)&F22&H22 -> 55278EG x Sambodromo46068 | C22: BRUNO RIBEIRO | D22: 55278 | F22: EG x Sambodromo | G22: 18h | H22: =IF(LEFT(I22,1)="1",46068,IF(LEFT(I22,1)="2",46069,IF(LEFT(I22,1)="3",46070,46074))) -> 46068 | I22: 1 - Primeiro dia | J22: =IF(LEN(A22&B22)<2,"Não Utilizou",IF((IFERROR(IFERROR(VLOOKUP(A22,Agendamento!A:C,3,0),VLOOKUP(B22,Agendamento!B:C,2,0)&"B"),"Encaixe"))="Agendado","Agend_OK",IF((IFERROR(IFERROR(VLOOKUP(A22,Agendamento!A:C,3,0),VLOOKUP(B22,Agendamento!B:C,2,0)&"B"),"Encaixe"))="AgendadoB","Agend_NOK",IF((IFERROR(IFERROR(VLOOKUP(A22,Agendamento!A:C,3,0),VLOOKUP(B22,Agendamento!B:C,2,0)&"B"),"Encaixe"))="Encaixe","Encaixe","Não Utilizou")))) -> Agend_OK | K22: =IFERROR(VLOOKUP(L22,'Base Colaboradores'!C:F,4,0),"PRESTADOR DE SERVIÇOS") -> FINANCAS JURIDICO E INFRAESTRUTURA | L22: CONSERVACAO PREDIAL EG | M22: THIAGO LACERDA DE LA VEGA | N22: COORD MANUTENCAO E OPERACAO PREDIAL
A23: =IF(LEN(D23)>1,D23,E23)&F23&H23&G23 -> 15692202719EG x Sambodromo4606819h | B23: =IF(LEN(D23)>1,D23,E23)&F23&H23 -> 15692202719EG x Sambodromo46068 | C23: CARINA RITTER | E23: 15692202719 | F23: EG x Sambodromo | G23: 19h | H23: =IF(LEFT(I23,1)="1",46068,IF(LEFT(I23,1)="2",46069,IF(LEFT(I23,1)="3",46070,46074))) -> 46068 | I23: 1 - Primeiro dia | J23: =IF(LEN(A23&B23)<2,"Não Utilizou",IF((IFERROR(IFERROR(VLOOKUP(A23,Agendamento!A:C,3,0),VLOOKUP(B23,Agendamento!B:C,2,0)&"B"),"Encaixe"))="Agendado","Agend_OK",IF((IFERROR(IFERROR(VLOOKUP(A23,Agendamento!A:C,3,0),VLOOKUP(B23,Agendamento!B:C,2,0)&"B"),"Encaixe"))="AgendadoB","Agend_NOK",IF((IFERROR(IFERROR(VLOOKUP(A23,Agendamento!A:C,3,0),VLOOKUP(B23,Agendamento!B:C,2,0)&"B"),"Encaixe"))="Encaixe","Encaixe","Não Utilizou")))) -> Agend_NOK | K23: =IFERROR(VLOOKUP(L23,'Base Colaboradores'!C:F,4,0),"PRESTADOR DE SERVIÇOS") -> PRESTADOR DE SERVIÇOS | L23: LET | M23: Prestador | N23: Prestador
A24: =IF(LEN(D24)>1,D24,E24)&F24&H24&G24 -> 08784901756EG x Sambodromo4606820h | B24: =IF(LEN(D24)>1,D24,E24)&F24&H24 -> 08784901756EG x Sambodromo46068 | C24: CARLOS ALBERTO | E24: 08784901756 | F24: EG x Sambodromo | G24: 20h | H24: =IF(LEFT(I24,1)="1",46068,IF(LEFT(I24,1)="2",46069,IF(LEFT(I24,1)="3",46070,46074))) -> 46068 | I24: 1 - Primeiro dia | J24: =IF(LEN(A24&B24)<2,"Não Utilizou",IF((IFERROR(IFERROR(VLOOKUP(A24,Agendamento!A:C,3,0),VLOOKUP(B24,Agendamento!B:C,2,0)&"B"),"Encaixe"))="Agendado","Agend_OK",IF((IFERROR(IFERROR(VLOOKUP(A24,Agendamento!A:C,3,0),VLOOKUP(B24,Agendamento!B:C,2,0)&"B"),"Encaixe"))="AgendadoB","Agend_NOK",IF((IFERROR(IFERROR(VLOOKUP(A24,Agendamento!A:C,3,0),VLOOKUP(B24,Agendamento!B:C,2,0)&"B"),"Encaixe"))="Encaixe","Encaixe","Não Utilizou")))) -> Agend_NOK | K24: =IFERROR(VLOOKUP(L24,'Base Colaboradores'!C:F,4,0),"PRESTADOR DE SERVIÇOS") -> PRESTADOR DE SERVIÇOS | L24: Top Service | M24: Prestador | N24: Prestador
A25: =IF(LEN(D25)>1,D25,E25)&F25&H25&G25 -> 54103JB x Sambodromo4606818h | B25: =IF(LEN(D25)>1,D25,E25)&F25&H25 -> 54103JB x Sambodromo46068 | C25: CARLOS MENDONÇA | D25: 54103 | F25: JB x Sambodromo | G25: 18h | H25: =IF(LEFT(I25,1)="1",46068,IF(LEFT(I25,1)="2",46069,IF(LEFT(I25,1)="3",46070,46074))) -> 46068 | I25: 1 - Primeiro dia | J25: =IF(LEN(A25&B25)<2,"Não Utilizou",IF((IFERROR(IFERROR(VLOOKUP(A25,Agendamento!A:C,3,0),VLOOKUP(B25,Agendamento!B:C,2,0)&"B"),"Encaixe"))="Agendado","Agend_OK",IF((IFERROR(IFERROR(VLOOKUP(A25,Agendamento!A:C,3,0),VLOOKUP(B25,Agendamento!B:C,2,0)&"B"),"Encaixe"))="AgendadoB","Agend_NOK",IF((IFERROR(IFERROR(VLOOKUP(A25,Agendamento!A:C,3,0),VLOOKUP(B25,Agendamento!B:C,2,0)&"B"),"Encaixe"))="Encaixe","Encaixe","Não Utilizou")))) -> Encaixe | K25: =IFERROR(VLOOKUP(L25,'Base Colaboradores'!C:F,4,0),"PRESTADOR DE SERVIÇOS") -> JORNALISMO | L25: SUPERVISAO IMAGEM RJ | M25: EDUARDO ALBERTO FERNANDEZ | N25: REPORTER CINEMATOGRAFICO II
A26: =IF(LEN(D26)>1,D26,E26)&F26&H26&G26 -> 89545EG x Sambodromo4606819h | B26: =IF(LEN(D26)>1,D26,E26)&F26&H26 -> 89545EG x Sambodromo46068 | C26: CARLOS PAIVA | D26: 89545 | F26: EG x Sambodromo | G26: 19h | H26: =IF(LEFT(I26,1)="1",46068,IF(LEFT(I26,1)="2",46069,IF(LEFT(I26,1)="3",46070,46074))) -> 46068 | I26: 1 - Primeiro dia | J26: =IF(LEN(A26&B26)<2,"Não Utilizou",IF((IFERROR(IFERROR(VLOOKUP(A26,Agendamento!A:C,3,0),VLOOKUP(B26,Agendamento!B:C,2,0)&"B"),"Encaixe"))="Agendado","Agend_OK",IF((IFERROR(IFERROR(VLOOKUP(A26,Agendamento!A:C,3,0),VLOOKUP(B26,Agendamento!B:C,2,0)&"B"),"Encaixe"))="AgendadoB","Agend_NOK",IF((IFERROR(IFERROR(VLOOKUP(A26,Agendamento!A:C,3,0),VLOOKUP(B26,Agendamento!B:C,2,0)&"B"),"Encaixe"))="Encaixe","Encaixe","Não Utilizou")))) -> Agend_NOK | K26: =IFERROR(VLOOKUP(L26,'Base Colaboradores'!C:F,4,0),"PRESTADOR DE SERVIÇOS") -> PRODUTOS DIGITAIS | L26: CULTURA POP 2 | M26: ANDERSON DEZAN RIBEIRO DE AZEVEDO | N26: EDITOR CONTEUDO WEB I
A27: =IF(LEN(D27)>1,D27,E27)&F27&H27&G27 -> 984JB x Sambodromo4606819h | B27: =IF(LEN(D27)>1,D27,E27)&F27&H27 -> 984JB x Sambodromo46068 | C27: CAROLINA DUCA | D27: 984 | F27: JB x Sambodromo | G27: 19h | H27: =IF(LEFT(I27,1)="1",46068,IF(LEFT(I27,1)="2",46069,IF(LEFT(I27,1)="3",46070,46074))) -> 46068 | I27: 1 - Primeiro dia | J27: =IF(LEN(A27&B27)<2,"Não Utilizou",IF((IFERROR(IFERROR(VLOOKUP(A27,Agendamento!A:C,3,0),VLOOKUP(B27,Agendamento!B:C,2,0)&"B"),"Encaixe"))="Agendado","Agend_OK",IF((IFERROR(IFERROR(VLOOKUP(A27,Agendamento!A:C,3,0),VLOOKUP(B27,Agendamento!B:C,2,0)&"B"),"Encaixe"))="AgendadoB","Agend_NOK",IF((IFERROR(IFERROR(VLOOKUP(A27,Agendamento!A:C,3,0),VLOOKUP(B27,Agendamento!B:C,2,0)&"B"),"Encaixe"))="Encaixe","Encaixe","Não Utilizou")))) -> Encaixe | K27: =IFERROR(VLOOKUP(L27,'Base Colaboradores'!C:F,4,0),"PRESTADOR DE SERVIÇOS") -> TECNOLOGIA | L27: INFRA E TELECOM | M27: RAYMUNDO COSTA PINTO BARROS | N27: DIR INFRA & TELECOM
A28: =IF(LEN(D28)>1,D28,E28)&F28&H28&G28 -> 41420JB x Sambodromo4606818h | B28: =IF(LEN(D28)>1,D28,E28)&F28&H28 -> 41420JB x Sambodromo46068 | C28: CHICO REGUEIRA | D28: 41420 | F28: JB x Sambodromo | G28: 18h | H28: =IF(LEFT(I28,1)="1",46068,IF(LEFT(I28,1)="2",46069,IF(LEFT(I28,1)="3",46070,46074))) -> 46068 | I28: 1 - Primeiro dia | J28: =IF(LEN(A28&B28)<2,"Não Utilizou",IF((IFERROR(IFERROR(VLOOKUP(A28,Agendamento!A:C,3,0),VLOOKUP(B28,Agendamento!B:C,2,0)&"B"),"Encaixe"))="Agendado","Agend_OK",IF((IFERROR(IFERROR(VLOOKUP(A28,Agendamento!A:C,3,0),VLOOKUP(B28,Agendamento!B:C,2,0)&"B"),"Encaixe"))="AgendadoB","Agend_NOK",IF((IFERROR(IFERROR(VLOOKUP(A28,Agendamento!A:C,3,0),VLOOKUP(B28,Agendamento!B:C,2,0)&"B"),"Encaixe"))="Encaixe","Encaixe","Não Utilizou")))) -> Encaixe | K28: =IFERROR(VLOOKUP(L28,'Base Colaboradores'!C:F,4,0),"PRESTADOR DE SERVIÇOS") -> JORNALISMO | L28: SUPERVISAO EDITORIA RJ | M28: PATRICIA DE ANDRADE PINTO | N28: REPORTER ESPECIAL I
A29: =IF(LEN(D29)>1,D29,E29)&F29&H29&G29 -> 05559496723EG x Sambodromo4606818h | B29: =IF(LEN(D29)>1,D29,E29)&F29&H29 -> 05559496723EG x Sambodromo46068 | C29: CINTHIA REGINA | E29: 05559496723 | F29: EG x Sambodromo | G29: 18h | H29: =IF(LEFT(I29,1)="1",46068,IF(LEFT(I29,1)="2",46069,IF(LEFT(I29,1)="3",46070,46074))) -> 46068 | I29: 1 - Primeiro dia | J29: =IF(LEN(A29&B29)<2,"Não Utilizou",IF((IFERROR(IFERROR(VLOOKUP(A29,Agendamento!A:C,3,0),VLOOKUP(B29,Agendamento!B:C,2,0)&"B"),"Encaixe"))="Agendado","Agend_OK",IF((IFERROR(IFERROR(VLOOKUP(A29,Agendamento!A:C,3,0),VLOOKUP(B29,Agendamento!B:C,2,0)&"B"),"Encaixe"))="AgendadoB","Agend_NOK",IF((IFERROR(IFERROR(VLOOKUP(A29,Agendamento!A:C,3,0),VLOOKUP(B29,Agendamento!B:C,2,0)&"B"),"Encaixe"))="Encaixe","Encaixe","Não Utilizou")))) -> Agend_OK | K29: =IFERROR(VLOOKUP(L29,'Base Colaboradores'!C:F,4,0),"PRESTADOR DE SERVIÇOS") -> PRESTADOR DE SERVIÇOS | L29: Top Service | M29: Prestador | N29: Prestador
A30: =IF(LEN(D30)>1,D30,E30)&F30&H30&G30 -> 02495836747EG x Sambodromo4606818h | B30: =IF(LEN(D30)>1,D30,E30)&F30&H30 -> 02495836747EG x Sambodromo46068 | C30: CLEBER CANDIDO | E30: 02495836747 | F30: EG x Sambodromo | G30: 18h | H30: =IF(LEFT(I30,1)="1",46068,IF(LEFT(I30,1)="2",46069,IF(LEFT(I30,1)="3",46070,46074))) -> 46068 | I30: 1 - Primeiro dia | J30: =IF(LEN(A30&B30)<2,"Não Utilizou",IF((IFERROR(IFERROR(VLOOKUP(A30,Agendamento!A:C,3,0),VLOOKUP(B30,Agendamento!B:C,2,0)&"B"),"Encaixe"))="Agendado","Agend_OK",IF((IFERROR(IFERROR(VLOOKUP(A30,Agendamento!A:C,3,0),VLOOKUP(B30,Agendamento!B:C,2,0)&"B"),"Encaixe"))="AgendadoB","Agend_NOK",IF((IFERROR(IFERROR(VLOOKUP(A30,Agendamento!A:C,3,0),VLOOKUP(B30,Agendamento!B:C,2,0)&"B"),"Encaixe"))="Encaixe","Encaixe","Não Utilizou")))) -> Agend_OK | K30: =IFERROR(VLOOKUP(L30,'Base Colaboradores'!C:F,4,0),"PRESTADOR DE SERVIÇOS") -> PRESTADOR DE SERVIÇOS | L30: Top Service | M30: Prestador | N30: Prestador
A31: =IF(LEN(D31)>1,D31,E31)&F31&H31&G31 -> 92563EG x Sambodromo4606820h | B31: =IF(LEN(D31)>1,D31,E31)&F31&H31 -> 92563EG x Sambodromo46068 | C31: CLEYTON COSTA | D31: 92563 | F31: EG x Sambodromo | G31: 20h | H31: =IF(LEFT(I31,1)="1",46068,IF(LEFT(I31,1)="2",46069,IF(LEFT(I31,1)="3",46070,46074))) -> 46068 | I31: 1 - Primeiro dia | J31: =IF(LEN(A31&B31)<2,"Não Utilizou",IF((IFERROR(IFERROR(VLOOKUP(A31,Agendamento!A:C,3,0),VLOOKUP(B31,Agendamento!B:C,2,0)&"B"),"Encaixe"))="Agendado","Agend_OK",IF((IFERROR(IFERROR(VLOOKUP(A31,Agendamento!A:C,3,0),VLOOKUP(B31,Agendamento!B:C,2,0)&"B"),"Encaixe"))="AgendadoB","Agend_NOK",IF((IFERROR(IFERROR(VLOOKUP(A31,Agendamento!A:C,3,0),VLOOKUP(B31,Agendamento!B:C,2,0)&"B"),"Encaixe"))="Encaixe","Encaixe","Não Utilizou")))) -> Encaixe | K31: =IFERROR(VLOOKUP(L31,'Base Colaboradores'!C:F,4,0),"PRESTADOR DE SERVIÇOS") -> FINANCAS JURIDICO E INFRAESTRUTURA | L31: TRANSPORTES RJ | M31: FABIO PAIXAO DOS SANTOS | N31: ENC SERVICOS
A32: =IF(LEN(D32)>1,D32,E32)&F32&H32&G32 -> 88220JB x Sambodromo4606821h | B32: =IF(LEN(D32)>1,D32,E32)&F32&H32 -> 88220JB x Sambodromo46068 | C32: CRISTIANE GOMES | D32: 88220 | F32: JB x Sambodromo | G32: 21h | H32: =IF(LEFT(I32,1)="1",46068,IF(LEFT(I32,1)="2",46069,IF(LEFT(I32,1)="3",46070,46074))) -> 46068 | I32: 1 - Primeiro dia | J32: =IF(LEN(A32&B32)<2,"Não Utilizou",IF((IFERROR(IFERROR(VLOOKUP(A32,Agendamento!A:C,3,0),VLOOKUP(B32,Agendamento!B:C,2,0)&"B"),"Encaixe"))="Agendado","Agend_OK",IF((IFERROR(IFERROR(VLOOKUP(A32,Agendamento!A:C,3,0),VLOOKUP(B32,Agendamento!B:C,2,0)&"B"),"Encaixe"))="AgendadoB","Agend_NOK",IF((IFERROR(IFERROR(VLOOKUP(A32,Agendamento!A:C,3,0),VLOOKUP(B32,Agendamento!B:C,2,0)&"B"),"Encaixe"))="Encaixe","Encaixe","Não Utilizou")))) -> Agend_NOK | K32: =IFERROR(VLOOKUP(L32,'Base Colaboradores'!C:F,4,0),"PRESTADOR DE SERVIÇOS") -> TECNOLOGIA | L32: MG2 | M32: PAULA FERNANDA LAGE MONTEIRO | N32: TEC CAPTACAO SOM I
A33: =IF(LEN(D33)>1,D33,E33)&F33&H33&G33 -> 03544004798EG x Sambodromo4606822h | B33: =IF(LEN(D33)>1,D33,E33)&F33&H33 -> 03544004798EG x Sambodromo46068 | C33: CRISTIANE RANGEL | E33: 03544004798 | F33: EG x Sambodromo | G33: 22h | H33: =IF(LEFT(I33,1)="1",46068,IF(LEFT(I33,1)="2",46069,IF(LEFT(I33,1)="3",46070,46074))) -> 46068 | I33: 1 - Primeiro dia | J33: =IF(LEN(A33&B33)<2,"Não Utilizou",IF((IFERROR(IFERROR(VLOOKUP(A33,Agendamento!A:C,3,0),VLOOKUP(B33,Agendamento!B:C,2,0)&"B"),"Encaixe"))="Agendado","Agend_OK",IF((IFERROR(IFERROR(VLOOKUP(A33,Agendamento!A:C,3,0),VLOOKUP(B33,Agendamento!B:C,2,0)&"B"),"Encaixe"))="AgendadoB","Agend_NOK",IF((IFERROR(IFERROR(VLOOKUP(A33,Agendamento!A:C,3,0),VLOOKUP(B33,Agendamento!B:C,2,0)&"B"),"Encaixe"))="Encaixe","Encaixe","Não Utilizou")))) -> Encaixe | K33: =IFERROR(VLOOKUP(L33,'Base Colaboradores'!C:F,4,0),"PRESTADOR DE SERVIÇOS") -> PRESTADOR DE SERVIÇOS | L33: Prestador | M33: Prestador | N33: Prestador
A34: =IF(LEN(D34)>1,D34,E34)&F34&H34&G34 -> 55607EG x Sambodromo4606817h | B34: =IF(LEN(D34)>1,D34,E34)&F34&H34 -> 55607EG x Sambodromo46068 | C34: CRISTIANO BORGES | D34: 55607 | F34: EG x Sambodromo | G34: 17h | H34: =IF(LEFT(I34,1)="1",46068,IF(LEFT(I34,1)="2",46069,IF(LEFT(I34,1)="3",46070,46074))) -> 46068 | I34: 1 - Primeiro dia | J34: =IF(LEN(A34&B34)<2,"Não Utilizou",IF((IFERROR(IFERROR(VLOOKUP(A34,Agendamento!A:C,3,0),VLOOKUP(B34,Agendamento!B:C,2,0)&"B"),"Encaixe"))="Agendado","Agend_OK",IF((IFERROR(IFERROR(VLOOKUP(A34,Agendamento!A:C,3,0),VLOOKUP(B34,Agendamento!B:C,2,0)&"B"),"Encaixe"))="AgendadoB","Agend_NOK",IF((IFERROR(IFERROR(VLOOKUP(A34,Agendamento!A:C,3,0),VLOOKUP(B34,Agendamento!B:C,2,0)&"B"),"Encaixe"))="Encaixe","Encaixe","Não Utilizou")))) -> Encaixe | K34: =IFERROR(VLOOKUP(L34,'Base Colaboradores'!C:F,4,0),"PRESTADOR DE SERVIÇOS") -> ESTUDIOS GLOBO | L34: PRODUCAO DE PERSONAGEM E AMBIENTE | M34: SAMANTHA DA COSTA ABEL | N34: PRODUTOR ARTE TITULAR
A35: =IF(LEN(D35)>1,D35,E35)&F35&H35&G35 -> 64607EG x Sambodromo4606817h | B35: =IF(LEN(D35)>1,D35,E35)&F35&H35 -> 64607EG x Sambodromo46068 | C35: CRISTIANO CRUZ | D35: 64607 | F35: EG x Sambodromo | G35: 17h | H35: =IF(LEFT(I35,1)="1",46068,IF(LEFT(I35,1)="2",46069,IF(LEFT(I35,1)="3",46070,46074))) -> 46068 | I35: 1 - Primeiro dia | J35: =IF(LEN(A35&B35)<2,"Não Utilizou",IF((IFERROR(IFERROR(VLOOKUP(A35,Agendamento!A:C,3,0),VLOOKUP(B35,Agendamento!B:C,2,0)&"B"),"Encaixe"))="Agendado","Agend_OK",IF((IFERROR(IFERROR(VLOOKUP(A35,Agendamento!A:C,3,0),VLOOKUP(B35,Agendamento!B:C,2,0)&"B"),"Encaixe"))="AgendadoB","Agend_NOK",IF((IFERROR(IFERROR(VLOOKUP(A35,Agendamento!A:C,3,0),VLOOKUP(B35,Agendamento!B:C,2,0)&"B"),"Encaixe"))="Encaixe","Encaixe","Não Utilizou")))) -> Agend_OK | K35: =IFERROR(VLOOKUP(L35,'Base Colaboradores'!C:F,4,0),"PRESTADOR DE SERVIÇOS") -> TECNOLOGIA | L35: IMAGEM EG | M35: FABIO LOEWENBACH CASCAO | N35: OPER CAMERA I
A36: =IF(LEN(D36)>1,D36,E36)&F36&H36&G36 -> 11414282702EG x Sambodromo4606818h | B36: =IF(LEN(D36)>1,D36,E36)&F36&H36 -> 11414282702EG x Sambodromo46068 | C36: DANIEL DEPLAN | E36: 11414282702 | F36: EG x Sambodromo | G36: 18h | H36: =IF(LEFT(I36,1)="1",46068,IF(LEFT(I36,1)="2",46069,IF(LEFT(I36,1)="3",46070,46074))) -> 46068 | I36: 1 - Primeiro dia | J36: =IF(LEN(A36&B36)<2,"Não Utilizou",IF((IFERROR(IFERROR(VLOOKUP(A36,Agendamento!A:C,3,0),VLOOKUP(B36,Agendamento!B:C,2,0)&"B"),"Encaixe"))="Agendado","Agend_OK",IF((IFERROR(IFERROR(VLOOKUP(A36,Agendamento!A:C,3,0),VLOOKUP(B36,Agendamento!B:C,2,0)&"B"),"Encaixe"))="AgendadoB","Agend_NOK",IF((IFERROR(IFERROR(VLOOKUP(A36,Agendamento!A:C,3,0),VLOOKUP(B36,Agendamento!B:C,2,0)&"B"),"Encaixe"))="Encaixe","Encaixe","Não Utilizou")))) -> Agend_NOK | K36: =IFERROR(VLOOKUP(L36,'Base Colaboradores'!C:F,4,0),"PRESTADOR DE SERVIÇOS") -> PRESTADOR DE SERVIÇOS | L36: Gilberto Merguizo Management Studio Eireli ( CAPA MGT) | M36: Prestador | N36: Prestador
A37: =IF(LEN(D37)>1,D37,E37)&F37&H37&G37 -> 86474JB x Sambodromo4606819h | B37: =IF(LEN(D37)>1,D37,E37)&F37&H37 -> 86474JB x Sambodromo46068 | C37: DANIEL PERALTA | D37: 86474 | F37: JB x Sambodromo | G37: 19h | H37: =IF(LEFT(I37,1)="1",46068,IF(LEFT(I37,1)="2",46069,IF(LEFT(I37,1)="3",46070,46074))) -> 46068 | I37: 1 - Primeiro dia | J37: =IF(LEN(A37&B37)<2,"Não Utilizou",IF((IFERROR(IFERROR(VLOOKUP(A37,Agendamento!A:C,3,0),VLOOKUP(B37,Agendamento!B:C,2,0)&"B"),"Encaixe"))="Agendado","Agend_OK",IF((IFERROR(IFERROR(VLOOKUP(A37,Agendamento!A:C,3,0),VLOOKUP(B37,Agendamento!B:C,2,0)&"B"),"Encaixe"))="AgendadoB","Agend_NOK",IF((IFERROR(IFERROR(VLOOKUP(A37,Agendamento!A:C,3,0),VLOOKUP(B37,Agendamento!B:C,2,0)&"B"),"Encaixe"))="Encaixe","Encaixe","Não Utilizou")))) -> Agend_NOK | K37: =IFERROR(VLOOKUP(L37,'Base Colaboradores'!C:F,4,0),"PRESTADOR DE SERVIÇOS") -> JORNALISMO | L37: SUPERVISAO IMAGEM RJ | M37: EDUARDO ALBERTO FERNANDEZ | N37: REPORTER CINEMATOGRAFICO III
A38: =IF(LEN(D38)>1,D38,E38)&F38&H38&G38 -> 78576EG x Sambodromo4606819h | B38: =IF(LEN(D38)>1,D38,E38)&F38&H38 -> 78576EG x Sambodromo46068 | C38: DANIELLA GUEDES | D38: 78576 | F38: EG x Sambodromo | G38: 19h | H38: =IF(LEFT(I38,1)="1",46068,IF(LEFT(I38,1)="2",46069,IF(LEFT(I38,1)="3",46070,46074))) -> 46068 | I38: 1 - Primeiro dia | J38: =IF(LEN(A38&B38)<2,"Não Utilizou",IF((IFERROR(IFERROR(VLOOKUP(A38,Agendamento!A:C,3,0),VLOOKUP(B38,Agendamento!B:C,2,0)&"B"),"Encaixe"))="Agendado","Agend_OK",IF((IFERROR(IFERROR(VLOOKUP(A38,Agendamento!A:C,3,0),VLOOKUP(B38,Agendamento!B:C,2,0)&"B"),"Encaixe"))="AgendadoB","Agend_NOK",IF((IFERROR(IFERROR(VLOOKUP(A38,Agendamento!A:C,3,0),VLOOKUP(B38,Agendamento!B:C,2,0)&"B"),"Encaixe"))="Encaixe","Encaixe","Não Utilizou")))) -> Agend_OK | K38: =IFERROR(VLOOKUP(L38,'Base Colaboradores'!C:F,4,0),"PRESTADOR DE SERVIÇOS") -> FINANCAS JURIDICO E INFRAESTRUTURA | L38: LOCACOES E LICENCIAMENTO DE EXTERNAS E EVENTOS | M38: RENATA RAPOSEIRAS SANTARONI | N38: ANL GESTAO IMOBILIARIA E AMBIENTAL III
A39: =IF(LEN(D39)>1,D39,E39)&F39&H39&G39 -> 87937EG x Sambodromo4606821h | B39: =IF(LEN(D39)>1,D39,E39)&F39&H39 -> 87937EG x Sambodromo46068 | C39: DAVI SAMPAIO | D39: 87937 | F39: EG x Sambodromo | G39: 21h | H39: =IF(LEFT(I39,1)="1",46068,IF(LEFT(I39,1)="2",46069,IF(LEFT(I39,1)="3",46070,46074))) -> 46068 | I39: 1 - Primeiro dia | J39: =IF(LEN(A39&B39)<2,"Não Utilizou",IF((IFERROR(IFERROR(VLOOKUP(A39,Agendamento!A:C,3,0),VLOOKUP(B39,Agendamento!B:C,2,0)&"B"),"Encaixe"))="Agendado","Agend_OK",IF((IFERROR(IFERROR(VLOOKUP(A39,Agendamento!A:C,3,0),VLOOKUP(B39,Agendamento!B:C,2,0)&"B"),"Encaixe"))="AgendadoB","Agend_NOK",IF((IFERROR(IFERROR(VLOOKUP(A39,Agendamento!A:C,3,0),VLOOKUP(B39,Agendamento!B:C,2,0)&"B"),"Encaixe"))="Encaixe","Encaixe","Não Utilizou")))) -> Encaixe | K39: =IFERROR(VLOOKUP(L39,'Base Colaboradores'!C:F,4,0),"PRESTADOR DE SERVIÇOS") -> TECNOLOGIA | L39: MG2 | M39: PAULA FERNANDA LAGE MONTEIRO | N39: ASSIST OPERACOES AUDIOVISUAIS II
A40: =IF(LEN(D40)>1,D40,E40)&F40&H40&G40 -> 92986JB x Sambodromo4606818h | B40: =IF(LEN(D40)>1,D40,E40)&F40&H40 -> 92986JB x Sambodromo46068 | C40: DAYANE ASSIS | D40: 92986 | F40: JB x Sambodromo | G40: 18h | H40: =IF(LEFT(I40,1)="1",46068,IF(LEFT(I40,1)="2",46069,IF(LEFT(I40,1)="3",46070,46074))) -> 46068 | I40: 1 - Primeiro dia | J40: =IF(LEN(A40&B40)<2,"Não Utilizou",IF((IFERROR(IFERROR(VLOOKUP(A40,Agendamento!A:C,3,0),VLOOKUP(B40,Agendamento!B:C,2,0)&"B"),"Encaixe"))="Agendado","Agend_OK",IF((IFERROR(IFERROR(VLOOKUP(A40,Agendamento!A:C,3,0),VLOOKUP(B40,Agendamento!B:C,2,0)&"B"),"Encaixe"))="AgendadoB","Agend_NOK",IF((IFERROR(IFERROR(VLOOKUP(A40,Agendamento!A:C,3,0),VLOOKUP(B40,Agendamento!B:C,2,0)&"B"),"Encaixe"))="Encaixe","Encaixe","Não Utilizou")))) -> Agend_OK | K40: =IFERROR(VLOOKUP(L40,'Base Colaboradores'!C:F,4,0),"PRESTADOR DE SERVIÇOS") -> TECNOLOGIA | L40: MG2 | M40: PAULA FERNANDA LAGE MONTEIRO | N40: ASSIST OPERACOES AUDIOVISUAIS I
A41: =IF(LEN(D41)>1,D41,E41)&F41&H41&G41 -> 92096EG x Sambodromo4606817h | B41: =IF(LEN(D41)>1,D41,E41)&F41&H41 -> 92096EG x Sambodromo46068 | C41: DEBORA VIANA | D41: 92096 | F41: EG x Sambodromo | G41: 17h | H41: =IF(LEFT(I41,1)="1",46068,IF(LEFT(I41,1)="2",46069,IF(LEFT(I41,1)="3",46070,46074))) -> 46068 | I41: 1 - Primeiro dia | J41: =IF(LEN(A41&B41)<2,"Não Utilizou",IF((IFERROR(IFERROR(VLOOKUP(A41,Agendamento!A:C,3,0),VLOOKUP(B41,Agendamento!B:C,2,0)&"B"),"Encaixe"))="Agendado","Agend_OK",IF((IFERROR(IFERROR(VLOOKUP(A41,Agendamento!A:C,3,0),VLOOKUP(B41,Agendamento!B:C,2,0)&"B"),"Encaixe"))="AgendadoB","Agend_NOK",IF((IFERROR(IFERROR(VLOOKUP(A41,Agendamento!A:C,3,0),VLOOKUP(B41,Agendamento!B:C,2,0)&"B"),"Encaixe"))="Encaixe","Encaixe","Não Utilizou")))) -> Encaixe | K41: =IFERROR(VLOOKUP(L41,'Base Colaboradores'!C:F,4,0),"PRESTADOR DE SERVIÇOS") -> TECNOLOGIA | L41: MG2 | M41: PAULA FERNANDA LAGE MONTEIRO | N41: ASSIST OPERACOES AUDIOVISUAIS I
A42: =IF(LEN(D42)>1,D42,E42)&F42&H42&G42 -> 70163EG x Sambodromo4606820h | B42: =IF(LEN(D42)>1,D42,E42)&F42&H42 -> 70163EG x Sambodromo46068 | C42: DIEGO FONTOURA | D42: 70163 | F42: EG x Sambodromo | G42: 20h | H42: =IF(LEFT(I42,1)="1",46068,IF(LEFT(I42,1)="2",46069,IF(LEFT(I42,1)="3",46070,46074))) -> 46068 | I42: 1 - Primeiro dia | J42: =IF(LEN(A42&B42)<2,"Não Utilizou",IF((IFERROR(IFERROR(VLOOKUP(A42,Agendamento!A:C,3,0),VLOOKUP(B42,Agendamento!B:C,2,0)&"B"),"Encaixe"))="Agendado","Agend_OK",IF((IFERROR(IFERROR(VLOOKUP(A42,Agendamento!A:C,3,0),VLOOKUP(B42,Agendamento!B:C,2,0)&"B"),"Encaixe"))="AgendadoB","Agend_NOK",IF((IFERROR(IFERROR(VLOOKUP(A42,Agendamento!A:C,3,0),VLOOKUP(B42,Agendamento!B:C,2,0)&"B"),"Encaixe"))="Encaixe","Encaixe","Não Utilizou")))) -> Encaixe | K42: =IFERROR(VLOOKUP(L42,'Base Colaboradores'!C:F,4,0),"PRESTADOR DE SERVIÇOS") -> TECNOLOGIA | L42: CAPTACAO EVENTOS ION | M42: IGOR GRACIANO DA SILVA | N42: TEC CAPTACAO SOM I
A43: =IF(LEN(D43)>1,D43,E43)&F43&H43&G43 -> 89176EG x Sambodromo4606817h | B43: =IF(LEN(D43)>1,D43,E43)&F43&H43 -> 89176EG x Sambodromo46068 | C43: DIEGO PEIXOTO | D43: 89176 | F43: EG x Sambodromo | G43: 17h | H43: =IF(LEFT(I43,1)="1",46068,IF(LEFT(I43,1)="2",46069,IF(LEFT(I43,1)="3",46070,46074))) -> 46068 | I43: 1 - Primeiro dia | J43: =IF(LEN(A43&B43)<2,"Não Utilizou",IF((IFERROR(IFERROR(VLOOKUP(A43,Agendamento!A:C,3,0),VLOOKUP(B43,Agendamento!B:C,2,0)&"B"),"Encaixe"))="Agendado","Agend_OK",IF((IFERROR(IFERROR(VLOOKUP(A43,Agendamento!A:C,3,0),VLOOKUP(B43,Agendamento!B:C,2,0)&"B"),"Encaixe"))="AgendadoB","Agend_NOK",IF((IFERROR(IFERROR(VLOOKUP(A43,Agendamento!A:C,3,0),VLOOKUP(B43,Agendamento!B:C,2,0)&"B"),"Encaixe"))="Encaixe","Encaixe","Não Utilizou")))) -> Encaixe | K43: =IFERROR(VLOOKUP(L43,'Base Colaboradores'!C:F,4,0),"PRESTADOR DE SERVIÇOS") -> ESTUDIOS GLOBO | L43: PRODUCAO ARTE E DESIGN | M43: TATIANA MANSO CASTELLO BRANCO | N43: PRODUTOR ARTE ASSISTENTE IV
A44: =IF(LEN(D44)>1,D44,E44)&F44&H44&G44 -> 26483JB x Sambodromo4606818h | B44: =IF(LEN(D44)>1,D44,E44)&F44&H44 -> 26483JB x Sambodromo46068 | C44: DIOGENES MELQUIADES | D44: 26483 | F44: JB x Sambodromo | G44: 18h | H44: =IF(LEFT(I44,1)="1",46068,IF(LEFT(I44,1)="2",46069,IF(LEFT(I44,1)="3",46070,46074))) -> 46068 | I44: 1 - Primeiro dia | J44: =IF(LEN(A44&B44)<2,"Não Utilizou",IF((IFERROR(IFERROR(VLOOKUP(A44,Agendamento!A:C,3,0),VLOOKUP(B44,Agendamento!B:C,2,0)&"B"),"Encaixe"))="Agendado","Agend_OK",IF((IFERROR(IFERROR(VLOOKUP(A44,Agendamento!A:C,3,0),VLOOKUP(B44,Agendamento!B:C,2,0)&"B"),"Encaixe"))="AgendadoB","Agend_NOK",IF((IFERROR(IFERROR(VLOOKUP(A44,Agendamento!A:C,3,0),VLOOKUP(B44,Agendamento!B:C,2,0)&"B"),"Encaixe"))="Encaixe","Encaixe","Não Utilizou")))) -> Encaixe | K44: =IFERROR(VLOOKUP(L44,'Base Colaboradores'!C:F,4,0),"PRESTADOR DE SERVIÇOS") -> JORNALISMO | L44: SUPERVISAO IMAGEM RJ | M44: EDUARDO ALBERTO FERNANDEZ | N44: REPORTER CINEMATOGRAFICO II
A45: =IF(LEN(D45)>1,D45,E45)&F45&H45&G45 -> 47107EG x Sambodromo4606818h | B45: =IF(LEN(D45)>1,D45,E45)&F45&H45 -> 47107EG x Sambodromo46068 | C45: DOUGLAS AZEREDO | D45: 47107 | F45: EG x Sambodromo | G45: 18h | H45: =IF(LEFT(I45,1)="1",46068,IF(LEFT(I45,1)="2",46069,IF(LEFT(I45,1)="3",46070,46074))) -> 46068 | I45: 1 - Primeiro dia | J45: =IF(LEN(A45&B45)<2,"Não Utilizou",IF((IFERROR(IFERROR(VLOOKUP(A45,Agendamento!A:C,3,0),VLOOKUP(B45,Agendamento!B:C,2,0)&"B"),"Encaixe"))="Agendado","Agend_OK",IF((IFERROR(IFERROR(VLOOKUP(A45,Agendamento!A:C,3,0),VLOOKUP(B45,Agendamento!B:C,2,0)&"B"),"Encaixe"))="AgendadoB","Agend_NOK",IF((IFERROR(IFERROR(VLOOKUP(A45,Agendamento!A:C,3,0),VLOOKUP(B45,Agendamento!B:C,2,0)&"B"),"Encaixe"))="Encaixe","Encaixe","Não Utilizou")))) -> Encaixe | K45: =IFERROR(VLOOKUP(L45,'Base Colaboradores'!C:F,4,0),"PRESTADOR DE SERVIÇOS") -> FINANCAS JURIDICO E INFRAESTRUTURA | L45: LOG EQUIPAMENTO JORNALISMO GSAT ESTUDIOS PRODUTORA | M45: THIAGO COSTA QUINTANILHA | N45: COORD LOGISTICA
A46: =IF(LEN(D46)>1,D46,E46)&F46&H46&G46 -> 16637174785EG x Sambodromo4606817h | B46: =IF(LEN(D46)>1,D46,E46)&F46&H46 -> 16637174785EG x Sambodromo46068 | C46: DOUGLAS BATISTA | E46: 16637174785 | F46: EG x Sambodromo | G46: 17h | H46: =IF(LEFT(I46,1)="1",46068,IF(LEFT(I46,1)="2",46069,IF(LEFT(I46,1)="3",46070,46074))) -> 46068 | I46: 1 - Primeiro dia | J46: =IF(LEN(A46&B46)<2,"Não Utilizou",IF((IFERROR(IFERROR(VLOOKUP(A46,Agendamento!A:C,3,0),VLOOKUP(B46,Agendamento!B:C,2,0)&"B"),"Encaixe"))="Agendado","Agend_OK",IF((IFERROR(IFERROR(VLOOKUP(A46,Agendamento!A:C,3,0),VLOOKUP(B46,Agendamento!B:C,2,0)&"B"),"Encaixe"))="AgendadoB","Agend_NOK",IF((IFERROR(IFERROR(VLOOKUP(A46,Agendamento!A:C,3,0),VLOOKUP(B46,Agendamento!B:C,2,0)&"B"),"Encaixe"))="Encaixe","Encaixe","Não Utilizou")))) -> Agend_OK | K46: =IFERROR(VLOOKUP(L46,'Base Colaboradores'!C:F,4,0),"PRESTADOR DE SERVIÇOS") -> PRESTADOR DE SERVIÇOS | L46: Top Service | M46: Prestador | N46: Prestador
A47: =IF(LEN(D47)>1,D47,E47)&F47&H47&G47 -> 1402526EG x Sambodromo4606817h | B47: =IF(LEN(D47)>1,D47,E47)&F47&H47 -> 1402526EG x Sambodromo46068 | C47: EDUARDO BEZERRA | E47: 1402526 | F47: EG x Sambodromo | G47: 17h | H47: =IF(LEFT(I47,1)="1",46068,IF(LEFT(I47,1)="2",46069,IF(LEFT(I47,1)="3",46070,46074))) -> 46068 | I47: 1 - Primeiro dia | J47: =IF(LEN(A47&B47)<2,"Não Utilizou",IF((IFERROR(IFERROR(VLOOKUP(A47,Agendamento!A:C,3,0),VLOOKUP(B47,Agendamento!B:C,2,0)&"B"),"Encaixe"))="Agendado","Agend_OK",IF((IFERROR(IFERROR(VLOOKUP(A47,Agendamento!A:C,3,0),VLOOKUP(B47,Agendamento!B:C,2,0)&"B"),"Encaixe"))="AgendadoB","Agend_NOK",IF((IFERROR(IFERROR(VLOOKUP(A47,Agendamento!A:C,3,0),VLOOKUP(B47,Agendamento!B:C,2,0)&"B"),"Encaixe"))="Encaixe","Encaixe","Não Utilizou")))) -> Encaixe | K47: =IFERROR(VLOOKUP(L47,'Base Colaboradores'!C:F,4,0),"PRESTADOR DE SERVIÇOS") -> PRESTADOR DE SERVIÇOS | L47: Prestador | M47: Prestador | N47: Prestador
A48: =IF(LEN(D48)>1,D48,E48)&F48&H48&G48 -> 51401EG x Sambodromo4606817h | B48: =IF(LEN(D48)>1,D48,E48)&F48&H48 -> 51401EG x Sambodromo46068 | C48: EDUARDO MAZZA | D48: 51401 | F48: EG x Sambodromo | G48: 17h | H48: =IF(LEFT(I48,1)="1",46068,IF(LEFT(I48,1)="2",46069,IF(LEFT(I48,1)="3",46070,46074))) -> 46068 | I48: 1 - Primeiro dia | J48: =IF(LEN(A48&B48)<2,"Não Utilizou",IF((IFERROR(IFERROR(VLOOKUP(A48,Agendamento!A:C,3,0),VLOOKUP(B48,Agendamento!B:C,2,0)&"B"),"Encaixe"))="Agendado","Agend_OK",IF((IFERROR(IFERROR(VLOOKUP(A48,Agendamento!A:C,3,0),VLOOKUP(B48,Agendamento!B:C,2,0)&"B"),"Encaixe"))="AgendadoB","Agend_NOK",IF((IFERROR(IFERROR(VLOOKUP(A48,Agendamento!A:C,3,0),VLOOKUP(B48,Agendamento!B:C,2,0)&"B"),"Encaixe"))="Encaixe","Encaixe","Não Utilizou")))) -> Agend_OK | K48: =IFERROR(VLOOKUP(L48,'Base Colaboradores'!C:F,4,0),"PRESTADOR DE SERVIÇOS") -> TECNOLOGIA | L48: MG2 | M48: PAULA FERNANDA LAGE MONTEIRO | N48: ASSIST OPERACOES AUDIOVISUAIS II
A49: =IF(LEN(D49)>1,D49,E49)&F49&H49&G49 -> 39266EG x Sambodromo4606817h | B49: =IF(LEN(D49)>1,D49,E49)&F49&H49 -> 39266EG x Sambodromo46068 | C49: EDUARDO SANTANA | D49: 39266 | F49: EG x Sambodromo | G49: 17h | H49: =IF(LEFT(I49,1)="1",46068,IF(LEFT(I49,1)="2",46069,IF(LEFT(I49,1)="3",46070,46074))) -> 46068 | I49: 1 - Primeiro dia | J49: =IF(LEN(A49&B49)<2,"Não Utilizou",IF((IFERROR(IFERROR(VLOOKUP(A49,Agendamento!A:C,3,0),VLOOKUP(B49,Agendamento!B:C,2,0)&"B"),"Encaixe"))="Agendado","Agend_OK",IF((IFERROR(IFERROR(VLOOKUP(A49,Agendamento!A:C,3,0),VLOOKUP(B49,Agendamento!B:C,2,0)&"B"),"Encaixe"))="AgendadoB","Agend_NOK",IF((IFERROR(IFERROR(VLOOKUP(A49,Agendamento!A:C,3,0),VLOOKUP(B49,Agendamento!B:C,2,0)&"B"),"Encaixe"))="Encaixe","Encaixe","Não Utilizou")))) -> Agend_NOK | K49: =IFERROR(VLOOKUP(L49,'Base Colaboradores'!C:F,4,0),"PRESTADOR DE SERVIÇOS") -> TECNOLOGIA | L49: IMAGEM EG | M49: FABIO LOEWENBACH CASCAO | N49: OPER CAMERA III
A50: =IF(LEN(D50)>1,D50,E50)&F50&H50&G50 -> 12452485705EG x Sambodromo4606819h | B50: =IF(LEN(D50)>1,D50,E50)&F50&H50 -> 12452485705EG x Sambodromo46068 | C50: ELLEN SOARES | E50: 12452485705 | F50: EG x Sambodromo | G50: 19h | H50: =IF(LEFT(I50,1)="1",46068,IF(LEFT(I50,1)="2",46069,IF(LEFT(I50,1)="3",46070,46074))) -> 46068 | I50: 1 - Primeiro dia | J50: =IF(LEN(A50&B50)<2,"Não Utilizou",IF((IFERROR(IFERROR(VLOOKUP(A50,Agendamento!A:C,3,0),VLOOKUP(B50,Agendamento!B:C,2,0)&"B"),"Encaixe"))="Agendado","Agend_OK",IF((IFERROR(IFERROR(VLOOKUP(A50,Agendamento!A:C,3,0),VLOOKUP(B50,Agendamento!B:C,2,0)&"B"),"Encaixe"))="AgendadoB","Agend_NOK",IF((IFERROR(IFERROR(VLOOKUP(A50,Agendamento!A:C,3,0),VLOOKUP(B50,Agendamento!B:C,2,0)&"B"),"Encaixe"))="Encaixe","Encaixe","Não Utilizou")))) -> Agend_NOK | K50: =IFERROR(VLOOKUP(L50,'Base Colaboradores'!C:F,4,0),"PRESTADOR DE SERVIÇOS") -> PRESTADOR DE SERVIÇOS | L50: Aura Imagens LTDA | M50: Prestador | N50: Prestador
A51: =IF(LEN(D51)>1,D51,E51)&F51&H51&G51 -> 89936JB x Sambodromo4606821h | B51: =IF(LEN(D51)>1,D51,E51)&F51&H51 -> 89936JB x Sambodromo46068 | C51: ESTER LIMA | D51: 89936 | F51: JB x Sambodromo | G51: 21h | H51: =IF(LEFT(I51,1)="1",46068,IF(LEFT(I51,1)="2",46069,IF(LEFT(I51,1)="3",46070,46074))) -> 46068 | I51: 1 - Primeiro dia | J51: =IF(LEN(A51&B51)<2,"Não Utilizou",IF((IFERROR(IFERROR(VLOOKUP(A51,Agendamento!A:C,3,0),VLOOKUP(B51,Agendamento!B:C,2,0)&"B"),"Encaixe"))="Agendado","Agend_OK",IF((IFERROR(IFERROR(VLOOKUP(A51,Agendamento!A:C,3,0),VLOOKUP(B51,Agendamento!B:C,2,0)&"B"),"Encaixe"))="AgendadoB","Agend_NOK",IF((IFERROR(IFERROR(VLOOKUP(A51,Agendamento!A:C,3,0),VLOOKUP(B51,Agendamento!B:C,2,0)&"B"),"Encaixe"))="Encaixe","Encaixe","Não Utilizou")))) -> Encaixe | K51: =IFERROR(VLOOKUP(L51,'Base Colaboradores'!C:F,4,0),"PRESTADOR DE SERVIÇOS") -> JORNALISMO | L51: SUPERVISAO EDITORIA RJ 03 04 | M51: FABRICIO PRADO MARTA | N51: PRODUTOR REPORTAGEM I
A52: =IF(LEN(D52)>1,D52,E52)&F52&H52&G52 -> 29913EG x Sambodromo4606820h | B52: =IF(LEN(D52)>1,D52,E52)&F52&H52 -> 29913EG x Sambodromo46068 | C52: FABIANO SIQUEIRA | D52: 29913 | F52: EG x Sambodromo | G52: 20h | H52: =IF(LEFT(I52,1)="1",46068,IF(LEFT(I52,1)="2",46069,IF(LEFT(I52,1)="3",46070,46074))) -> 46068 | I52: 1 - Primeiro dia | J52: =IF(LEN(A52&B52)<2,"Não Utilizou",IF((IFERROR(IFERROR(VLOOKUP(A52,Agendamento!A:C,3,0),VLOOKUP(B52,Agendamento!B:C,2,0)&"B"),"Encaixe"))="Agendado","Agend_OK",IF((IFERROR(IFERROR(VLOOKUP(A52,Agendamento!A:C,3,0),VLOOKUP(B52,Agendamento!B:C,2,0)&"B"),"Encaixe"))="AgendadoB","Agend_NOK",IF((IFERROR(IFERROR(VLOOKUP(A52,Agendamento!A:C,3,0),VLOOKUP(B52,Agendamento!B:C,2,0)&"B"),"Encaixe"))="Encaixe","Encaixe","Não Utilizou")))) -> Agend_OK | K52: =IFERROR(VLOOKUP(L52,'Base Colaboradores'!C:F,4,0),"PRESTADOR DE SERVIÇOS") -> TECNOLOGIA | L52: MG2 | M52: PAULA FERNANDA LAGE MONTEIRO | N52: ILUMINADOR II
A53: =IF(LEN(D53)>1,D53,E53)&F53&H53&G53 -> 78101EG x Sambodromo4606822h | B53: =IF(LEN(D53)>1,D53,E53)&F53&H53 -> 78101EG x Sambodromo46068 | C53: FABIANO VAZ | D53: 78101 | F53: EG x Sambodromo | G53: 22h | H53: =IF(LEFT(I53,1)="1",46068,IF(LEFT(I53,1)="2",46069,IF(LEFT(I53,1)="3",46070,46074))) -> 46068 | I53: 1 - Primeiro dia | J53: =IF(LEN(A53&B53)<2,"Não Utilizou",IF((IFERROR(IFERROR(VLOOKUP(A53,Agendamento!A:C,3,0),VLOOKUP(B53,Agendamento!B:C,2,0)&"B"),"Encaixe"))="Agendado","Agend_OK",IF((IFERROR(IFERROR(VLOOKUP(A53,Agendamento!A:C,3,0),VLOOKUP(B53,Agendamento!B:C,2,0)&"B"),"Encaixe"))="AgendadoB","Agend_NOK",IF((IFERROR(IFERROR(VLOOKUP(A53,Agendamento!A:C,3,0),VLOOKUP(B53,Agendamento!B:C,2,0)&"B"),"Encaixe"))="Encaixe","Encaixe","Não Utilizou")))) -> Encaixe | K53: =IFERROR(VLOOKUP(L53,'Base Colaboradores'!C:F,4,0),"PRESTADOR DE SERVIÇOS") -> FINANCAS JURIDICO E INFRAESTRUTURA | L53: TRANSPORTES RJ | M53: FABIO PAIXAO DOS SANTOS | N53: ENC SERVICOS
A54: =IF(LEN(D54)>1,D54,E54)&F54&H54&G54 -> 68808EG x Sambodromo4606820h | B54: =IF(LEN(D54)>1,D54,E54)&F54&H54 -> 68808EG x Sambodromo46068 | C54: FABIO PAIXAO | D54: 68808 | F54: EG x Sambodromo | G54: 20h | H54: =IF(LEFT(I54,1)="1",46068,IF(LEFT(I54,1)="2",46069,IF(LEFT(I54,1)="3",46070,46074))) -> 46068 | I54: 1 - Primeiro dia | J54: =IF(LEN(A54&B54)<2,"Não Utilizou",IF((IFERROR(IFERROR(VLOOKUP(A54,Agendamento!A:C,3,0),VLOOKUP(B54,Agendamento!B:C,2,0)&"B"),"Encaixe"))="Agendado","Agend_OK",IF((IFERROR(IFERROR(VLOOKUP(A54,Agendamento!A:C,3,0),VLOOKUP(B54,Agendamento!B:C,2,0)&"B"),"Encaixe"))="AgendadoB","Agend_NOK",IF((IFERROR(IFERROR(VLOOKUP(A54,Agendamento!A:C,3,0),VLOOKUP(B54,Agendamento!B:C,2,0)&"B"),"Encaixe"))="Encaixe","Encaixe","Não Utilizou")))) -> Encaixe | K54: =IFERROR(VLOOKUP(L54,'Base Colaboradores'!C:F,4,0),"PRESTADOR DE SERVIÇOS") -> FINANCAS JURIDICO E INFRAESTRUTURA | L54: TRANSPORTES RJ | M54: THIAGO COSTA QUINTANILHA | N54: COORD OPERACAO TRANSPORTES
A55: =IF(LEN(D55)>1,D55,E55)&F55&H55&G55 -> 53831EG x Sambodromo4606818h | B55: =IF(LEN(D55)>1,D55,E55)&F55&H55 -> 53831EG x Sambodromo46068 | C55: FABIO SOUZA | D55: 53831 | F55: EG x Sambodromo | G55: 18h | H55: =IF(LEFT(I55,1)="1",46068,IF(LEFT(I55,1)="2",46069,IF(LEFT(I55,1)="3",46070,46074))) -> 46068 | I55: 1 - Primeiro dia | J55: =IF(LEN(A55&B55)<2,"Não Utilizou",IF((IFERROR(IFERROR(VLOOKUP(A55,Agendamento!A:C,3,0),VLOOKUP(B55,Agendamento!B:C,2,0)&"B"),"Encaixe"))="Agendado","Agend_OK",IF((IFERROR(IFERROR(VLOOKUP(A55,Agendamento!A:C,3,0),VLOOKUP(B55,Agendamento!B:C,2,0)&"B"),"Encaixe"))="AgendadoB","Agend_NOK",IF((IFERROR(IFERROR(VLOOKUP(A55,Agendamento!A:C,3,0),VLOOKUP(B55,Agendamento!B:C,2,0)&"B"),"Encaixe"))="Encaixe","Encaixe","Não Utilizou")))) -> Encaixe | K55: =IFERROR(VLOOKUP(L55,'Base Colaboradores'!C:F,4,0),"PRESTADOR DE SERVIÇOS") -> FINANCAS JURIDICO E INFRAESTRUTURA | L55: EXTERNAS E EVENTOS EG | M55: THIAGO DE SOUZA AZEVEDO | N55: ANL SEGURANCA
A56: =IF(LEN(D56)>1,D56,E56)&F56&H56&G56 -> 82493JB x Sambodromo4606819h | B56: =IF(LEN(D56)>1,D56,E56)&F56&H56 -> 82493JB x Sambodromo46068 | C56: FABRICIO MOTA | D56: 82493 | F56: JB x Sambodromo | G56: 19h | H56: =IF(LEFT(I56,1)="1",46068,IF(LEFT(I56,1)="2",46069,IF(LEFT(I56,1)="3",46070,46074))) -> 46068 | I56: 1 - Primeiro dia | J56: =IF(LEN(A56&B56)<2,"Não Utilizou",IF((IFERROR(IFERROR(VLOOKUP(A56,Agendamento!A:C,3,0),VLOOKUP(B56,Agendamento!B:C,2,0)&"B"),"Encaixe"))="Agendado","Agend_OK",IF((IFERROR(IFERROR(VLOOKUP(A56,Agendamento!A:C,3,0),VLOOKUP(B56,Agendamento!B:C,2,0)&"B"),"Encaixe"))="AgendadoB","Agend_NOK",IF((IFERROR(IFERROR(VLOOKUP(A56,Agendamento!A:C,3,0),VLOOKUP(B56,Agendamento!B:C,2,0)&"B"),"Encaixe"))="Encaixe","Encaixe","Não Utilizou")))) -> Agend_OK | K56: =IFERROR(VLOOKUP(L56,'Base Colaboradores'!C:F,4,0),"PRESTADOR DE SERVIÇOS") -> JORNALISMO | L56: SUPERVISAO IMAGEM RJ | M56: EDUARDO ALBERTO FERNANDEZ | N56: REPORTER CINEMATOGRAFICO III
A57: =IF(LEN(D57)>1,D57,E57)&F57&H57&G57 -> 38344EG x Sambodromo4606818h | B57: =IF(LEN(D57)>1,D57,E57)&F57&H57 -> 38344EG x Sambodromo46068 | C57: FATIMA LINS | D57: 38344 | F57: EG x Sambodromo | G57: 18h | H57: =IF(LEFT(I57,1)="1",46068,IF(LEFT(I57,1)="2",46069,IF(LEFT(I57,1)="3",46070,46074))) -> 46068 | I57: 1 - Primeiro dia | J57: =IF(LEN(A57&B57)<2,"Não Utilizou",IF((IFERROR(IFERROR(VLOOKUP(A57,Agendamento!A:C,3,0),VLOOKUP(B57,Agendamento!B:C,2,0)&"B"),"Encaixe"))="Agendado","Agend_OK",IF((IFERROR(IFERROR(VLOOKUP(A57,Agendamento!A:C,3,0),VLOOKUP(B57,Agendamento!B:C,2,0)&"B"),"Encaixe"))="AgendadoB","Agend_NOK",IF((IFERROR(IFERROR(VLOOKUP(A57,Agendamento!A:C,3,0),VLOOKUP(B57,Agendamento!B:C,2,0)&"B"),"Encaixe"))="Encaixe","Encaixe","Não Utilizou")))) -> Agend_NOK | K57: =IFERROR(VLOOKUP(L57,'Base Colaboradores'!C:F,4,0),"PRESTADOR DE SERVIÇOS") -> FINANCAS JURIDICO E INFRAESTRUTURA | L57: CONSERVACAO PREDIAL EG | M57: BRUNO DA CAMARA RIBEIRO | N57: ANL OPERACOES PREDIAIS II
A58: =IF(LEN(D58)>1,D58,E58)&F58&H58&G58 -> 92430JB x Sambodromo4606819h | B58: =IF(LEN(D58)>1,D58,E58)&F58&H58 -> 92430JB x Sambodromo46068 | C58: FELIPE GOMES | D58: 92430 | F58: JB x Sambodromo | G58: 19h | H58: =IF(LEFT(I58,1)="1",46068,IF(LEFT(I58,1)="2",46069,IF(LEFT(I58,1)="3",46070,46074))) -> 46068 | I58: 1 - Primeiro dia | J58: =IF(LEN(A58&B58)<2,"Não Utilizou",IF((IFERROR(IFERROR(VLOOKUP(A58,Agendamento!A:C,3,0),VLOOKUP(B58,Agendamento!B:C,2,0)&"B"),"Encaixe"))="Agendado","Agend_OK",IF((IFERROR(IFERROR(VLOOKUP(A58,Agendamento!A:C,3,0),VLOOKUP(B58,Agendamento!B:C,2,0)&"B"),"Encaixe"))="AgendadoB","Agend_NOK",IF((IFERROR(IFERROR(VLOOKUP(A58,Agendamento!A:C,3,0),VLOOKUP(B58,Agendamento!B:C,2,0)&"B"),"Encaixe"))="Encaixe","Encaixe","Não Utilizou")))) -> Agend_OK | K58: =IFERROR(VLOOKUP(L58,'Base Colaboradores'!C:F,4,0),"PRESTADOR DE SERVIÇOS") -> PRODUTOS DIGITAIS | L58: REDES SOCIAIS GSHOW E RECEITAS | M58: MIRELLE APARECIDA MACEDO DE FRANCA | N58: COORD CONTEUDO I
A59: =IF(LEN(D59)>1,D59,E59)&F59&H59&G59 -> 256174111EG x Sambodromo4606817h | B59: =IF(LEN(D59)>1,D59,E59)&F59&H59 -> 256174111EG x Sambodromo46068 | C59: FELIPE MONTEIRO | E59: 256174111 | F59: EG x Sambodromo | G59: 17h | H59: =IF(LEFT(I59,1)="1",46068,IF(LEFT(I59,1)="2",46069,IF(LEFT(I59,1)="3",46070,46074))) -> 46068 | I59: 1 - Primeiro dia | J59: =IF(LEN(A59&B59)<2,"Não Utilizou",IF((IFERROR(IFERROR(VLOOKUP(A59,Agendamento!A:C,3,0),VLOOKUP(B59,Agendamento!B:C,2,0)&"B"),"Encaixe"))="Agendado","Agend_OK",IF((IFERROR(IFERROR(VLOOKUP(A59,Agendamento!A:C,3,0),VLOOKUP(B59,Agendamento!B:C,2,0)&"B"),"Encaixe"))="AgendadoB","Agend_NOK",IF((IFERROR(IFERROR(VLOOKUP(A59,Agendamento!A:C,3,0),VLOOKUP(B59,Agendamento!B:C,2,0)&"B"),"Encaixe"))="Encaixe","Encaixe","Não Utilizou")))) -> Encaixe | K59: =IFERROR(VLOOKUP(L59,'Base Colaboradores'!C:F,4,0),"PRESTADOR DE SERVIÇOS") -> PRESTADOR DE SERVIÇOS | L59: Prestador | M59: Prestador | N59: Prestador
A60: =IF(LEN(D60)>1,D60,E60)&F60&H60&G60 -> 08726109778EG x Sambodromo4606817h | B60: =IF(LEN(D60)>1,D60,E60)&F60&H60 -> 08726109778EG x Sambodromo46068 | C60: FELIPE DA SILVA | E60: 08726109778 | F60: EG x Sambodromo | G60: 17h | H60: =IF(LEFT(I60,1)="1",46068,IF(LEFT(I60,1)="2",46069,IF(LEFT(I60,1)="3",46070,46074))) -> 46068 | I60: 1 - Primeiro dia | J60: =IF(LEN(A60&B60)<2,"Não Utilizou",IF((IFERROR(IFERROR(VLOOKUP(A60,Agendamento!A:C,3,0),VLOOKUP(B60,Agendamento!B:C,2,0)&"B"),"Encaixe"))="Agendado","Agend_OK",IF((IFERROR(IFERROR(VLOOKUP(A60,Agendamento!A:C,3,0),VLOOKUP(B60,Agendamento!B:C,2,0)&"B"),"Encaixe"))="AgendadoB","Agend_NOK",IF((IFERROR(IFERROR(VLOOKUP(A60,Agendamento!A:C,3,0),VLOOKUP(B60,Agendamento!B:C,2,0)&"B"),"Encaixe"))="Encaixe","Encaixe","Não Utilizou")))) -> Encaixe | K60: =IFERROR(VLOOKUP(L60,'Base Colaboradores'!C:F,4,0),"PRESTADOR DE SERVIÇOS") -> PRESTADOR DE SERVIÇOS | L60: MyView Drones | M60: Prestador | N60: Prestador
A61: =IF(LEN(D61)>1,D61,E61)&F61&H61&G61 -> 62489EG x Sambodromo4606822h | B61: =IF(LEN(D61)>1,D61,E61)&F61&H61 -> 62489EG x Sambodromo46068 | C61: FELLIPE HAZON | D61: 62489 | F61: EG x Sambodromo | G61: 22h | H61: =IF(LEFT(I61,1)="1",46068,IF(LEFT(I61,1)="2",46069,IF(LEFT(I61,1)="3",46070,46074))) -> 46068 | I61: 1 - Primeiro dia | J61: =IF(LEN(A61&B61)<2,"Não Utilizou",IF((IFERROR(IFERROR(VLOOKUP(A61,Agendamento!A:C,3,0),VLOOKUP(B61,Agendamento!B:C,2,0)&"B"),"Encaixe"))="Agendado","Agend_OK",IF((IFERROR(IFERROR(VLOOKUP(A61,Agendamento!A:C,3,0),VLOOKUP(B61,Agendamento!B:C,2,0)&"B"),"Encaixe"))="AgendadoB","Agend_NOK",IF((IFERROR(IFERROR(VLOOKUP(A61,Agendamento!A:C,3,0),VLOOKUP(B61,Agendamento!B:C,2,0)&"B"),"Encaixe"))="Encaixe","Encaixe","Não Utilizou")))) -> Agend_NOK | K61: =IFERROR(VLOOKUP(L61,'Base Colaboradores'!C:F,4,0),"PRESTADOR DE SERVIÇOS") -> TECNOLOGIA | L61: IMAGEM EG | M61: FABIO LOEWENBACH CASCAO | N61: OPER CAMERA IV
A62: =IF(LEN(D62)>1,D62,E62)&F62&H62&G62 -> 84206EG x Sambodromo4606817h | B62: =IF(LEN(D62)>1,D62,E62)&F62&H62 -> 84206EG x Sambodromo46068 | C62: FERNANDA FELICIO | D62: 84206 | F62: EG x Sambodromo | G62: 17h | H62: =IF(LEFT(I62,1)="1",46068,IF(LEFT(I62,1)="2",46069,IF(LEFT(I62,1)="3",46070,46074))) -> 46068 | I62: 1 - Primeiro dia | J62: =IF(LEN(A62&B62)<2,"Não Utilizou",IF((IFERROR(IFERROR(VLOOKUP(A62,Agendamento!A:C,3,0),VLOOKUP(B62,Agendamento!B:C,2,0)&"B"),"Encaixe"))="Agendado","Agend_OK",IF((IFERROR(IFERROR(VLOOKUP(A62,Agendamento!A:C,3,0),VLOOKUP(B62,Agendamento!B:C,2,0)&"B"),"Encaixe"))="AgendadoB","Agend_NOK",IF((IFERROR(IFERROR(VLOOKUP(A62,Agendamento!A:C,3,0),VLOOKUP(B62,Agendamento!B:C,2,0)&"B"),"Encaixe"))="Encaixe","Encaixe","Não Utilizou")))) -> Agend_NOK | K62: =IFERROR(VLOOKUP(L62,'Base Colaboradores'!C:F,4,0),"PRESTADOR DE SERVIÇOS") -> TECNOLOGIA | L62: IMAGEM EG | M62: FABIO LOEWENBACH CASCAO | N62: OPER CAMERA I
A63: =IF(LEN(D63)>1,D63,E63)&F63&H63&G63 -> 36886JB x Sambodromo4606822h | B63: =IF(LEN(D63)>1,D63,E63)&F63&H63 -> 36886JB x Sambodromo46068 | C63: FERNANDA GRAELL | D63: 36886 | F63: JB x Sambodromo | G63: 22h | H63: =IF(LEFT(I63,1)="1",46068,IF(LEFT(I63,1)="2",46069,IF(LEFT(I63,1)="3",46070,46074))) -> 46068 | I63: 1 - Primeiro dia | J63: =IF(LEN(A63&B63)<2,"Não Utilizou",IF((IFERROR(IFERROR(VLOOKUP(A63,Agendamento!A:C,3,0),VLOOKUP(B63,Agendamento!B:C,2,0)&"B"),"Encaixe"))="Agendado","Agend_OK",IF((IFERROR(IFERROR(VLOOKUP(A63,Agendamento!A:C,3,0),VLOOKUP(B63,Agendamento!B:C,2,0)&"B"),"Encaixe"))="AgendadoB","Agend_NOK",IF((IFERROR(IFERROR(VLOOKUP(A63,Agendamento!A:C,3,0),VLOOKUP(B63,Agendamento!B:C,2,0)&"B"),"Encaixe"))="Encaixe","Encaixe","Não Utilizou")))) -> Encaixe | K63: =IFERROR(VLOOKUP(L63,'Base Colaboradores'!C:F,4,0),"PRESTADOR DE SERVIÇOS") -> JORNALISMO | L63: SUPERVISAO EDITORIA RJ | M63: PATRICIA DE ANDRADE PINTO | N63: REPORTER ESPECIAL I
A64: =IF(LEN(D64)>1,D64,E64)&F64&H64&G64 -> 05668430723JB x Sambodromo4606819h | B64: =IF(LEN(D64)>1,D64,E64)&F64&H64 -> 05668430723JB x Sambodromo46068 | C64: FERNANDO ACQUARONE | E64: 05668430723 | F64: JB x Sambodromo | G64: 19h | H64: =IF(LEFT(I64,1)="1",46068,IF(LEFT(I64,1)="2",46069,IF(LEFT(I64,1)="3",46070,46074))) -> 46068 | I64: 1 - Primeiro dia | J64: =IF(LEN(A64&B64)<2,"Não Utilizou",IF((IFERROR(IFERROR(VLOOKUP(A64,Agendamento!A:C,3,0),VLOOKUP(B64,Agendamento!B:C,2,0)&"B"),"Encaixe"))="Agendado","Agend_OK",IF((IFERROR(IFERROR(VLOOKUP(A64,Agendamento!A:C,3,0),VLOOKUP(B64,Agendamento!B:C,2,0)&"B"),"Encaixe"))="AgendadoB","Agend_NOK",IF((IFERROR(IFERROR(VLOOKUP(A64,Agendamento!A:C,3,0),VLOOKUP(B64,Agendamento!B:C,2,0)&"B"),"Encaixe"))="Encaixe","Encaixe","Não Utilizou")))) -> Encaixe | K64: =IFERROR(VLOOKUP(L64,'Base Colaboradores'!C:F,4,0),"PRESTADOR DE SERVIÇOS") -> PRESTADOR DE SERVIÇOS | L64: Prestador | M64: Prestador | N64: Prestador
A65: =IF(LEN(D65)>1,D65,E65)&F65&H65&G65 -> 63011EG x Sambodromo4606818h | B65: =IF(LEN(D65)>1,D65,E65)&F65&H65 -> 63011EG x Sambodromo46068 | C65: FERNANDO ANDRADE | D65: 63011 | F65: EG x Sambodromo | G65: 18h | H65: =IF(LEFT(I65,1)="1",46068,IF(LEFT(I65,1)="2",46069,IF(LEFT(I65,1)="3",46070,46074))) -> 46068 | I65: 1 - Primeiro dia | J65: =IF(LEN(A65&B65)<2,"Não Utilizou",IF((IFERROR(IFERROR(VLOOKUP(A65,Agendamento!A:C,3,0),VLOOKUP(B65,Agendamento!B:C,2,0)&"B"),"Encaixe"))="Agendado","Agend_OK",IF((IFERROR(IFERROR(VLOOKUP(A65,Agendamento!A:C,3,0),VLOOKUP(B65,Agendamento!B:C,2,0)&"B"),"Encaixe"))="AgendadoB","Agend_NOK",IF((IFERROR(IFERROR(VLOOKUP(A65,Agendamento!A:C,3,0),VLOOKUP(B65,Agendamento!B:C,2,0)&"B"),"Encaixe"))="Encaixe","Encaixe","Não Utilizou")))) -> Agend_NOK | K65: =IFERROR(VLOOKUP(L65,'Base Colaboradores'!C:F,4,0),"PRESTADOR DE SERVIÇOS") -> FINANCAS JURIDICO E INFRAESTRUTURA | L65: ALIMENTACAO EVENTOS E EXTERNAS | M65: CRISTIANE ARAUJO DIAS DA CRUZ | N65: ANL ALIMENTACAO I
A66: =IF(LEN(D66)>1,D66,E66)&F66&H66&G66 -> 87113JB x Sambodromo4606818h | B66: =IF(LEN(D66)>1,D66,E66)&F66&H66 -> 87113JB x Sambodromo46068 | C66: FRANCINI AUGUSTO | D66: 87113 | F66: JB x Sambodromo | G66: 18h | H66: =IF(LEFT(I66,1)="1",46068,IF(LEFT(I66,1)="2",46069,IF(LEFT(I66,1)="3",46070,46074))) -> 46068 | I66: 1 - Primeiro dia | J66: =IF(LEN(A66&B66)<2,"Não Utilizou",IF((IFERROR(IFERROR(VLOOKUP(A66,Agendamento!A:C,3,0),VLOOKUP(B66,Agendamento!B:C,2,0)&"B"),"Encaixe"))="Agendado","Agend_OK",IF((IFERROR(IFERROR(VLOOKUP(A66,Agendamento!A:C,3,0),VLOOKUP(B66,Agendamento!B:C,2,0)&"B"),"Encaixe"))="AgendadoB","Agend_NOK",IF((IFERROR(IFERROR(VLOOKUP(A66,Agendamento!A:C,3,0),VLOOKUP(B66,Agendamento!B:C,2,0)&"B"),"Encaixe"))="Encaixe","Encaixe","Não Utilizou")))) -> Agend_NOK | K66: =IFERROR(VLOOKUP(L66,'Base Colaboradores'!C:F,4,0),"PRESTADOR DE SERVIÇOS") -> JORNALISMO | L66: SUPERVISAO EDITORIA RJ | M66: PATRICIA DE ANDRADE PINTO | N66: REPORTER II
A67: =IF(LEN(D67)>1,D67,E67)&F67&H67&G67 -> 68495EG x Sambodromo4606818h | B67: =IF(LEN(D67)>1,D67,E67)&F67&H67 -> 68495EG x Sambodromo46068 | C67: FREDERICO SIQUEIRA | D67: 68495 | F67: EG x Sambodromo | G67: 18h | H67: =IF(LEFT(I67,1)="1",46068,IF(LEFT(I67,1)="2",46069,IF(LEFT(I67,1)="3",46070,46074))) -> 46068 | I67: 1 - Primeiro dia | J67: =IF(LEN(A67&B67)<2,"Não Utilizou",IF((IFERROR(IFERROR(VLOOKUP(A67,Agendamento!A:C,3,0),VLOOKUP(B67,Agendamento!B:C,2,0)&"B"),"Encaixe"))="Agendado","Agend_OK",IF((IFERROR(IFERROR(VLOOKUP(A67,Agendamento!A:C,3,0),VLOOKUP(B67,Agendamento!B:C,2,0)&"B"),"Encaixe"))="AgendadoB","Agend_NOK",IF((IFERROR(IFERROR(VLOOKUP(A67,Agendamento!A:C,3,0),VLOOKUP(B67,Agendamento!B:C,2,0)&"B"),"Encaixe"))="Encaixe","Encaixe","Não Utilizou")))) -> Encaixe | K67: =IFERROR(VLOOKUP(L67,'Base Colaboradores'!C:F,4,0),"PRESTADOR DE SERVIÇOS") -> FINANCAS JURIDICO E INFRAESTRUTURA | L67: OPERACOES CENOGRAFICAS | M67: THIAGO TEIXEIRA MARTINS | N67: GER OPERACOES CENOGRAFICAS
A68: =IF(LEN(D68)>1,D68,E68)&F68&H68&G68 -> 92132EG x Sambodromo4606818h | B68: =IF(LEN(D68)>1,D68,E68)&F68&H68 -> 92132EG x Sambodromo46068 | C68: GABRIELLE LOPES | D68: 92132 | F68: EG x Sambodromo | G68: 18h | H68: =IF(LEFT(I68,1)="1",46068,IF(LEFT(I68,1)="2",46069,IF(LEFT(I68,1)="3",46070,46074))) -> 46068 | I68: 1 - Primeiro dia | J68: =IF(LEN(A68&B68)<2,"Não Utilizou",IF((IFERROR(IFERROR(VLOOKUP(A68,Agendamento!A:C,3,0),VLOOKUP(B68,Agendamento!B:C,2,0)&"B"),"Encaixe"))="Agendado","Agend_OK",IF((IFERROR(IFERROR(VLOOKUP(A68,Agendamento!A:C,3,0),VLOOKUP(B68,Agendamento!B:C,2,0)&"B"),"Encaixe"))="AgendadoB","Agend_NOK",IF((IFERROR(IFERROR(VLOOKUP(A68,Agendamento!A:C,3,0),VLOOKUP(B68,Agendamento!B:C,2,0)&"B"),"Encaixe"))="Encaixe","Encaixe","Não Utilizou")))) -> Agend_OK | K68: =IFERROR(VLOOKUP(L68,'Base Colaboradores'!C:F,4,0),"PRESTADOR DE SERVIÇOS") -> PRODUTOS DIGITAIS | L68: CULTURA POP 1 | M68: ELIANE COSTA DOS SANTOS | N68: EDITOR CONTEUDO WEB I
A69: =IF(LEN(D69)>1,D69,E69)&F69&H69&G69 -> 28472EG x Sambodromo4606817h | B69: =IF(LEN(D69)>1,D69,E69)&F69&H69 -> 28472EG x Sambodromo46068 | C69: HAILSON CARMO | D69: 28472 | F69: EG x Sambodromo | G69: 17h | H69: =IF(LEFT(I69,1)="1",46068,IF(LEFT(I69,1)="2",46069,IF(LEFT(I69,1)="3",46070,46074))) -> 46068 | I69: 1 - Primeiro dia | J69: =IF(LEN(A69&B69)<2,"Não Utilizou",IF((IFERROR(IFERROR(VLOOKUP(A69,Agendamento!A:C,3,0),VLOOKUP(B69,Agendamento!B:C,2,0)&"B"),"Encaixe"))="Agendado","Agend_OK",IF((IFERROR(IFERROR(VLOOKUP(A69,Agendamento!A:C,3,0),VLOOKUP(B69,Agendamento!B:C,2,0)&"B"),"Encaixe"))="AgendadoB","Agend_NOK",IF((IFERROR(IFERROR(VLOOKUP(A69,Agendamento!A:C,3,0),VLOOKUP(B69,Agendamento!B:C,2,0)&"B"),"Encaixe"))="Encaixe","Encaixe","Não Utilizou")))) -> Encaixe | K69: =IFERROR(VLOOKUP(L69,'Base Colaboradores'!C:F,4,0),"PRESTADOR DE SERVIÇOS") -> TECNOLOGIA | L69: CAPTACAO EVENTOS ION | M69: IGOR GRACIANO DA SILVA | N69: LIDER TECNOLOGIA
A70: =IF(LEN(D70)>1,D70,E70)&F70&H70&G70 -> 40874EG x Sambodromo4606817h | B70: =IF(LEN(D70)>1,D70,E70)&F70&H70 -> 40874EG x Sambodromo46068 | C70: HARLEY ORNELAS | D70: 40874 | F70: EG x Sambodromo | G70: 17h | H70: =IF(LEFT(I70,1)="1",46068,IF(LEFT(I70,1)="2",46069,IF(LEFT(I70,1)="3",46070,46074))) -> 46068 | I70: 1 - Primeiro dia | J70: =IF(LEN(A70&B70)<2,"Não Utilizou",IF((IFERROR(IFERROR(VLOOKUP(A70,Agendamento!A:C,3,0),VLOOKUP(B70,Agendamento!B:C,2,0)&"B"),"Encaixe"))="Agendado","Agend_OK",IF((IFERROR(IFERROR(VLOOKUP(A70,Agendamento!A:C,3,0),VLOOKUP(B70,Agendamento!B:C,2,0)&"B"),"Encaixe"))="AgendadoB","Agend_NOK",IF((IFERROR(IFERROR(VLOOKUP(A70,Agendamento!A:C,3,0),VLOOKUP(B70,Agendamento!B:C,2,0)&"B"),"Encaixe"))="Encaixe","Encaixe","Não Utilizou")))) -> Encaixe | K70: =IFERROR(VLOOKUP(L70,'Base Colaboradores'!C:F,4,0),"PRESTADOR DE SERVIÇOS") -> FINANCAS JURIDICO E INFRAESTRUTURA | L70: SEGURANCA EMPRESARIAL RJ | M70: ROGERIO DUARTE GONCALVES | N70: GER SEGURANCA EMPRESARIAL RJ
A71: =IF(LEN(D71)>1,D71,E71)&F71&H71&G71 -> 55856EG x Sambodromo4606818h | B71: =IF(LEN(D71)>1,D71,E71)&F71&H71 -> 55856EG x Sambodromo46068 | C71: HOMERO CARRAZZONI | D71: 55856 | F71: EG x Sambodromo | G71: 18h | H71: =IF(LEFT(I71,1)="1",46068,IF(LEFT(I71,1)="2",46069,IF(LEFT(I71,1)="3",46070,46074))) -> 46068 | I71: 1 - Primeiro dia | J71: =IF(LEN(A71&B71)<2,"Não Utilizou",IF((IFERROR(IFERROR(VLOOKUP(A71,Agendamento!A:C,3,0),VLOOKUP(B71,Agendamento!B:C,2,0)&"B"),"Encaixe"))="Agendado","Agend_OK",IF((IFERROR(IFERROR(VLOOKUP(A71,Agendamento!A:C,3,0),VLOOKUP(B71,Agendamento!B:C,2,0)&"B"),"Encaixe"))="AgendadoB","Agend_NOK",IF((IFERROR(IFERROR(VLOOKUP(A71,Agendamento!A:C,3,0),VLOOKUP(B71,Agendamento!B:C,2,0)&"B"),"Encaixe"))="Encaixe","Encaixe","Não Utilizou")))) -> Encaixe | K71: =IFERROR(VLOOKUP(L71,'Base Colaboradores'!C:F,4,0),"PRESTADOR DE SERVIÇOS") -> FINANCAS JURIDICO E INFRAESTRUTURA | L71: SUPRIMENTOS SERVICOS E LOGISTICA | M71: MAURICIO GONZALEZ PINTO | N71: DIR SUPRIMENTOS SERVICOS E LOGISTICA
A72: =IF(LEN(D72)>1,D72,E72)&F72&H72&G72 -> 86792EG x Sambodromo4606820h | B72: =IF(LEN(D72)>1,D72,E72)&F72&H72 -> 86792EG x Sambodromo46068 | C72: IGOR RIBEIRO | D72: 86792 | F72: EG x Sambodromo | G72: 20h | H72: =IF(LEFT(I72,1)="1",46068,IF(LEFT(I72,1)="2",46069,IF(LEFT(I72,1)="3",46070,46074))) -> 46068 | I72: 1 - Primeiro dia | J72: =IF(LEN(A72&B72)<2,"Não Utilizou",IF((IFERROR(IFERROR(VLOOKUP(A72,Agendamento!A:C,3,0),VLOOKUP(B72,Agendamento!B:C,2,0)&"B"),"Encaixe"))="Agendado","Agend_OK",IF((IFERROR(IFERROR(VLOOKUP(A72,Agendamento!A:C,3,0),VLOOKUP(B72,Agendamento!B:C,2,0)&"B"),"Encaixe"))="AgendadoB","Agend_NOK",IF((IFERROR(IFERROR(VLOOKUP(A72,Agendamento!A:C,3,0),VLOOKUP(B72,Agendamento!B:C,2,0)&"B"),"Encaixe"))="Encaixe","Encaixe","Não Utilizou")))) -> Agend_NOK | K72: =IFERROR(VLOOKUP(L72,'Base Colaboradores'!C:F,4,0),"PRESTADOR DE SERVIÇOS") -> TECNOLOGIA | L72: IMAGEM ION | M72: THIAGO CACHOEIRA DE SOUZA | N72: OPER CAMERA I
A73: =IF(LEN(D73)>1,D73,E73)&F73&H73&G73 -> 79897JB x Sambodromo4606818h | B73: =IF(LEN(D73)>1,D73,E73)&F73&H73 -> 79897JB x Sambodromo46068 | C73: ISADORA NEUMANN | D73: 79897 | F73: JB x Sambodromo | G73: 18h | H73: =IF(LEFT(I73,1)="1",46068,IF(LEFT(I73,1)="2",46069,IF(LEFT(I73,1)="3",46070,46074))) -> 46068 | I73: 1 - Primeiro dia | J73: =IF(LEN(A73&B73)<2,"Não Utilizou",IF((IFERROR(IFERROR(VLOOKUP(A73,Agendamento!A:C,3,0),VLOOKUP(B73,Agendamento!B:C,2,0)&"B"),"Encaixe"))="Agendado","Agend_OK",IF((IFERROR(IFERROR(VLOOKUP(A73,Agendamento!A:C,3,0),VLOOKUP(B73,Agendamento!B:C,2,0)&"B"),"Encaixe"))="AgendadoB","Agend_NOK",IF((IFERROR(IFERROR(VLOOKUP(A73,Agendamento!A:C,3,0),VLOOKUP(B73,Agendamento!B:C,2,0)&"B"),"Encaixe"))="Encaixe","Encaixe","Não Utilizou")))) -> Agend_NOK | K73: =IFERROR(VLOOKUP(L73,'Base Colaboradores'!C:F,4,0),"PRESTADOR DE SERVIÇOS") -> JORNALISMO | L73: FANTASTICO WEB | M73: PERLA RODRIGUES AFFONSO ALVES | N73: EDITOR II
A74: =IF(LEN(D74)>1,D74,E74)&F74&H74&G74 -> 92932EG x Sambodromo4606818h | B74: =IF(LEN(D74)>1,D74,E74)&F74&H74 -> 92932EG x Sambodromo46068 | C74: IZABELA MONTEIRO | D74: 92932 | F74: EG x Sambodromo | G74: 18h | H74: =IF(LEFT(I74,1)="1",46068,IF(LEFT(I74,1)="2",46069,IF(LEFT(I74,1)="3",46070,46074))) -> 46068 | I74: 1 - Primeiro dia | J74: =IF(LEN(A74&B74)<2,"Não Utilizou",IF((IFERROR(IFERROR(VLOOKUP(A74,Agendamento!A:C,3,0),VLOOKUP(B74,Agendamento!B:C,2,0)&"B"),"Encaixe"))="Agendado","Agend_OK",IF((IFERROR(IFERROR(VLOOKUP(A74,Agendamento!A:C,3,0),VLOOKUP(B74,Agendamento!B:C,2,0)&"B"),"Encaixe"))="AgendadoB","Agend_NOK",IF((IFERROR(IFERROR(VLOOKUP(A74,Agendamento!A:C,3,0),VLOOKUP(B74,Agendamento!B:C,2,0)&"B"),"Encaixe"))="Encaixe","Encaixe","Não Utilizou")))) -> Agend_OK | K74: =IFERROR(VLOOKUP(L74,'Base Colaboradores'!C:F,4,0),"PRESTADOR DE SERVIÇOS") -> PRODUTOS DIGITAIS | L74: CULTURA POP 1 | M74: ELIANE COSTA DOS SANTOS | N74: EDITOR CONTEUDO WEB I
A75: =IF(LEN(D75)>1,D75,E75)&F75&H75&G75 -> 38164JB x Sambodromo4606818h | B75: =IF(LEN(D75)>1,D75,E75)&F75&H75 -> 38164JB x Sambodromo46068 | C75: JOAO COTTA | D75: 38164 | F75: JB x Sambodromo | G75: 18h | H75: =IF(LEFT(I75,1)="1",46068,IF(LEFT(I75,1)="2",46069,IF(LEFT(I75,1)="3",46070,46074))) -> 46068 | I75: 1 - Primeiro dia | J75: =IF(LEN(A75&B75)<2,"Não Utilizou",IF((IFERROR(IFERROR(VLOOKUP(A75,Agendamento!A:C,3,0),VLOOKUP(B75,Agendamento!B:C,2,0)&"B"),"Encaixe"))="Agendado","Agend_OK",IF((IFERROR(IFERROR(VLOOKUP(A75,Agendamento!A:C,3,0),VLOOKUP(B75,Agendamento!B:C,2,0)&"B"),"Encaixe"))="AgendadoB","Agend_NOK",IF((IFERROR(IFERROR(VLOOKUP(A75,Agendamento!A:C,3,0),VLOOKUP(B75,Agendamento!B:C,2,0)&"B"),"Encaixe"))="Encaixe","Encaixe","Não Utilizou")))) -> Agend_OK | K75: =IFERROR(VLOOKUP(L75,'Base Colaboradores'!C:F,4,0),"PRESTADOR DE SERVIÇOS") -> MARCA E COMUNICACAO | L75: SOL DE RELACIONAMENTO - CONTEUDO - ENTRETENIMENTO | M75: PAULA LORDELLO GUERREIRO ALVES | N75: ESPEC CONTEUDO
A76: =IF(LEN(D76)>1,D76,E76)&F76&H76&G76 -> 54850JB x Sambodromo4606819h | B76: =IF(LEN(D76)>1,D76,E76)&F76&H76 -> 54850JB x Sambodromo46068 | C76: JOAO GUILHERME | D76: 54850 | F76: JB x Sambodromo | G76: 19h | H76: =IF(LEFT(I76,1)="1",46068,IF(LEFT(I76,1)="2",46069,IF(LEFT(I76,1)="3",46070,46074))) -> 46068 | I76: 1 - Primeiro dia | J76: =IF(LEN(A76&B76)<2,"Não Utilizou",IF((IFERROR(IFERROR(VLOOKUP(A76,Agendamento!A:C,3,0),VLOOKUP(B76,Agendamento!B:C,2,0)&"B"),"Encaixe"))="Agendado","Agend_OK",IF((IFERROR(IFERROR(VLOOKUP(A76,Agendamento!A:C,3,0),VLOOKUP(B76,Agendamento!B:C,2,0)&"B"),"Encaixe"))="AgendadoB","Agend_NOK",IF((IFERROR(IFERROR(VLOOKUP(A76,Agendamento!A:C,3,0),VLOOKUP(B76,Agendamento!B:C,2,0)&"B"),"Encaixe"))="Encaixe","Encaixe","Não Utilizou")))) -> Agend_OK | K76: =IFERROR(VLOOKUP(L76,'Base Colaboradores'!C:F,4,0),"PRESTADOR DE SERVIÇOS") -> TECNOLOGIA | L76: IMAGEM JB | M76: JEAN CARLO GOULART ALVES | N76: OPER CAMERA I
A77: =IF(LEN(D77)>1,D77,E77)&F77&H77&G77 -> 12491135710EG x Sambodromo4606817h | B77: =IF(LEN(D77)>1,D77,E77)&F77&H77 -> 12491135710EG x Sambodromo46068 | C77: JOAO MENEZES | E77: 12491135710 | F77: EG x Sambodromo | G77: 17h | H77: =IF(LEFT(I77,1)="1",46068,IF(LEFT(I77,1)="2",46069,IF(LEFT(I77,1)="3",46070,46074))) -> 46068 | I77: 1 - Primeiro dia | J77: =IF(LEN(A77&B77)<2,"Não Utilizou",IF((IFERROR(IFERROR(VLOOKUP(A77,Agendamento!A:C,3,0),VLOOKUP(B77,Agendamento!B:C,2,0)&"B"),"Encaixe"))="Agendado","Agend_OK",IF((IFERROR(IFERROR(VLOOKUP(A77,Agendamento!A:C,3,0),VLOOKUP(B77,Agendamento!B:C,2,0)&"B"),"Encaixe"))="AgendadoB","Agend_NOK",IF((IFERROR(IFERROR(VLOOKUP(A77,Agendamento!A:C,3,0),VLOOKUP(B77,Agendamento!B:C,2,0)&"B"),"Encaixe"))="Encaixe","Encaixe","Não Utilizou")))) -> Agend_OK | K77: =IFERROR(VLOOKUP(L77,'Base Colaboradores'!C:F,4,0),"PRESTADOR DE SERVIÇOS") -> PRESTADOR DE SERVIÇOS | L77: Top Service | M77: Prestador | N77: Prestador
A78: =IF(LEN(D78)>1,D78,E78)&F78&H78&G78 -> 12158421711JB x Sambodromo4606819h | B78: =IF(LEN(D78)>1,D78,E78)&F78&H78 -> 12158421711JB x Sambodromo46068 | C78: JULIA CARVALHO | E78: 12158421711 | F78: JB x Sambodromo | G78: 19h | H78: =IF(LEFT(I78,1)="1",46068,IF(LEFT(I78,1)="2",46069,IF(LEFT(I78,1)="3",46070,46074))) -> 46068 | I78: 1 - Primeiro dia | J78: =IF(LEN(A78&B78)<2,"Não Utilizou",IF((IFERROR(IFERROR(VLOOKUP(A78,Agendamento!A:C,3,0),VLOOKUP(B78,Agendamento!B:C,2,0)&"B"),"Encaixe"))="Agendado","Agend_OK",IF((IFERROR(IFERROR(VLOOKUP(A78,Agendamento!A:C,3,0),VLOOKUP(B78,Agendamento!B:C,2,0)&"B"),"Encaixe"))="AgendadoB","Agend_NOK",IF((IFERROR(IFERROR(VLOOKUP(A78,Agendamento!A:C,3,0),VLOOKUP(B78,Agendamento!B:C,2,0)&"B"),"Encaixe"))="Encaixe","Encaixe","Não Utilizou")))) -> Encaixe | K78: =IFERROR(VLOOKUP(L78,'Base Colaboradores'!C:F,4,0),"PRESTADOR DE SERVIÇOS") -> PRESTADOR DE SERVIÇOS | L78: Prestador | M78: Prestador | N78: Prestador
A79: =IF(LEN(D79)>1,D79,E79)&F79&H79&G79 -> 79650EG x Sambodromo4606817h | B79: =IF(LEN(D79)>1,D79,E79)&F79&H79 -> 79650EG x Sambodromo46068 | C79: JULIA PAULA | D79: 79650 | F79: EG x Sambodromo | G79: 17h | H79: =IF(LEFT(I79,1)="1",46068,IF(LEFT(I79,1)="2",46069,IF(LEFT(I79,1)="3",46070,46074))) -> 46068 | I79: 1 - Primeiro dia | J79: =IF(LEN(A79&B79)<2,"Não Utilizou",IF((IFERROR(IFERROR(VLOOKUP(A79,Agendamento!A:C,3,0),VLOOKUP(B79,Agendamento!B:C,2,0)&"B"),"Encaixe"))="Agendado","Agend_OK",IF((IFERROR(IFERROR(VLOOKUP(A79,Agendamento!A:C,3,0),VLOOKUP(B79,Agendamento!B:C,2,0)&"B"),"Encaixe"))="AgendadoB","Agend_NOK",IF((IFERROR(IFERROR(VLOOKUP(A79,Agendamento!A:C,3,0),VLOOKUP(B79,Agendamento!B:C,2,0)&"B"),"Encaixe"))="Encaixe","Encaixe","Não Utilizou")))) -> Encaixe | K79: =IFERROR(VLOOKUP(L79,'Base Colaboradores'!C:F,4,0),"PRESTADOR DE SERVIÇOS") -> TECNOLOGIA | L79: TECNOLOGIA PARA SHOWS E EVENTOS | M79: RODRIGO OTAVIO RODRIGUES ROSA | N79: PRODUTOR TECNOLOGIA III
A80: =IF(LEN(D80)>1,D80,E80)&F80&H80&G80 -> 82093EG x Sambodromo4606820h | B80: =IF(LEN(D80)>1,D80,E80)&F80&H80 -> 82093EG x Sambodromo46068 | C80: JULIANA GONÇALVES | D80: 82093 | F80: EG x Sambodromo | G80: 20h | H80: =IF(LEFT(I80,1)="1",46068,IF(LEFT(I80,1)="2",46069,IF(LEFT(I80,1)="3",46070,46074))) -> 46068 | I80: 1 - Primeiro dia | J80: =IF(LEN(A80&B80)<2,"Não Utilizou",IF((IFERROR(IFERROR(VLOOKUP(A80,Agendamento!A:C,3,0),VLOOKUP(B80,Agendamento!B:C,2,0)&"B"),"Encaixe"))="Agendado","Agend_OK",IF((IFERROR(IFERROR(VLOOKUP(A80,Agendamento!A:C,3,0),VLOOKUP(B80,Agendamento!B:C,2,0)&"B"),"Encaixe"))="AgendadoB","Agend_NOK",IF((IFERROR(IFERROR(VLOOKUP(A80,Agendamento!A:C,3,0),VLOOKUP(B80,Agendamento!B:C,2,0)&"B"),"Encaixe"))="Encaixe","Encaixe","Não Utilizou")))) -> Agend_NOK | K80: =IFERROR(VLOOKUP(L80,'Base Colaboradores'!C:F,4,0),"PRESTADOR DE SERVIÇOS") -> FINANCAS JURIDICO E INFRAESTRUTURA | L80: TRANSPORTES RJ | M80: FABIO PAIXAO DOS SANTOS | N80: LIDER SERVICOS E LOGISTICA
A81: =IF(LEN(D81)>1,D81,E81)&F81&H81&G81 -> 52789EG x Sambodromo4606817h | B81: =IF(LEN(D81)>1,D81,E81)&F81&H81 -> 52789EG x Sambodromo46068 | C81: JULIANA PINNA | D81: 52789 | F81: EG x Sambodromo | G81: 17h | H81: =IF(LEFT(I81,1)="1",46068,IF(LEFT(I81,1)="2",46069,IF(LEFT(I81,1)="3",46070,46074))) -> 46068 | I81: 1 - Primeiro dia | J81: =IF(LEN(A81&B81)<2,"Não Utilizou",IF((IFERROR(IFERROR(VLOOKUP(A81,Agendamento!A:C,3,0),VLOOKUP(B81,Agendamento!B:C,2,0)&"B"),"Encaixe"))="Agendado","Agend_OK",IF((IFERROR(IFERROR(VLOOKUP(A81,Agendamento!A:C,3,0),VLOOKUP(B81,Agendamento!B:C,2,0)&"B"),"Encaixe"))="AgendadoB","Agend_NOK",IF((IFERROR(IFERROR(VLOOKUP(A81,Agendamento!A:C,3,0),VLOOKUP(B81,Agendamento!B:C,2,0)&"B"),"Encaixe"))="Encaixe","Encaixe","Não Utilizou")))) -> Agend_OK | K81: =IFERROR(VLOOKUP(L81,'Base Colaboradores'!C:F,4,0),"PRESTADOR DE SERVIÇOS") -> PRODUTOS DIGITAIS | L81: PRODUCAO EM VIDEO 2 | M81: MARIANO EMILIO DELLASOPPA | N81: PRODUTOR VIDEO II
A82: =IF(LEN(D82)>1,D82,E82)&F82&H82&G82 -> 87450JB x Sambodromo4606818h | B82: =IF(LEN(D82)>1,D82,E82)&F82&H82 -> 87450JB x Sambodromo46068 | C82: JURANDIR FERREIRA | D82: 87450 | F82: JB x Sambodromo | G82: 18h | H82: =IF(LEFT(I82,1)="1",46068,IF(LEFT(I82,1)="2",46069,IF(LEFT(I82,1)="3",46070,46074))) -> 46068 | I82: 1 - Primeiro dia | J82: =IF(LEN(A82&B82)<2,"Não Utilizou",IF((IFERROR(IFERROR(VLOOKUP(A82,Agendamento!A:C,3,0),VLOOKUP(B82,Agendamento!B:C,2,0)&"B"),"Encaixe"))="Agendado","Agend_OK",IF((IFERROR(IFERROR(VLOOKUP(A82,Agendamento!A:C,3,0),VLOOKUP(B82,Agendamento!B:C,2,0)&"B"),"Encaixe"))="AgendadoB","Agend_NOK",IF((IFERROR(IFERROR(VLOOKUP(A82,Agendamento!A:C,3,0),VLOOKUP(B82,Agendamento!B:C,2,0)&"B"),"Encaixe"))="Encaixe","Encaixe","Não Utilizou")))) -> Encaixe | K82: =IFERROR(VLOOKUP(L82,'Base Colaboradores'!C:F,4,0),"PRESTADOR DE SERVIÇOS") -> JORNALISMO | L82: SUPERVISAO IMAGEM RJ | M82: EDUARDO ALBERTO FERNANDEZ | N82: REPORTER CINEMATOGRAFICO II
A83: =IF(LEN(D83)>1,D83,E83)&F83&H83&G83 -> 86335EG x Sambodromo4606820h | B83: =IF(LEN(D83)>1,D83,E83)&F83&H83 -> 86335EG x Sambodromo46068 | C83: KAIO LINO | D83: 86335 | F83: EG x Sambodromo | G83: 20h | H83: =IF(LEFT(I83,1)="1",46068,IF(LEFT(I83,1)="2",46069,IF(LEFT(I83,1)="3",46070,46074))) -> 46068 | I83: 1 - Primeiro dia | J83: =IF(LEN(A83&B83)<2,"Não Utilizou",IF((IFERROR(IFERROR(VLOOKUP(A83,Agendamento!A:C,3,0),VLOOKUP(B83,Agendamento!B:C,2,0)&"B"),"Encaixe"))="Agendado","Agend_OK",IF((IFERROR(IFERROR(VLOOKUP(A83,Agendamento!A:C,3,0),VLOOKUP(B83,Agendamento!B:C,2,0)&"B"),"Encaixe"))="AgendadoB","Agend_NOK",IF((IFERROR(IFERROR(VLOOKUP(A83,Agendamento!A:C,3,0),VLOOKUP(B83,Agendamento!B:C,2,0)&"B"),"Encaixe"))="Encaixe","Encaixe","Não Utilizou")))) -> Encaixe | K83: =IFERROR(VLOOKUP(L83,'Base Colaboradores'!C:F,4,0),"PRESTADOR DE SERVIÇOS") -> TECNOLOGIA | L83: SUPORTE PRODUCAO PRODUTOS E PLATAFORMAS RJ | M83: CAIO VINICIUS SCRIBONI | N83: ANL TELECOM I
A84: =IF(LEN(D84)>1,D84,E84)&F84&H84&G84 -> 83922EG x Sambodromo4606817h | B84: =IF(LEN(D84)>1,D84,E84)&F84&H84 -> 83922EG x Sambodromo46068 | C84: KARINA VERIDIANO | D84: 83922 | F84: EG x Sambodromo | G84: 17h | H84: =IF(LEFT(I84,1)="1",46068,IF(LEFT(I84,1)="2",46069,IF(LEFT(I84,1)="3",46070,46074))) -> 46068 | I84: 1 - Primeiro dia | J84: =IF(LEN(A84&B84)<2,"Não Utilizou",IF((IFERROR(IFERROR(VLOOKUP(A84,Agendamento!A:C,3,0),VLOOKUP(B84,Agendamento!B:C,2,0)&"B"),"Encaixe"))="Agendado","Agend_OK",IF((IFERROR(IFERROR(VLOOKUP(A84,Agendamento!A:C,3,0),VLOOKUP(B84,Agendamento!B:C,2,0)&"B"),"Encaixe"))="AgendadoB","Agend_NOK",IF((IFERROR(IFERROR(VLOOKUP(A84,Agendamento!A:C,3,0),VLOOKUP(B84,Agendamento!B:C,2,0)&"B"),"Encaixe"))="Encaixe","Encaixe","Não Utilizou")))) -> Agend_OK | K84: =IFERROR(VLOOKUP(L84,'Base Colaboradores'!C:F,4,0),"PRESTADOR DE SERVIÇOS") -> FINANCAS JURIDICO E INFRAESTRUTURA | L84: INTELIGENCIA SEGURANCA EMPRESARIAL | M84: RONILDO DOS SANTOS ROSENDO | N84: ANL SEGURANCA EMPRESARIAL I
A85: =IF(LEN(D85)>1,D85,E85)&F85&H85&G85 -> 77746JB x Sambodromo4606821h | B85: =IF(LEN(D85)>1,D85,E85)&F85&H85 -> 77746JB x Sambodromo46068 | C85: KLEYTON CINTRA | D85: 77746 | F85: JB x Sambodromo | G85: 21h | H85: =IF(LEFT(I85,1)="1",46068,IF(LEFT(I85,1)="2",46069,IF(LEFT(I85,1)="3",46070,46074))) -> 46068 | I85: 1 - Primeiro dia | J85: =IF(LEN(A85&B85)<2,"Não Utilizou",IF((IFERROR(IFERROR(VLOOKUP(A85,Agendamento!A:C,3,0),VLOOKUP(B85,Agendamento!B:C,2,0)&"B"),"Encaixe"))="Agendado","Agend_OK",IF((IFERROR(IFERROR(VLOOKUP(A85,Agendamento!A:C,3,0),VLOOKUP(B85,Agendamento!B:C,2,0)&"B"),"Encaixe"))="AgendadoB","Agend_NOK",IF((IFERROR(IFERROR(VLOOKUP(A85,Agendamento!A:C,3,0),VLOOKUP(B85,Agendamento!B:C,2,0)&"B"),"Encaixe"))="Encaixe","Encaixe","Não Utilizou")))) -> Encaixe | K85: =IFERROR(VLOOKUP(L85,'Base Colaboradores'!C:F,4,0),"PRESTADOR DE SERVIÇOS") -> JORNALISMO | L85: SUPERVISAO IMAGEM RJ | M85: EDUARDO ALBERTO FERNANDEZ | N85: REPORTER CINEMATOGRAFICO III
A86: =IF(LEN(D86)>1,D86,E86)&F86&H86&G86 -> 56200JB x Sambodromo4606819h | B86: =IF(LEN(D86)>1,D86,E86)&F86&H86 -> 56200JB x Sambodromo46068 | C86: LARISSA SCHMIDT | D86: 56200 | F86: JB x Sambodromo | G86: 19h | H86: =IF(LEFT(I86,1)="1",46068,IF(LEFT(I86,1)="2",46069,IF(LEFT(I86,1)="3",46070,46074))) -> 46068 | I86: 1 - Primeiro dia | J86: =IF(LEN(A86&B86)<2,"Não Utilizou",IF((IFERROR(IFERROR(VLOOKUP(A86,Agendamento!A:C,3,0),VLOOKUP(B86,Agendamento!B:C,2,0)&"B"),"Encaixe"))="Agendado","Agend_OK",IF((IFERROR(IFERROR(VLOOKUP(A86,Agendamento!A:C,3,0),VLOOKUP(B86,Agendamento!B:C,2,0)&"B"),"Encaixe"))="AgendadoB","Agend_NOK",IF((IFERROR(IFERROR(VLOOKUP(A86,Agendamento!A:C,3,0),VLOOKUP(B86,Agendamento!B:C,2,0)&"B"),"Encaixe"))="Encaixe","Encaixe","Não Utilizou")))) -> Encaixe | K86: =IFERROR(VLOOKUP(L86,'Base Colaboradores'!C:F,4,0),"PRESTADOR DE SERVIÇOS") -> JORNALISMO | L86: SUPERVISAO EDITORIA RJ | M86: PATRICIA DE ANDRADE PINTO | N86: REPORTER III
A87: =IF(LEN(D87)>1,D87,E87)&F87&H87&G87 -> 92578EG x Sambodromo4606818h | B87: =IF(LEN(D87)>1,D87,E87)&F87&H87 -> 92578EG x Sambodromo46068 | C87: LEANDRO SALLES | D87: 92578 | F87: EG x Sambodromo | G87: 18h | H87: =IF(LEFT(I87,1)="1",46068,IF(LEFT(I87,1)="2",46069,IF(LEFT(I87,1)="3",46070,46074))) -> 46068 | I87: 1 - Primeiro dia | J87: =IF(LEN(A87&B87)<2,"Não Utilizou",IF((IFERROR(IFERROR(VLOOKUP(A87,Agendamento!A:C,3,0),VLOOKUP(B87,Agendamento!B:C,2,0)&"B"),"Encaixe"))="Agendado","Agend_OK",IF((IFERROR(IFERROR(VLOOKUP(A87,Agendamento!A:C,3,0),VLOOKUP(B87,Agendamento!B:C,2,0)&"B"),"Encaixe"))="AgendadoB","Agend_NOK",IF((IFERROR(IFERROR(VLOOKUP(A87,Agendamento!A:C,3,0),VLOOKUP(B87,Agendamento!B:C,2,0)&"B"),"Encaixe"))="Encaixe","Encaixe","Não Utilizou")))) -> Encaixe | K87: =IFERROR(VLOOKUP(L87,'Base Colaboradores'!C:F,4,0),"PRESTADOR DE SERVIÇOS") -> FINANCAS JURIDICO E INFRAESTRUTURA | L87: TRANSPORTES RJ | M87: FABIO PAIXAO DOS SANTOS | N87: MOTORISTA CARRETEIRO
A88: =IF(LEN(D88)>1,D88,E88)&F88&H88&G88 -> 09058655709EG x Sambodromo4606821h | B88: =IF(LEN(D88)>1,D88,E88)&F88&H88 -> 09058655709EG x Sambodromo46068 | C88: LEONARDO DA COSTA | E88: 09058655709 | F88: EG x Sambodromo | G88: 21h | H88: =IF(LEFT(I88,1)="1",46068,IF(LEFT(I88,1)="2",46069,IF(LEFT(I88,1)="3",46070,46074))) -> 46068 | I88: 1 - Primeiro dia | J88: =IF(LEN(A88&B88)<2,"Não Utilizou",IF((IFERROR(IFERROR(VLOOKUP(A88,Agendamento!A:C,3,0),VLOOKUP(B88,Agendamento!B:C,2,0)&"B"),"Encaixe"))="Agendado","Agend_OK",IF((IFERROR(IFERROR(VLOOKUP(A88,Agendamento!A:C,3,0),VLOOKUP(B88,Agendamento!B:C,2,0)&"B"),"Encaixe"))="AgendadoB","Agend_NOK",IF((IFERROR(IFERROR(VLOOKUP(A88,Agendamento!A:C,3,0),VLOOKUP(B88,Agendamento!B:C,2,0)&"B"),"Encaixe"))="Encaixe","Encaixe","Não Utilizou")))) -> Encaixe | K88: =IFERROR(VLOOKUP(L88,'Base Colaboradores'!C:F,4,0),"PRESTADOR DE SERVIÇOS") -> PRESTADOR DE SERVIÇOS | L88: Prestador | M88: Prestador | N88: Prestador
A89: =IF(LEN(D89)>1,D89,E89)&F89&H89&G89 -> 10818221769JB x Sambodromo4606818h | B89: =IF(LEN(D89)>1,D89,E89)&F89&H89 -> 10818221769JB x Sambodromo46068 | C89: LEONARDO NASCIMENTO | E89: 10818221769 | F89: JB x Sambodromo | G89: 18h | H89: =IF(LEFT(I89,1)="1",46068,IF(LEFT(I89,1)="2",46069,IF(LEFT(I89,1)="3",46070,46074))) -> 46068 | I89: 1 - Primeiro dia | J89: =IF(LEN(A89&B89)<2,"Não Utilizou",IF((IFERROR(IFERROR(VLOOKUP(A89,Agendamento!A:C,3,0),VLOOKUP(B89,Agendamento!B:C,2,0)&"B"),"Encaixe"))="Agendado","Agend_OK",IF((IFERROR(IFERROR(VLOOKUP(A89,Agendamento!A:C,3,0),VLOOKUP(B89,Agendamento!B:C,2,0)&"B"),"Encaixe"))="AgendadoB","Agend_NOK",IF((IFERROR(IFERROR(VLOOKUP(A89,Agendamento!A:C,3,0),VLOOKUP(B89,Agendamento!B:C,2,0)&"B"),"Encaixe"))="Encaixe","Encaixe","Não Utilizou")))) -> Encaixe | K89: =IFERROR(VLOOKUP(L89,'Base Colaboradores'!C:F,4,0),"PRESTADOR DE SERVIÇOS") -> PRESTADOR DE SERVIÇOS | L89: Prestador | M89: Prestador | N89: Prestador
A90: =IF(LEN(D90)>1,D90,E90)&F90&H90&G90 -> 77822JB x Sambodromo4606821h | B90: =IF(LEN(D90)>1,D90,E90)&F90&H90 -> 77822JB x Sambodromo46068 | C90: LUCAS CEREJO | D90: 77822 | F90: JB x Sambodromo | G90: 21h | H90: =IF(LEFT(I90,1)="1",46068,IF(LEFT(I90,1)="2",46069,IF(LEFT(I90,1)="3",46070,46074))) -> 46068 | I90: 1 - Primeiro dia | J90: =IF(LEN(A90&B90)<2,"Não Utilizou",IF((IFERROR(IFERROR(VLOOKUP(A90,Agendamento!A:C,3,0),VLOOKUP(B90,Agendamento!B:C,2,0)&"B"),"Encaixe"))="Agendado","Agend_OK",IF((IFERROR(IFERROR(VLOOKUP(A90,Agendamento!A:C,3,0),VLOOKUP(B90,Agendamento!B:C,2,0)&"B"),"Encaixe"))="AgendadoB","Agend_NOK",IF((IFERROR(IFERROR(VLOOKUP(A90,Agendamento!A:C,3,0),VLOOKUP(B90,Agendamento!B:C,2,0)&"B"),"Encaixe"))="Encaixe","Encaixe","Não Utilizou")))) -> Encaixe | K90: =IFERROR(VLOOKUP(L90,'Base Colaboradores'!C:F,4,0),"PRESTADOR DE SERVIÇOS") -> JORNALISMO | L90: SUPERVISAO IMAGEM RJ | M90: EDUARDO ALBERTO FERNANDEZ | N90: REPORTER CINEMATOGRAFICO III
A91: =IF(LEN(D91)>1,D91,E91)&F91&H91&G91 -> 17922076703EG x Sambodromo4606817h | B91: =IF(LEN(D91)>1,D91,E91)&F91&H91 -> 17922076703EG x Sambodromo46068 | C91: LUCAS COUTINHO | E91: 17922076703 | F91: EG x Sambodromo | G91: 17h | H91: =IF(LEFT(I91,1)="1",46068,IF(LEFT(I91,1)="2",46069,IF(LEFT(I91,1)="3",46070,46074))) -> 46068 | I91: 1 - Primeiro dia | J91: =IF(LEN(A91&B91)<2,"Não Utilizou",IF((IFERROR(IFERROR(VLOOKUP(A91,Agendamento!A:C,3,0),VLOOKUP(B91,Agendamento!B:C,2,0)&"B"),"Encaixe"))="Agendado","Agend_OK",IF((IFERROR(IFERROR(VLOOKUP(A91,Agendamento!A:C,3,0),VLOOKUP(B91,Agendamento!B:C,2,0)&"B"),"Encaixe"))="AgendadoB","Agend_NOK",IF((IFERROR(IFERROR(VLOOKUP(A91,Agendamento!A:C,3,0),VLOOKUP(B91,Agendamento!B:C,2,0)&"B"),"Encaixe"))="Encaixe","Encaixe","Não Utilizou")))) -> Agend_OK | K91: =IFERROR(VLOOKUP(L91,'Base Colaboradores'!C:F,4,0),"PRESTADOR DE SERVIÇOS") -> PRESTADOR DE SERVIÇOS | L91: Top Service | M91: Prestador | N91: Prestador
A92: =IF(LEN(D92)>1,D92,E92)&F92&H92&G92 -> 50598EG x Sambodromo4606822h | B92: =IF(LEN(D92)>1,D92,E92)&F92&H92 -> 50598EG x Sambodromo46068 | C92: LUCIANA GONÇALVES | D92: 50598 | F92: EG x Sambodromo | G92: 22h | H92: =IF(LEFT(I92,1)="1",46068,IF(LEFT(I92,1)="2",46069,IF(LEFT(I92,1)="3",46070,46074))) -> 46068 | I92: 1 - Primeiro dia | J92: =IF(LEN(A92&B92)<2,"Não Utilizou",IF((IFERROR(IFERROR(VLOOKUP(A92,Agendamento!A:C,3,0),VLOOKUP(B92,Agendamento!B:C,2,0)&"B"),"Encaixe"))="Agendado","Agend_OK",IF((IFERROR(IFERROR(VLOOKUP(A92,Agendamento!A:C,3,0),VLOOKUP(B92,Agendamento!B:C,2,0)&"B"),"Encaixe"))="AgendadoB","Agend_NOK",IF((IFERROR(IFERROR(VLOOKUP(A92,Agendamento!A:C,3,0),VLOOKUP(B92,Agendamento!B:C,2,0)&"B"),"Encaixe"))="Encaixe","Encaixe","Não Utilizou")))) -> Encaixe | K92: =IFERROR(VLOOKUP(L92,'Base Colaboradores'!C:F,4,0),"PRESTADOR DE SERVIÇOS") -> ESTUDIOS GLOBO | L92: FIGURINO ASSISTENTES | M92: ELISA MUNIZ COIFMAN | N92: FIGURINISTA ASSISTENTE II
A93: =IF(LEN(D93)>1,D93,E93)&F93&H93&G93 -> 11885547781EG x Sambodromo4606817h | B93: =IF(LEN(D93)>1,D93,E93)&F93&H93 -> 11885547781EG x Sambodromo46068 | C93: LUCIANA PEREIRA | E93: 11885547781 | F93: EG x Sambodromo | G93: 17h | H93: =IF(LEFT(I93,1)="1",46068,IF(LEFT(I93,1)="2",46069,IF(LEFT(I93,1)="3",46070,46074))) -> 46068 | I93: 1 - Primeiro dia | J93: =IF(LEN(A93&B93)<2,"Não Utilizou",IF((IFERROR(IFERROR(VLOOKUP(A93,Agendamento!A:C,3,0),VLOOKUP(B93,Agendamento!B:C,2,0)&"B"),"Encaixe"))="Agendado","Agend_OK",IF((IFERROR(IFERROR(VLOOKUP(A93,Agendamento!A:C,3,0),VLOOKUP(B93,Agendamento!B:C,2,0)&"B"),"Encaixe"))="AgendadoB","Agend_NOK",IF((IFERROR(IFERROR(VLOOKUP(A93,Agendamento!A:C,3,0),VLOOKUP(B93,Agendamento!B:C,2,0)&"B"),"Encaixe"))="Encaixe","Encaixe","Não Utilizou")))) -> Agend_OK | K93: =IFERROR(VLOOKUP(L93,'Base Colaboradores'!C:F,4,0),"PRESTADOR DE SERVIÇOS") -> PRESTADOR DE SERVIÇOS | L93: Top Service | M93: Prestador | N93: Prestador
A94: =IF(LEN(D94)>1,D94,E94)&F94&H94&G94 -> 03607749469EG x Sambodromo4606818h | B94: =IF(LEN(D94)>1,D94,E94)&F94&H94 -> 03607749469EG x Sambodromo46068 | C94: LUCIMAR DE OLIVEIRA | E94: 03607749469 | F94: EG x Sambodromo | G94: 18h | H94: =IF(LEFT(I94,1)="1",46068,IF(LEFT(I94,1)="2",46069,IF(LEFT(I94,1)="3",46070,46074))) -> 46068 | I94: 1 - Primeiro dia | J94: =IF(LEN(A94&B94)<2,"Não Utilizou",IF((IFERROR(IFERROR(VLOOKUP(A94,Agendamento!A:C,3,0),VLOOKUP(B94,Agendamento!B:C,2,0)&"B"),"Encaixe"))="Agendado","Agend_OK",IF((IFERROR(IFERROR(VLOOKUP(A94,Agendamento!A:C,3,0),VLOOKUP(B94,Agendamento!B:C,2,0)&"B"),"Encaixe"))="AgendadoB","Agend_NOK",IF((IFERROR(IFERROR(VLOOKUP(A94,Agendamento!A:C,3,0),VLOOKUP(B94,Agendamento!B:C,2,0)&"B"),"Encaixe"))="Encaixe","Encaixe","Não Utilizou")))) -> Agend_OK | K94: =IFERROR(VLOOKUP(L94,'Base Colaboradores'!C:F,4,0),"PRESTADOR DE SERVIÇOS") -> PRESTADOR DE SERVIÇOS | L94: Top Service | M94: Prestador | N94: Prestador
A95: =IF(LEN(D95)>1,D95,E95)&F95&H95&G95 -> 72174JB x Sambodromo4606819h | B95: =IF(LEN(D95)>1,D95,E95)&F95&H95 -> 72174JB x Sambodromo46068 | C95: LUISA AGRA | D95: 72174 | F95: JB x Sambodromo | G95: 19h | H95: =IF(LEFT(I95,1)="1",46068,IF(LEFT(I95,1)="2",46069,IF(LEFT(I95,1)="3",46070,46074))) -> 46068 | I95: 1 - Primeiro dia | J95: =IF(LEN(A95&B95)<2,"Não Utilizou",IF((IFERROR(IFERROR(VLOOKUP(A95,Agendamento!A:C,3,0),VLOOKUP(B95,Agendamento!B:C,2,0)&"B"),"Encaixe"))="Agendado","Agend_OK",IF((IFERROR(IFERROR(VLOOKUP(A95,Agendamento!A:C,3,0),VLOOKUP(B95,Agendamento!B:C,2,0)&"B"),"Encaixe"))="AgendadoB","Agend_NOK",IF((IFERROR(IFERROR(VLOOKUP(A95,Agendamento!A:C,3,0),VLOOKUP(B95,Agendamento!B:C,2,0)&"B"),"Encaixe"))="Encaixe","Encaixe","Não Utilizou")))) -> Agend_OK | K95: =IFERROR(VLOOKUP(L95,'Base Colaboradores'!C:F,4,0),"PRESTADOR DE SERVIÇOS") -> PRODUTOS DIGITAIS | L95: REDES SOCIAIS GSHOW E RECEITAS | M95: FELIPE GOMES DE LIMA | N95: ANL CONTEUDO I
A96: =IF(LEN(D96)>1,D96,E96)&F96&H96&G96 -> 30651JB x Sambodromo4606818h | B96: =IF(LEN(D96)>1,D96,E96)&F96&H96 -> 30651JB x Sambodromo46068 | C96: LUIZ ANTONIO VALE | D96: 30651 | F96: JB x Sambodromo | G96: 18h | H96: =IF(LEFT(I96,1)="1",46068,IF(LEFT(I96,1)="2",46069,IF(LEFT(I96,1)="3",46070,46074))) -> 46068 | I96: 1 - Primeiro dia | J96: =IF(LEN(A96&B96)<2,"Não Utilizou",IF((IFERROR(IFERROR(VLOOKUP(A96,Agendamento!A:C,3,0),VLOOKUP(B96,Agendamento!B:C,2,0)&"B"),"Encaixe"))="Agendado","Agend_OK",IF((IFERROR(IFERROR(VLOOKUP(A96,Agendamento!A:C,3,0),VLOOKUP(B96,Agendamento!B:C,2,0)&"B"),"Encaixe"))="AgendadoB","Agend_NOK",IF((IFERROR(IFERROR(VLOOKUP(A96,Agendamento!A:C,3,0),VLOOKUP(B96,Agendamento!B:C,2,0)&"B"),"Encaixe"))="Encaixe","Encaixe","Não Utilizou")))) -> Agend_OK | K96: =IFERROR(VLOOKUP(L96,'Base Colaboradores'!C:F,4,0),"PRESTADOR DE SERVIÇOS") -> JORNALISMO | L96: SUPERVISAO EDITORIA RJ 03 04 | M96: FABRICIO PRADO MARTA | N96: PRODUTOR LIDER
A97: =IF(LEN(D97)>1,D97,E97)&F97&H97&G97 -> 89417EG x Sambodromo4606819h | B97: =IF(LEN(D97)>1,D97,E97)&F97&H97 -> 89417EG x Sambodromo46068 | C97: LUIZ CARLOS NUNES | D97: 89417 | F97: EG x Sambodromo | G97: 19h | H97: =IF(LEFT(I97,1)="1",46068,IF(LEFT(I97,1)="2",46069,IF(LEFT(I97,1)="3",46070,46074))) -> 46068 | I97: 1 - Primeiro dia | J97: =IF(LEN(A97&B97)<2,"Não Utilizou",IF((IFERROR(IFERROR(VLOOKUP(A97,Agendamento!A:C,3,0),VLOOKUP(B97,Agendamento!B:C,2,0)&"B"),"Encaixe"))="Agendado","Agend_OK",IF((IFERROR(IFERROR(VLOOKUP(A97,Agendamento!A:C,3,0),VLOOKUP(B97,Agendamento!B:C,2,0)&"B"),"Encaixe"))="AgendadoB","Agend_NOK",IF((IFERROR(IFERROR(VLOOKUP(A97,Agendamento!A:C,3,0),VLOOKUP(B97,Agendamento!B:C,2,0)&"B"),"Encaixe"))="Encaixe","Encaixe","Não Utilizou")))) -> Encaixe | K97: =IFERROR(VLOOKUP(L97,'Base Colaboradores'!C:F,4,0),"PRESTADOR DE SERVIÇOS") -> FINANCAS JURIDICO E INFRAESTRUTURA | L97: TRANSPORTES RJ | M97: FABIO PAIXAO DOS SANTOS | N97: MOTORISTA CARRETEIRO
A98: =IF(LEN(D98)>1,D98,E98)&F98&H98&G98 -> 86767JB x Sambodromo4606818h | B98: =IF(LEN(D98)>1,D98,E98)&F98&H98 -> 86767JB x Sambodromo46068 | C98: MARCELO ANTHONY | D98: 86767 | F98: JB x Sambodromo | G98: 18h | H98: =IF(LEFT(I98,1)="1",46068,IF(LEFT(I98,1)="2",46069,IF(LEFT(I98,1)="3",46070,46074))) -> 46068 | I98: 1 - Primeiro dia | J98: =IF(LEN(A98&B98)<2,"Não Utilizou",IF((IFERROR(IFERROR(VLOOKUP(A98,Agendamento!A:C,3,0),VLOOKUP(B98,Agendamento!B:C,2,0)&"B"),"Encaixe"))="Agendado","Agend_OK",IF((IFERROR(IFERROR(VLOOKUP(A98,Agendamento!A:C,3,0),VLOOKUP(B98,Agendamento!B:C,2,0)&"B"),"Encaixe"))="AgendadoB","Agend_NOK",IF((IFERROR(IFERROR(VLOOKUP(A98,Agendamento!A:C,3,0),VLOOKUP(B98,Agendamento!B:C,2,0)&"B"),"Encaixe"))="Encaixe","Encaixe","Não Utilizou")))) -> Encaixe | K98: =IFERROR(VLOOKUP(L98,'Base Colaboradores'!C:F,4,0),"PRESTADOR DE SERVIÇOS") -> TECNOLOGIA | L98: COT E EXTERNA JB | M98: BEATHRIZ VERAS DE LIMA LOPES | N98: TEC SISTEMAS AUDIOVISUAIS II
A99: =IF(LEN(D99)>1,D99,E99)&F99&H99&G99 -> 90220EG x Sambodromo4606819h | B99: =IF(LEN(D99)>1,D99,E99)&F99&H99 -> 90220EG x Sambodromo46068 | C99: MARCIO GOMES | D99: 90220 | F99: EG x Sambodromo | G99: 19h | H99: =IF(LEFT(I99,1)="1",46068,IF(LEFT(I99,1)="2",46069,IF(LEFT(I99,1)="3",46070,46074))) -> 46068 | I99: 1 - Primeiro dia | J99: =IF(LEN(A99&B99)<2,"Não Utilizou",IF((IFERROR(IFERROR(VLOOKUP(A99,Agendamento!A:C,3,0),VLOOKUP(B99,Agendamento!B:C,2,0)&"B"),"Encaixe"))="Agendado","Agend_OK",IF((IFERROR(IFERROR(VLOOKUP(A99,Agendamento!A:C,3,0),VLOOKUP(B99,Agendamento!B:C,2,0)&"B"),"Encaixe"))="AgendadoB","Agend_NOK",IF((IFERROR(IFERROR(VLOOKUP(A99,Agendamento!A:C,3,0),VLOOKUP(B99,Agendamento!B:C,2,0)&"B"),"Encaixe"))="Encaixe","Encaixe","Não Utilizou")))) -> Agend_OK | K99: =IFERROR(VLOOKUP(L99,'Base Colaboradores'!C:F,4,0),"PRESTADOR DE SERVIÇOS") -> PRODUTOS DIGITAIS | L99: CULTURA POP 1 | M99: ELIANE COSTA DOS SANTOS | N99: EDITOR CONTEUDO WEB II
A100: =IF(LEN(D100)>1,D100,E100)&F100&H100&G100 -> 11261284739EG x Sambodromo4606820h | B100: =IF(LEN(D100)>1,D100,E100)&F100&H100 -> 11261284739EG x Sambodromo46068 | C100: MARCOS VINICIUS | E100: 11261284739 | F100: EG x Sambodromo | G100: 20h | H100: =IF(LEFT(I100,1)="1",46068,IF(LEFT(I100,1)="2",46069,IF(LEFT(I100,1)="3",46070,46074))) -> 46068 | I100: 1 - Primeiro dia | J100: =IF(LEN(A100&B100)<2,"Não Utilizou",IF((IFERROR(IFERROR(VLOOKUP(A100,Agendamento!A:C,3,0),VLOOKUP(B100,Agendamento!B:C,2,0)&"B"),"Encaixe"))="Agendado","Agend_OK",IF((IFERROR(IFERROR(VLOOKUP(A100,Agendamento!A:C,3,0),VLOOKUP(B100,Agendamento!B:C,2,0)&"B"),"Encaixe"))="AgendadoB","Agend_NOK",IF((IFERROR(IFERROR(VLOOKUP(A100,Agendamento!A:C,3,0),VLOOKUP(B100,Agendamento!B:C,2,0)&"B"),"Encaixe"))="Encaixe","Encaixe","Não Utilizou")))) -> Agend_NOK | K100: =IFERROR(VLOOKUP(L100,'Base Colaboradores'!C:F,4,0),"PRESTADOR DE SERVIÇOS") -> PRESTADOR DE SERVIÇOS | L100: Gran Coffee | M100: Prestador | N100: Prestador
...

Sheet Base Colaboradores
A1: Matricula | B1: Nome Funcionário | C1: Departamento | D1: Gestor Imediato | E1: Cargo | F1: N1
A2: 51682 | B2: AARAO IRVING MANHAES MARINS | C2: 3D E NOVAS TECNOLOGIAS | D2: RUDA PIM FONSECA | E2: ESPEC TECNOLOGIA INOVACAO I | F2: TECNOLOGIA
A3: 92718 | B3: ABEL VERONICO DA SILVA NETO | C3: PROGRAMAS TV GLOBO E FORMATOS | D3: CARLOS AFONSO GONÇALVES GARSCHAGEN | E3: COMENTARISTA ESPECIAL I | F3: ESPORTE
A4: 4093 | B4: ABIATAR ARRUDA | C4: SUPERVISAO IMAGEM SP | D4: THIAGO CAPELLE FERREIRA | E4: REPORTER CINEMATOGRAFICO III | F4: JORNALISMO
A5: 89911 | B5: ABNER DA SILVA ANDRADE | C5: DESENVOLVIMENTO GLOBOADS OPERACAO E RETENCAO | D5: CARLOS ALEXANDRE PAPANI FERREIRA | E5: DESENVOLVEDOR I | F5: TECNOLOGIA
A6: 13222 | B6: ABRAAO ASSUNCAO CRUZ | C6: SUPERVISAO IMAGEM SP | D6: THIAGO CAPELLE FERREIRA | E6: REPORTER CINEMATOGRAFICO MOTOLINK II | F6: JORNALISMO
A7: 89255 | B7: ACACIA FIDELIS DE FREITAS | C7: MG4 | D7: MARCELO CARDOSO DE ALMEIDA | E7: TEC CAPTACAO SOM I | F7: TECNOLOGIA
A8: 27592 | B8: ACCACIO MAGALHAES FERNANDES | C8: DESIGN ESPORTE JORNALISMO SP REGIONAIS | D8: RODOLPHO BARCELLOS XAVIER FILHO | E8: PRODUTOR DESIGN E EFEITOS VISUAIS II | F8: TECNOLOGIA
A9: 91607 | B9: ACELINO SERGENIS MAURIENSE DA SILVA JUNIOR | C9: CENTRO DE PRODUCAO DE REALITIES | D9: PAULO HENRIQUE DE ALBUQUERQUE MEIRA | E9: TEC SISTEMAS AUDIOVISUAIS II | F9: TECNOLOGIA
A10: 80882 | B10: ACIRLENE FREITAS | C10: TECNOLOGIA POS PRODUCAO E DESIGN | D10: CAROLINA YOSHICO JI | E10: TEC SISTEMAS AUDIOVISUAIS I | F10: TECNOLOGIA
A11: 63024 | B11: ADAILTON BERNARDES DE ARAUJO | C11: POS PRODUCAO EG - SONORIZACAO | D11: JOAO ALFREDO CURVELLO DA SILVEIRA | E11: SONOPLASTA II | F11: TECNOLOGIA
A12: 56021 | B12: ADAILTON DOS SANTOS SOARES | C12: OPERACAO NOITE | D12: CARLOS ALEXANDRE REBELO | E12: MAQUINISTA | F12: FINANCAS JURIDICO E INFRAESTRUTURA
A13: 88384 | B13: ADAILTON RIBEIRO ANDRE | C13: OPERACAO NOITE | D13: CARLOS ALEXANDRE REBELO | E13: MONTADOR I | F13: FINANCAS JURIDICO E INFRAESTRUTURA
... A1139: 77830 | B1139: ANDRE FERNANDES MARTINS DA SILVEIRA | C1139: REDACAO ESPORTES SP | D1139: CAUE DE CASTRO DIAS | E1139: ASSIST ADMINISTRATIVO II | F1139: ESPORTE
A1140: 341 | B1140: ANDRE FERRAZ SADDY | C1140: CB-DIRETORIA GERAL | E1140: DIRETOR GERAL CB | F1140: -
A1141: 13307 | B1141: ANDRE FERREIRA ALVES | C1141: IMAGEM SP | D1141: WILLIANS RODRIGUES DIAS | E1141: OPER CAMERA II | F1141: TECNOLOGIA
A1142: 90899 | B1142: ANDRE FERREIRA DE FREITAS ALVES PELLEGRINO | C1142: DRAMA E FILMES | D1142: SUELY WELLER | E1142: ANL CONTEUDO II | F1142: PRODUTOS DIGITAIS
A1143: 69066 | B1143: ANDRE FILIPE SILVA CARVALHO | C1143: PLATAFORMA DE PRODUCAO BSB | D1143: HEGLY LEMOS CAVALCANTE | E1143: ANL PLATAFORMA PRODUCAO I | F1143: TECNOLOGIA
A1144: 36921 | B1144: ANDRE FORMOSO DA SILVA | C1144: IMAGEM JB | D1144: JEAN CARLO GOULART ALVES | E1144: OPER CAMERA I | F1144: TECNOLOGIA
A1145: 87503 | B1145: ANDRE FREHSE RIBAS | C1145: SUPERVISAO REDACAO ESPORTE BH I | D1145: MARCELO TULIO MENDONCA SILVA | E1145: PRODUTOR REPORTAGEM I | F1145: ESPORTE
A1146: 90450 | B1146: ANDRE GUSTAVO DE ANDRADE GALLINDO | C1146: REPORTAGEM ESPORTE RJ | D1146: CAROLINA ALVARENGA ELUSTONDO | E1146: REPORTER ESPECIAL II | F1146: ESPORTE
A1147: 57803 | B1147: ANDRE LEITE FRANCISCO | C1147: PRODUCAO ARTE E DESIGN | D1147: TATIANA MANSO CASTELLO BRANCO | E1147: PRODUTOR ARTE ASSISTENTE IV | F1147: ESTUDIOS GLOBO
A1148: 79307 | B1148: ANDRE LEON SANTANA SOBREIRA | C1148: DESIGN REC | D1148: EDUARDO FELIPE DE MENEZES NETO | E1148: DESIGNER I | F1148: TECNOLOGIA
A1149: 67516 | B1149: ANDRE LEONARDO CORREA LEITAO | C1149: DESENVOLVIMENTO GE APP E SDE | D1149: VIVIEN ELAINE PARENTE TAVARES | E1149: COORD DESENVOLVIMENTO PRODUTOS | F1149: TECNOLOGIA
A1150: 85893 | B1150: ANDRE LEONARDO DE MATOS DA SILVEIRA | C1150: CI E CC | D1150: DIOGO MATHIAS SANTANA DA SILVA | E1150: ASSIST OPERACOES AUDIOVISUAIS I | F1150: TECNOLOGIA
A1151: 2831 | B1151: ANDRE LIMA E SILVA | C1151: CINEGRAFIA BRASILIA | D1151: MARCONE SEVERINO PRYSTHON PORTO PAIVA | E1151: REPORTER CINEMATOGRAFICO III | F1151: JORNALISMO
A1152: 80735 | B1152: ANDRE LINS NUNES | C1152: NEGOCIOS I | D1152: GUSTAVO LERNER | E1152: EXECUTIVO NEGOCIOS II | F1152: NEGOCIOS INTEGRADOS EM PUBLICIDADE
... A9948: 37362 | B9948: MARCELO SANTOS WANCE DE SOUZA | C9948: PRODUTOS E EXPERIENCIA | D9948: RAYMUNDO COSTA PINTO BARROS | E9948: DIR PRODUTOS & EXPERIENCIA | F9948: TECNOLOGIA
A9949: 212 | B9949: MARCELO SCALZO | C9949: NBCU-EXECUTIVO GERAL | E9949: DIR GERAL NBCU BRASIL | F9949: -
A9950: 51285 | B9950: MARCELO SILVA RIBEIRO | C9950: OPERACAO NOITE | D9950: CARLOS ALEXANDRE REBELO | E9950: MONTADOR II | F9950: FINANCAS JURIDICO E INFRAESTRUTURA
A9951: 85260 | B9951: MARCELO SINEIRO LOUREIRO | C9951: SOLUCOES DE COLABORACAO | D9951: EDUARDO LOUZANE PAVAN | E9951: ANL OPERACOES TECNOLOGIA III | F9951: TECNOLOGIA
A9952: 583 | B9952: MARCELO SOARES NEGRI CONTURSI | C9952: BACKSTAGE EXPERIENCIA DE DESENVOLVIMENTO | D9952: CARLOS EUGENIO RODRIGUES GUSMAO | E9952: GER DESENVOLVIMENTO PLATAFORMAS DIGITAIS | F9952: TECNOLOGIA
A9953: 85196 | B9953: MARCELO TIAGO FUCHER MELLO | C9953: PRODUCAO ARTE E DESIGN | D9953: TATIANA MANSO CASTELLO BRANCO | E9953: PRODUTOR ARTE ASSISTENTE IV | F9953: ESTUDIOS GLOBO
A9954: 86140 | B9954: MARCELO TOBIAS DOS SANTOS DA COSTA | C9954: SUPERVISAO EDITORIAS BRASILIA 02 03 | D9954: VERONICA MORENA DUTRA PINHEIRO | E9954: PRODUTOR REPORTAGEM I | F9954: JORNALISMO
A9955: 80919 | B9955: MARCELO TOMIELLO ZORZI | C9955: DEVOPS E SRE ENTREGAR | D9955: ROBSON SOARES NUNES JUNIOR | E9955: ESPEC DEVOPS II | F9955: TECNOLOGIA
A9956: 2482 | B9956: MARCELO TULIO MENDONCA SILVA | C9956: SUPERVISAO REDACAO ESPORTE BH I | D9956: CAMILA VALADARES GERTRUDES PEREIRA | E9956: EDITOR SUP EXEC WEB | F9956: ESPORTE
A9957: 53940 | B9957: MARCELO VALE FONTANA | C9957: PLATAFORMAS DE CAPTACAO E PRODUCAO | D9957: FABIO VIVIANI FERRAZ | E9957: GER SOLUCOES MIDIAS | F9957: TECNOLOGIA
A9958: 71430 | B9958: MARCELO VEIGA PENNA | C9958: DESIGN JORNALISMO E ESPORTE RJ | D9958: ANDREA ASCOLI ALVES DE LIMA | E9958: DESIGNER II | F9958: TECNOLOGIA
A9959: 2948 | B9959: MARCELO VICTOR MACIEL | C9959: PARCERIAS DE SUSTENTACAO SP E REG - BSB | D9959: GUILHERME MORAIS BERNARDES | E9959: PRODUCT OWNER III | F9959: TECNOLOGIA
A9960: 69091 | B9960: MARCELO VIEIRA PEREIRA | C9960: COMPRAS PARA ARTE - DRAMATURGIA | D9960: DANIELLE FRAUCHES THURLER PIMENTEL | E9960: ASSIST COMPRAS I | F9960: FINANCAS JURIDICO E INFRAESTRUTURA
A9961: 77180 | B9961: MARCELO VIGANO DE PINHO | C9961: DESENVOLVIMENTO - SALESFORCE VENDAS B2B I | D9961: GEORGE KISSMANN | E9961: ANL FUNCIONAL II | F9961: TECNOLOGIA
... A15484: 80779 | B15484: ZUZILEISON OLIVEIRA MOREIRA | C15484: SUPERVISAO REPORTAGEM BELO HORIZONTE 01 | D15484: GISELLI TEIXEIRA DA SILVA VIEIRA | E15484: REPORTER II | F15484: JORNALISMO

Sheet ANÁLISE CAPACIDADE
B4: SITE | C4: ESCOPO | D4: HORÁRIO | E4: DATA | F4: CAPACIDADE | G4: PLANEJADO | H4: REAL
B5: EG | C5: VAI | D5: 0.5 | E5: 46068 | F5: 15 | G5: 9 | H5: 2
B6: EG | C6: VAI | D6: 0.66666667 | E6: 46068 | F6: 15 | G6: 4 | H6: 15
B7: EG | C7: VAI | D7: 0.70833333 | E7: 46068 | F7: 75 | G7: 59 | H7: 35
B8: EG | C8: VAI | D8: 0.75 | E8: 46068 | F8: 53 | G8: 33 | H8: 25
B9: EG | C9: VAI | D9: 0.79166667 | E9: 46068 | F9: 45 | G9: 16 | H9: 16
B10: EG | C10: VAI | D10: 0.83333333 | E10: 46068 | F10: 57 | G10: 21 | H10: 12
B11: EG | C11: VAI | D11: 0.875 | E11: 46068 | F11: 45 | G11: 7 | H11: 5
B12: EG | C12: VAI | D12: 0.91666667 | E12: 46068 | F12: 45 | G12: 5 | H12: 10
B13: EG | C13: VAI | D13: 0.95833333 | E13: 46068 | F13: 4 | G13: 1 | H13: 2
B14: EG | C14: VEM | D14: 1 | E14: 46068 | F14: 64 | G14: 13 | H14: 12
B15: EG | C15: VEM | D15: 1.0416667 | E15: 46068 | F15: 64 | G15: 10 | H15: 3
B16: EG | C16: VEM | D16: 1.0833333 | E16: 46068 | F16: 53 | G16: 15 | H16: 13
... B22: EG | C22: VEM | D22: 1.3333333 | E22: 46068 | F22: 19 | G22: 6 | H22: 0
B30: SITE | C30: ESCOPO | D30: HORÁRIO | E30: DATA | F30: CAPACIDADE | G30: PLANEJADO | H30: REAL
B31: JB | C31: VAI | D31: 0.70833333 | E31: 46068 | F31: 4 | G31: 4 | H31: 1
B32: JB | C32: VAI | D32: 0.75 | E32: 46068 | F32: 60 | G32: 51 | H32: 24
B33: JB | C33: VAI | D33: 0.79166667 | E33: 46068 | F33: 42 | G33: 19 | H33: 21
B34: JB | C34: VAI | D34: 0.83333333 | E34: 46068 | F34: 45 | G34: 8 | H34: 6
B35: JB | C35: VAI | D35: 0.875 | E35: 46068 | F35: 23 | G35: 4 | H35: 2
B36: JB | C36: VAI | D36: 0.91666667 | E36: 46068 | F36: 4 | G36: 2 | H36: 1
B37: JB | C37: VAI | D37: 0.95833333 | E37: 46068 | F37: 4 | G37: 0 | H37: 2
B38: JB | C38: VEM | D38: 1 | E38: 46068 | F38: 4 | G38: 4 | H38: 2
B39: JB | C39: VEM | D39: 1.0416667 | E39: 46068 | F39: 45 | G39: 7 | H39: 6
B40: JB | C40: VEM | D40: 1.0833333 | E40: 46068 | F40: 23 | G40: 15 | H40: 6
B41: JB | C41: VEM | D41: 1.125 | E41: 46068 | F41: 19 | G41: 11 | H41: 5
B42: JB | C42: VEM | D42: 1.1666667 | E42: 46068 | F42: 19 | G42: 13 | H42: 6
... B46: JB | C46: VEM | D46: 1.3333333 | E46: 46068 | F46: 0 | G46: 0 | H46: 0
B50: SITE | C50: ESCOPO | D50: HORÁRIO | E50: DATA | F50: CAPACIDADE | G50: PLANEJADO | H50: REAL
B51: EG | C51: VAI | D51: 0.66666667 | E51: 46069 | F51: 15 | G51: 4 | H51: 4
B52: EG | C52: VAI | D52: 0.70833333 | E52: 46069 | F52: 66 | G52: 60 | H52: 40
B53: EG | C53: VAI | D53: 0.75 | E53: 46069 | F53: 32 | G53: 53 | H53: 15
B54: EG | C54: VAI | D54: 0.79166667 | E54: 46069 | F54: 16 | G54: 45 | H54: 14
B55: EG | C55: VAI | D55: 0.83333333 | E55: 46069 | F55: 21 | G55: 57 | H55: 13
B56: EG | C56: VAI | D56: 0.875 | E56: 46069 | F56: 8 | G56: 45 | H56: 13
B57: EG | C57: VAI | D57: 0.91666667 | E57: 46069 | F57: 6 | G57: 45 | H57: 25
B58: EG | C58: VAI | D58: 0.95833333 | E58: 46069 | F58: 1 | G58: 4 | H58: 4
B59: EG | C59: VEM | D59: 1 | E59: 46069 | F59: 13 | G59: 64 | H59: 4
B60: EG | C60: VEM | D60: 1.0416667 | E60: 46069 | F60: 9 | G60: 64 | H60: 11
B61: EG | C61: VEM | D61: 1.0833333 | E61: 46069 | F61: 16 | G61: 53 | H61: 10
B62: EG | C62: VEM | D62: 1.125 | E62: 46069 | F62: 10 | G62: 60 | H62: 3
... B67: EG | C67: VEM | D67: 1.3333333 | E67: 46069 | F67: 7 | G67: 19 | H67: 0
B71: SITE | C71: ESCOPO | D71: HORÁRIO | E71: DATA | F71: CAPACIDADE | G71: PLANEJADO | H71: REAL
B72: JB | C72: VAI | D72: 0.70833333 | E72: 46069 | F72: 0 | G72: 0 | H72: 0
B73: JB | C73: VAI | D73: 0.75 | E73: 46069 | F73: 60 | G73: 51 | H73: 12
B74: JB | C74: VAI | D74: 0.79166667 | E74: 46069 | F74: 42 | G74: 18 | H74: 23
B75: JB | C75: VAI | D75: 0.83333333 | E75: 46069 | F75: 45 | G75: 8 | H75: 10
B76: JB | C76: VAI | D76: 0.875 | E76: 46069 | F76: 23 | G76: 4 | H76: 5
B77: JB | C77: VAI | D77: 0.91666667 | E77: 46069 | F77: 4 | G77: 2 | H77: 1
B78: JB | C78: VAI | D78: 0.95833333 | E78: 46069 | F78: 4 | G78: 0 | H78: 1
B79: JB | C79: VEM | D79: 1 | E79: 46069 | F79: 4 | G79: 3 | H79: 5
B80: JB | C80: VEM | D80: 1.0416667 | E80: 46069 | F80: 45 | G80: 7 | H80: 5
B81: JB | C81: VEM | D81: 1.0833333 | E81: 46069 | F81: 23 | G81: 16 | H81: 9
B82: JB | C82: VEM | D82: 1.125 | E82: 46069 | F82: 19 | G82: 12 | H82: 3
B83: JB | C83: VEM | D83: 1.1666667 | E83: 46069 | F83: 19 | G83: 14 | H83: 5
... B87: JB | C87: VEM | D87: 1.3333333 | E87: 46069 | F87: 0 | G87: 0 | H87: 0
B93: SITE | C93: ESCOPO | D93: HORÁRIO | E93: DATA | F93: CAPACIDADE | G93: PLANEJADO | H93: REAL
B94: EG | C94: VAI | D94: 0.66666667 | E94: 46070 | F94: 15 | G94: 4 | H94: 4
B95: EG | C95: VAI | D95: 0.70833333 | E95: 46070 | F95: 66 | G95: 58 | H95: 25
B96: EG | C96: VAI | D96: 0.75 | E96: 46070 | F96: 32 | G96: 33 | H96: 26
B97: EG | C97: VAI | D97: 0.79166667 | E97: 46070 | F97: 16 | G97: 15 | H97: 16
B98: EG | C98: VAI | D98: 0.83333333 | E98: 46070 | F98: 21 | G98: 21 | H98: 11
B99: EG | C99: VAI | D99: 0.875 | E99: 46070 | F99: 8 | G99: 7 | H99: 5
B100: EG | C100: VAI | D100: 0.91666667 | E100: 46070 | F100: 6 | G100: 5 | H100: 11
B101: EG | C101: VAI | D101: 0.95833333 | E101: 46070 | F101: 1 | G101: 1 | H101: 2
B102: EG | C102: VEM | D102: 1 | E102: 46070 | F102: 13 | G102: 13 | H102: 10
B103: EG | C103: VEM | D103: 1.0416667 | E103: 46070 | F103: 9 | G103: 9 | H103: 3
B104: EG | C104: VEM | D104: 1.0833333 | E104: 46070 | F104: 16 | G104: 13 | H104: 9
B105: EG | C105: VEM | D105: 1.125 | E105: 46070 | F105: 10 | G105: 11 | H105: 3
... B110: EG | C110: VEM | D110: 1.3333333 | E110: 46070 | F110: 7 | G110: 6 | H110: 0
B114: SITE | C114: ESCOPO | D114: HORÁRIO | E114: DATA | F114: CAPACIDADE | G114: PLANEJADO | H114: REAL
B115: JB | C115: VAI | D115: 0.70833333 | E115: 46070 | F115: 0 | G115: 0 | H115: 0
B116: JB | C116: VAI | D116: 0.75 | E116: 46070 | F116: 60 | G116: 51 | H116: 12
B117: JB | C117: VAI | D117: 0.79166667 | E117: 46070 | F117: 42 | G117: 20 | H117: 15
B118: JB | C118: VAI | D118: 0.83333333 | E118: 46070 | F118: 45 | G118: 9 | H118: 14
B119: JB | C119: VAI | D119: 0.875 | E119: 46070 | F119: 23 | G119: 5 | H119: 5
B120: JB | C120: VAI | D120: 0.91666667 | E120: 46070 | F120: 4 | G120: 2 | H120: 1
B121: JB | C121: VAI | D121: 0.95833333 | E121: 46070 | F121: 4 | G121: 0 | H121: 2
B122: JB | C122: VEM | D122: 1 | E122: 46070 | F122: 4 | G122: 4 | H122: 2
B123: JB | C123: VEM | D123: 1.0416667 | E123: 46070 | F123: 45 | G123: 6 | H123: 5
B124: JB | C124: VEM | D124: 1.0833333 | E124: 46070 | F124: 23 | G124: 16 | H124: 11
B125: JB | C125: VEM | D125: 1.125 | E125: 46070 | F125: 19 | G125: 12 | H125: 3
B126: JB | C126: VEM | D126: 1.1666667 | E126: 46070 | F126: 19 | G126: 14 | H126: 7
... B130: JB | C130: VEM | D130: 1.3333333 | E130: 46070 | F130: 0 | G130: 0 | H130: 0
B134: SITE | C134: ESCOPO | D134: HORÁRIO | E134: DATA | F134: CAPACIDADE | G134: PLANEJADO | H134: REAL
B135: EG | C135: VAI | D135: 0.66666667 | E135: 46074 | F135: 15 | G135: 4 | H135: 15
B136: EG | C136: VAI | D136: 0.70833333 | E136: 46074 | F136: 66 | G136: 65 | H136: 14
B137: EG | C137: VAI | D137: 0.75 | E137: 46074 | F137: 32 | G137: 29 | H137: 14
B138: EG | C138: VAI | D138: 0.79166667 | E138: 46074 | F138: 16 | G138: 14 | H138: 7
B139: EG | C139: VAI | D139: 0.83333333 | E139: 46074 | F139: 21 | G139: 20 | H139: 13
B140: EG | C140: VAI | D140: 0.875 | E140: 46074 | F140: 8 | G140: 8 | H140: 7
B141: EG | C141: VAI | D141: 0.91666667 | E141: 46074 | F141: 6 | G141: 4 | H141: 9
B142: EG | C142: VAI | D142: 0.95833333 | E142: 46074 | F142: 1 | G142: 1 | H142: 6
B143: EG | C143: VEM | D143: 1 | E143: 46074 | F143: 13 | G143: 13 | H143: 6
B144: EG | C144: VEM | D144: 1.0416667 | E144: 46074 | F144: 9 | G144: 7 | H144: 4
B145: EG | C145: VEM | D145: 1.0833333 | E145: 46074 | F145: 16 | G145: 13 | H145: 3
B146: EG | C146: VEM | D146: 1.125 | E146: 46074 | F146: 10 | G146: 12 | H146: 6
... B151: EG | C151: VEM | D151: 1.3333333 | E151: 46074 | F151: 7 | G151: 9 | H151: 24
B154: SITE | C154: ESCOPO | D154: HORÁRIO | E154: DATA | F154: CAPACIDADE | G154: PLANEJADO | H154: REAL
B155: JB | C155: VAI | D155: 0.70833333 | E155: 46074 | F155: 0 | G155: 0 | H155: 0
...
